Workbook
Name Sel_Month: Dashboard!$D$2
Name Unique_Months: OFFSET(Conf!$D$1, 0, 0, COUNTA(Conf!$D:$D), 1)

Sheet Dashboard
A1: Spending Report | G1: Budgets | L1: Custom Categories
C2: Month | D2: 45413 | G2: Custom Category | H2: Frequency | I2: Amount | J2: Monthly | L2: Name | M2: Amount | N2: Custom Category
G3: Home Insurance | H3: Monthly | I3: 428 | J3: =Budgets[[#This Row],[Amount]]*_xlfn.XLOOKUP(Budgets[[#This Row],[Frequency]],Frequency[Frequency],Frequency[Factor],1,0) -> 428 | L3: BELAIR INS/ASS | M3: <100 | N3: Insurance,Home
A4: Row Labels | B4: 6M Average | C4: Budget | D4: Montly Spending | E4: Used | G4: Food and Drink, Restaurants | H4: Weekly | I4: 200 | J4: =Budgets[[#This Row],[Amount]]*_xlfn.XLOOKUP(Budgets[[#This Row],[Frequency]],Frequency[Frequency],Frequency[Factor],1,0) -> 800 | L4: BELAIR INS/ASS | M4: >100 | N4: Insurance,Car
A5: Bank Fees | B5: 2.5077778 | C5: 2.5077778 | D5: {=_xlfn.IFS(A5="","",A5="Grand Total",SUM(D$4:D4),TRUE,IF(COUNTIF(Transactions[Custom Category],Dashboard!A5)>0,SUMIFS(Transactions[Amount],Transactions[Custom Category],Dashboard!A5,Transactions[Month],Sel_Month),SUMIFS(Transactions[Amount],Transactions[Name],Dashboard!A5,Transactions[Month],Sel_Month)))} -> 5.1 | E5: =IF(C5="","",IF(C5=0,0,1-((C5-D5)/C5))) -> 2.033673 | L5: NEW YORK TIMES | N5: Subscriptions
A6: Business,Advertising | B6: 6.21 | C6: 6.21 | D6: {=_xlfn.IFS(A6="","",A6="Grand Total",SUM(D$4:D5),TRUE,IF(COUNTIF(Transactions[Custom Category],Dashboard!A6)>0,SUMIFS(Transactions[Amount],Transactions[Custom Category],Dashboard!A6,Transactions[Month],Sel_Month),SUMIFS(Transactions[Amount],Transactions[Name],Dashboard!A6,Transactions[Month],Sel_Month)))} -> 12.42 | E6: =IF(C6="","",IF(C6=0,0,1-((C6-D6)/C6))) -> 2 | L6: McDonald | N6: Food and Drink, Restaurants
A7: Discretionary | B7: 16.39 | C7: 16.39 | D7: {=_xlfn.IFS(A7="","",A7="Grand Total",SUM(D$4:D6),TRUE,IF(COUNTIF(Transactions[Custom Category],Dashboard!A7)>0,SUMIFS(Transactions[Amount],Transactions[Custom Category],Dashboard!A7,Transactions[Month],Sel_Month),SUMIFS(Transactions[Amount],Transactions[Name],Dashboard!A7,Transactions[Month],Sel_Month)))} -> 0 | E7: =IF(C7="","",IF(C7=0,0,1-((C7-D7)/C7))) -> 0 | L7: e-Transfer sent Manuel | N7: Transfer,Internal
A8: Food and Drink, Restaurants | B8: 414.67286 | C8: 800 | D8: {=_xlfn.IFS(A8="","",A8="Grand Total",SUM(D$4:D7),TRUE,IF(COUNTIF(Transactions[Custom Category],Dashboard!A8)>0,SUMIFS(Transactions[Amount],Transactions[Custom Category],Dashboard!A8,Transactions[Month],Sel_Month),SUMIFS(Transactions[Amount],Transactions[Name],Dashboard!A8,Transactions[Month],Sel_Month)))} -> 0 | E8: =IF(C8="","",IF(C8=0,0,1-((C8-D8)/C8))) -> 0 | L8: e-Transfer sent Paula | N8: Transfer,Internal
A9: Groceries | B9: 248.36 | C9: 248.36 | D9: {=_xlfn.IFS(A9="","",A9="Grand Total",SUM(D$4:D8),TRUE,IF(COUNTIF(Transactions[Custom Category],Dashboard!A9)>0,SUMIFS(Transactions[Amount],Transactions[Custom Category],Dashboard!A9,Transactions[Month],Sel_Month),SUMIFS(Transactions[Amount],Transactions[Name],Dashboard!A9,Transactions[Month],Sel_Month)))} -> 0 | E9: =IF(C9="","",IF(C9=0,0,1-((C9-D9)/C9))) -> 0 | L9: Subscription | N9: Subscriptions
A10: Home,Supplies | B10: 128.65625 | C10: 128.65625 | D10: {=_xlfn.IFS(A10="","",A10="Grand Total",SUM(D$4:D9),TRUE,IF(COUNTIF(Transactions[Custom Category],Dashboard!A10)>0,SUMIFS(Transactions[Amount],Transactions[Custom Category],Dashboard!A10,Transactions[Month],Sel_Month),SUMIFS(Transactions[Amount],Transactions[Name],Dashboard!A10,Transactions[Month],Sel_Month)))} -> 98.41 | E10: =IF(C10="","",IF(C10=0,0,1-((C10-D10)/C10))) -> 0.76490649 | L10: SPL | N10: Loans,Car
A11: Income,Interest | B11: -0.01 | C11: -0.01 | D11: {=_xlfn.IFS(A11="","",A11="Grand Total",SUM(D$4:D10),TRUE,IF(COUNTIF(Transactions[Custom Category],Dashboard!A11)>0,SUMIFS(Transactions[Amount],Transactions[Custom Category],Dashboard!A11,Transactions[Month],Sel_Month),SUMIFS(Transactions[Amount],Transactions[Name],Dashboard!A11,Transactions[Month],Sel_Month)))} -> 0 | E11: =IF(C11="","",IF(C11=0,0,1-((C11-D11)/C11))) -> 0 | L11: Service, Utilities, Electric | N11: Utilities,Electric
A12: Income,Repayment | B12: -3209.0714 | C12: -3209.0714 | D12: {=_xlfn.IFS(A12="","",A12="Grand Total",SUM(D$4:D11),TRUE,IF(COUNTIF(Transactions[Custom Category],Dashboard!A12)>0,SUMIFS(Transactions[Amount],Transactions[Custom Category],Dashboard!A12,Transactions[Month],Sel_Month),SUMIFS(Transactions[Amount],Transactions[Name],Dashboard!A12,Transactions[Month],Sel_Month)))} -> -3266 | E12: =IF(C12="","",IF(C12=0,0,1-((C12-D12)/C12))) -> 1.0177399 | L12: Online Banking foreign exchange | N12: Income,Salary
A13: Income,Salary | B13: -18125.097 | C13: -18125.097 | D13: {=_xlfn.IFS(A13="","",A13="Grand Total",SUM(D$4:D12),TRUE,IF(COUNTIF(Transactions[Custom Category],Dashboard!A13)>0,SUMIFS(Transactions[Amount],Transactions[Custom Category],Dashboard!A13,Transactions[Month],Sel_Month),SUMIFS(Transactions[Amount],Transactions[Name],Dashboard!A13,Transactions[Month],Sel_Month)))} -> -22459.99 | E13: =IF(C13="","",IF(C13=0,0,1-((C13-D13)/C13))) -> 1.2391652 | L13: Bank Fees, Overdraft | N13: Bank Fees
A14: Income,Tax Refund | B14: -3713.1 | C14: -3713.1 | D14: {=_xlfn.IFS(A14="","",A14="Grand Total",SUM(D$4:D13),TRUE,IF(COUNTIF(Transactions[Custom Category],Dashboard!A14)>0,SUMIFS(Transactions[Amount],Transactions[Custom Category],Dashboard!A14,Transactions[Month],Sel_Month),SUMIFS(Transactions[Amount],Transactions[Name],Dashboard!A14,Transactions[Month],Sel_Month)))} -> -3713.1 | E14: =IF(C14="","",IF(C14=0,0,1-((C14-D14)/C14))) -> 1 | L14: CITY OF TORONTO | N14: Utilities,Water
A15: Insurance,Car | B15: 432.996 | C15: 432.996 | D15: {=_xlfn.IFS(A15="","",A15="Grand Total",SUM(D$4:D14),TRUE,IF(COUNTIF(Transactions[Custom Category],Dashboard!A15)>0,SUMIFS(Transactions[Amount],Transactions[Custom Category],Dashboard!A15,Transactions[Month],Sel_Month),SUMIFS(Transactions[Amount],Transactions[Name],Dashboard!A15,Transactions[Month],Sel_Month)))} -> 438.75 | E15: =IF(C15="","",IF(C15=0,0,1-((C15-D15)/C15))) -> 1.0132888 | L15: Interest, Interest Earned | N15: Income,Interest
A16: Insurance,Home | B16: 57.905 | C16: 57.905 | D16: {=_xlfn.IFS(A16="","",A16="Grand Total",SUM(D$4:D15),TRUE,IF(COUNTIF(Transactions[Custom Category],Dashboard!A16)>0,SUMIFS(Transactions[Amount],Transactions[Custom Category],Dashboard!A16,Transactions[Month],Sel_Month),SUMIFS(Transactions[Amount],Transactions[Name],Dashboard!A16,Transactions[Month],Sel_Month)))} -> 56.05 | E16: =IF(C16="","",IF(C16=0,0,1-((C16-D16)/C16))) -> 0.96796477 | L16: Payment | N16: Transfer,Internal
... A29: Utilities,Electric | B29: 139.88333 | C29: 139.88333 | D29: {=_xlfn.IFS(A29="","",A29="Grand Total",SUM(D$4:D28),TRUE,IF(COUNTIF(Transactions[Custom Category],Dashboard!A29)>0,SUMIFS(Transactions[Amount],Transactions[Custom Category],Dashboard!A29,Transactions[Month],Sel_Month),SUMIFS(Transactions[Amount],Transactions[Name],Dashboard!A29,Transactions[Month],Sel_Month)))} -> 153.32 | E29: =IF(C29="","",IF(C29=0,0,1-((C29-D29)/C29))) -> 1.0960562 | L29: Autodeposit PAULA ANDREA AMARILES | N29: Transfer,Internal
A30: Utilities,Gas | B30: 153.08333 | C30: 153.08333 | D30: {=_xlfn.IFS(A30="","",A30="Grand Total",SUM(D$4:D29),TRUE,IF(COUNTIF(Transactions[Custom Category],Dashboard!A30)>0,SUMIFS(Transactions[Amount],Transactions[Custom Category],Dashboard!A30,Transactions[Month],Sel_Month),SUMIFS(Transactions[Amount],Transactions[Name],Dashboard!A30,Transactions[Month],Sel_Month)))} -> 153.29 | E30: =IF(C30="","",IF(C30=0,0,1-((C30-D30)/C30))) -> 1.00135 | L30: Lorena | M30: <0 | N30: Income,Repayment
A31: Utilities,Water | B31: 489.91 | C31: 489.91 | D31: {=_xlfn.IFS(A31="","",A31="Grand Total",SUM(D$4:D30),TRUE,IF(COUNTIF(Transactions[Custom Category],Dashboard!A31)>0,SUMIFS(Transactions[Amount],Transactions[Custom Category],Dashboard!A31,Transactions[Month],Sel_Month),SUMIFS(Transactions[Amount],Transactions[Name],Dashboard!A31,Transactions[Month],Sel_Month)))} -> 0 | E31: =IF(C31="","",IF(C31=0,0,1-((C31-D31)/C31))) -> 0 | L31: David Alexander | M31: <0 | N31: Income,Repayment
A32: Total | B32: 14532.99 | C32: 14532.99 | D32: {=_xlfn.IFS(A32="","",A32="Grand Total",SUM(D$4:D31),TRUE,IF(COUNTIF(Transactions[Custom Category],Dashboard!A32)>0,SUMIFS(Transactions[Amount],Transactions[Custom Category],Dashboard!A32,Transactions[Month],Sel_Month),SUMIFS(Transactions[Amount],Transactions[Name],Dashboard!A32,Transactions[Month],Sel_Month)))} -> 0 | E32: =IF(C32="","",IF(C32=0,0,1-((C32-D32)/C32))) -> 0 | L32: Ana Maria | M32: <0 | N32: Income,Repayment
D33: {=_xlfn.IFS(A33="","",A33="Grand Total",SUM(D$4:D32),TRUE,IF(COUNTIF(Transactions[Custom Category],Dashboard!A33)>0,SUMIFS(Transactions[Amount],Transactions[Custom Category],Dashboard!A33,Transactions[Month],Sel_Month),SUMIFS(Transactions[Amount],Transactions[Name],Dashboard!A33,Transactions[Month],Sel_Month)))} | E33: =IF(C33="","",IF(C33=0,0,1-((C33-D33)/C33))) | L33: Barian | M33: <0 | N33: Income,Repayment
D34: {=_xlfn.IFS(A34="","",A34="Grand Total",SUM(D$4:D33),TRUE,IF(COUNTIF(Transactions[Custom Category],Dashboard!A34)>0,SUMIFS(Transactions[Amount],Transactions[Custom Category],Dashboard!A34,Transactions[Month],Sel_Month),SUMIFS(Transactions[Amount],Transactions[Name],Dashboard!A34,Transactions[Month],Sel_Month)))} | E34: =IF(C34="","",IF(C34=0,0,1-((C34-D34)/C34))) | L34: Bridgeway | N34: Rent
D35: {=_xlfn.IFS(A35="","",A35="Grand Total",SUM(D$4:D34),TRUE,IF(COUNTIF(Transactions[Custom Category],Dashboard!A35)>0,SUMIFS(Transactions[Amount],Transactions[Custom Category],Dashboard!A35,Transactions[Month],Sel_Month),SUMIFS(Transactions[Amount],Transactions[Name],Dashboard!A35,Transactions[Month],Sel_Month)))} | E35: =IF(C35="","",IF(C35=0,0,1-((C35-D35)/C35)))
D36: {=_xlfn.IFS(A36="","",A36="Total",SUM(D$4:D35),TRUE,IF(COUNTIF(Transactions[Custom Category],Dashboard!A36)>0,SUMIFS(Transactions[Amount],Transactions[Custom Category],Dashboard!A36,Transactions[Month],Sel_Month),SUMIFS(Transactions[Amount],Transactions[Name],Dashboard!A36,Transactions[Month],Sel_Month)))} | E36: =IF(C36="","",IF(C36=0,0,1-((C36-D36)/C36)))
D37: {=_xlfn.IFS(A37="","",A37="Grand Total",SUM(D$4:D36),TRUE,IF(COUNTIF(Transactions[Custom Category],Dashboard!A37)>0,SUMIFS(Transactions[Amount],Transactions[Custom Category],Dashboard!A37,Transactions[Month],Sel_Month),SUMIFS(Transactions[Amount],Transactions[Name],Dashboard!A37,Transactions[Month],Sel_Month)))} | E37: =IF(C37="","",IF(C37=0,0,1-((C37-D37)/C37)))
D38: {=_xlfn.IFS(A38="","",A38="Grand Total",SUM(D$4:D37),TRUE,IF(COUNTIF(Transactions[Custom Category],Dashboard!A38)>0,SUMIFS(Transactions[Amount],Transactions[Custom Category],Dashboard!A38,Transactions[Month],Sel_Month),SUMIFS(Transactions[Amount],Transactions[Name],Dashboard!A38,Transactions[Month],Sel_Month)))} | E38: =IF(C38="","",IF(C38=0,0,1-((C38-D38)/C38)))
D39: {=_xlfn.IFS(A39="","",A39="Grand Total",SUM(D$4:D38),TRUE,IF(COUNTIF(Transactions[Custom Category],Dashboard!A39)>0,SUMIFS(Transactions[Amount],Transactions[Custom Category],Dashboard!A39,Transactions[Month],Sel_Month),SUMIFS(Transactions[Amount],Transactions[Name],Dashboard!A39,Transactions[Month],Sel_Month)))} | E39: =IF(C39="","",IF(C39=0,0,1-((C39-D39)/C39)))
D40: {=_xlfn.IFS(A40="","",A40="Grand Total",SUM(D$4:D39),TRUE,IF(COUNTIF(Transactions[Custom Category],Dashboard!A40)>0,SUMIFS(Transactions[Amount],Transactions[Custom Category],Dashboard!A40,Transactions[Month],Sel_Month),SUMIFS(Transactions[Amount],Transactions[Name],Dashboard!A40,Transactions[Month],Sel_Month)))} | E40: =IF(C40="","",IF(C40=0,0,1-((C40-D40)/C40)))
D41: {=_xlfn.IFS(A41="","",A41="Grand Total",SUM(D$4:D40),TRUE,IF(COUNTIF(Transactions[Custom Category],Dashboard!A41)>0,SUMIFS(Transactions[Amount],Transactions[Custom Category],Dashboard!A41,Transactions[Month],Sel_Month),SUMIFS(Transactions[Amount],Transactions[Name],Dashboard!A41,Transactions[Month],Sel_Month)))} | E41: =IF(C41="","",IF(C41=0,0,1-((C41-D41)/C41)))
D42: {=_xlfn.IFS(A42="","",A42="Grand Total",SUM(D$4:D41),TRUE,IF(COUNTIF(Transactions[Custom Category],Dashboard!A42)>0,SUMIFS(Transactions[Amount],Transactions[Custom Category],Dashboard!A42,Transactions[Month],Sel_Month),SUMIFS(Transactions[Amount],Transactions[Name],Dashboard!A42,Transactions[Month],Sel_Month)))} | E42: =IF(C42="","",IF(C42=0,0,1-((C42-D42)/C42)))
D43: {=_xlfn.IFS(A43="","",A43="Grand Total",SUM(D$4:D42),TRUE,IF(COUNTIF(Transactions[Custom Category],Dashboard!A43)>0,SUMIFS(Transactions[Amount],Transactions[Custom Category],Dashboard!A43,Transactions[Month],Sel_Month),SUMIFS(Transactions[Amount],Transactions[Name],Dashboard!A43,Transactions[Month],Sel_Month)))} | E43: =IF(C43="","",IF(C43=0,0,1-((C43-D43)/C43)))
D44: {=_xlfn.IFS(A44="","",A44="Grand Total",SUM(D$4:D43),TRUE,IF(COUNTIF(Transactions[Custom Category],Dashboard!A44)>0,SUMIFS(Transactions[Amount],Transactions[Custom Category],Dashboard!A44,Transactions[Month],Sel_Month),SUMIFS(Transactions[Amount],Transactions[Name],Dashboard!A44,Transactions[Month],Sel_Month)))} | E44: =IF(C44="","",IF(C44=0,0,1-((C44-D44)/C44)))
D45: {=_xlfn.IFS(A45="","",A45="Grand Total",SUM(D$4:D44),TRUE,IF(COUNTIF(Transactions[Custom Category],Dashboard!A45)>0,SUMIFS(Transactions[Amount],Transactions[Custom Category],Dashboard!A45,Transactions[Month],Sel_Month),SUMIFS(Transactions[Amount],Transactions[Name],Dashboard!A45,Transactions[Month],Sel_Month)))} | E45: =IF(C45="","",IF(C45=0,0,1-((C45-D45)/C45)))
D46: {=_xlfn.IFS(A46="","",A46="Grand Total",SUM(D$4:D45),TRUE,IF(COUNTIF(Transactions[Custom Category],Dashboard!A46)>0,SUMIFS(Transactions[Amount],Transactions[Custom Category],Dashboard!A46,Transactions[Month],Sel_Month),SUMIFS(Transactions[Amount],Transactions[Name],Dashboard!A46,Transactions[Month],Sel_Month)))} | E46: =IF(C46="","",IF(C46=0,0,1-((C46-D46)/C46)))
D47: {=_xlfn.IFS(A47="","",A47="Grand Total",SUM(D$4:D46),TRUE,IF(COUNTIF(Transactions[Custom Category],Dashboard!A47)>0,SUMIFS(Transactions[Amount],Transactions[Custom Category],Dashboard!A47,Transactions[Month],Sel_Month),SUMIFS(Transactions[Amount],Transactions[Name],Dashboard!A47,Transactions[Month],Sel_Month)))} | E47: =IF(C47="","",IF(C47=0,0,1-((C47-D47)/C47)))
D48: {=_xlfn.IFS(A48="","",A48="Grand Total",SUM(D$4:D47),TRUE,IF(COUNTIF(Transactions[Custom Category],Dashboard!A48)>0,SUMIFS(Transactions[Amount],Transactions[Custom Category],Dashboard!A48,Transactions[Month],Sel_Month),SUMIFS(Transactions[Amount],Transactions[Name],Dashboard!A48,Transactions[Month],Sel_Month)))} | E48: =IF(C48="","",IF(C48=0,0,1-((C48-D48)/C48)))
... D434: {=_xlfn.IFS(A434="","",A434="Grand Total",SUM(D$4:D433),TRUE,IF(COUNTIF(Transactions[Custom Category],Dashboard!A434)>0,SUMIFS(Transactions[Amount],Transactions[Custom Category],Dashboard!A434,Transactions[Month],Sel_Month),SUMIFS(Transactions[Amount],Transactions[Name],Dashboard!A434,Transactions[Month],Sel_Month)))} | E434: =IF(C434="","",IF(C434=0,0,1-((C434-D434)/C434)))
D435: {=_xlfn.IFS(A435="","",A435="Grand Total",SUM(D$4:D434),TRUE,IF(COUNTIF(Transactions[Custom Category],Dashboard!A435)>0,SUMIFS(Transactions[Amount],Transactions[Custom Category],Dashboard!A435,Transactions[Month],Sel_Month),SUMIFS(Transactions[Amount],Transactions[Name],Dashboard!A435,Transactions[Month],Sel_Month)))}

Sheet Accounts
A1: Institution Name | B1: Credential ID | C1: Next Cursor | D1: Balance | E1: Mask | F1: Name | G1: Plaid Account ID | H1: Subtype | I1: Type
A2: Scotiabank | B2: 12 | C2: CAESJWdCa0xiVlBvTjVjRXZuQTFLNDF2SEI0TTg2ZW54NEM4MXltMzMaDAiZ4JuwBhCYqIXwAiIMCJngm7AGEJiohfACKgwImeCbsAYQmKiF8AI= | D2: 0.27 | E2: 386 | F2: Preferred Package | G2: prmkQjxRzEikMOjvZwjyuky9emyqeau3VyE5V | H2: checking | I2: depository
A3: Scotiabank | B3: 12 | C3: CAESJWdCa0xiVlBvTjVjRXZuQTFLNDF2SEI0TTg2ZW54NEM4MXltMzMaDAiZ4JuwBhCYqIXwAiIMCJngm7AGEJiohfACKgwImeCbsAYQmKiF8AI= | D3: 15551.34 | E3: 8692 | F3: Scotia Plan Loan | G3: XgrzK9XyN3c9JxXeELXouQ83yo8bywcdpxAZm | H3: consumer | I3: loan
A4: TD Canada Trust | B4: 13 | D4: 0 | E4: 3214 | F4: LINE OF CREDIT UNSECURED | G4: rJLZ6wO0petXPbJ0zLxECqYmVDeYwztVgPojO | H4: line of credit | I4: loan
A5: TD Canada Trust | B5: 13 | E5: 3403 | F5: MUTUAL FUND RESP - FAMILY PLAN | G5: Z0Yb9AqdaVCD4AMZy1KLuQrwvAkrXMCbL1eP1 | H5: resp | I5: investment
A6: TD Canada Trust | B6: 13 | E6: 3413 | F6: MUTUAL FUND RESP - FAMILY PLAN | G6: 54P9jkB7LKIV4NoJjx9YCOpJrPbp3wswAJrmv | H6: resp | I6: investment
A7: TD Canada Trust | B7: 13 | E7: 9351 | F7: TD EPREMIUM SAVINGS ACCOUNT | G7: jbzL89ZqpmUxBy38KJYbuV4z18r46YIew9Ek5 | H7: savings | I7: depository
A8: TD Canada Trust | B8: 13 | E8: 9W9J | F8: TFSA | G8: 4r1z0Kq56yfk65ewgDNofMZ6j1PZnBHR7wazV | H8: tfsa | I8: investment
A9: TD Canada Trust | B9: 13 | E9: 9W9K | F9: US TFSA | G9: aJYyPxvqRptKO1Dpwk4jCPdN4ModXxC75o03D | H9: tfsa | I9: investment
A10: TD Canada Trust | B10: 13 | E10: 9W9S | F10: SDRSP | G10: x13VRqpNXecvneDw93NEszypOvXyB0COQZ7pD | H10: rrsp | I10: investment
A11: TD Canada Trust | B11: 13 | E11: 9W9U | F11: US SDRSP | G11: JmgwNE95RVS9Y10npJd6CqvNk9zvm0tmvjK3w | H11: rrsp | I11: investment
A12: TD Canada Trust | B12: 13 | E12: 9W9V | F12: RESP ACCOUNT | G12: 8w3Oy0K6PvcjZd8gQV6YupxXQD0xPmHxVMokd | H12: resp | I12: investment
A13: RBC Royal Bank | B13: 14 | C13: CAESJVhwOGplemFuTnlUQk5vNkFSWG5wVUJWWm1yNm41VkN6M2dtekIaCwj2qO2wBhCIxLlLIgsI9qjtsAYQiMS5SyoLCPao7bAGEIjEuUs= | D13: -429.54 | E13: 6614 | F13: RBC Staff Banking | G13: eOMxkwaqNZH7Vznj6o6XTA4KJOvewbhnEVmgd | H13: checking | I13: depository
A14: RBC Royal Bank | B14: 14 | C14: CAESJVhwOGplemFuTnlUQk5vNkFSWG5wVUJWWm1yNm41VkN6M2dtekIaCwj2qO2wBhCIxLlLIgsI9qjtsAYQiMS5SyoLCPao7bAGEIjEuUs= | D14: 102.46 | E14: 9669 | F14: WestJet RBC World Elite Mastercard | G14: NpJvYzRnNdTaNZ0XOMOATOvYmey8M7ioaPe7Y | H14: credit card | I14: credit
A15: Scotiabank | B15: 12 | C15: CAESJWdCa0xiVlBvTjVjRXZuQTFLNDF2SEI0TTg2ZW54NEM4MXltMzMaDAiZ4JuwBhCYqIXwAiIMCJngm7AGEJiohfACKgwImeCbsAYQmKiF8AI= | D15: 0.27 | E15: 386 | F15: Preferred Package | G15: prmkQjxRzEikMOjvZwjyuky9emyqeau3VyE5V | H15: checking | I15: depository
A16: Scotiabank | B16: 12 | C16: CAESJWdCa0xiVlBvTjVjRXZuQTFLNDF2SEI0TTg2ZW54NEM4MXltMzMaDAiZ4JuwBhCYqIXwAiIMCJngm7AGEJiohfACKgwImeCbsAYQmKiF8AI= | D16: 15551.34 | E16: 8692 | F16: Scotia Plan Loan | G16: XgrzK9XyN3c9JxXeELXouQ83yo8bywcdpxAZm | H16: consumer | I16: loan
A17: TD Canada Trust | B17: 13 | D17: 0 | E17: 3214 | F17: LINE OF CREDIT UNSECURED | G17: rJLZ6wO0petXPbJ0zLxECqYmVDeYwztVgPojO | H17: line of credit | I17: loan
A18: TD Canada Trust | B18: 13 | D18: 0 | E18: 3403 | F18: MUTUAL FUND RESP - FAMILY PLAN | G18: Z0Yb9AqdaVCD4AMZy1KLuQrwvAkrXMCbL1eP1 | H18: resp | I18: investment
A19: TD Canada Trust | B19: 13 | D19: 0 | E19: 3413 | F19: MUTUAL FUND RESP - FAMILY PLAN | G19: 54P9jkB7LKIV4NoJjx9YCOpJrPbp3wswAJrmv | H19: resp | I19: investment
A20: TD Canada Trust | B20: 13 | E20: 9351 | F20: TD EPREMIUM SAVINGS ACCOUNT | G20: jbzL89ZqpmUxBy38KJYbuV4z18r46YIew9Ek5 | H20: savings | I20: depository
A21: TD Canada Trust | B21: 13 | E21: 9W9J | F21: TFSA | G21: 4r1z0Kq56yfk65ewgDNofMZ6j1PZnBHR7wazV | H21: tfsa | I21: investment
A22: TD Canada Trust | B22: 13 | E22: 9W9K | F22: US TFSA | G22: aJYyPxvqRptKO1Dpwk4jCPdN4ModXxC75o03D | H22: tfsa | I22: investment
A23: TD Canada Trust | B23: 13 | E23: 9W9S | F23: SDRSP | G23: x13VRqpNXecvneDw93NEszypOvXyB0COQZ7pD | H23: rrsp | I23: investment
A24: TD Canada Trust | B24: 13 | E24: 9W9U | F24: US SDRSP | G24: JmgwNE95RVS9Y10npJd6CqvNk9zvm0tmvjK3w | H24: rrsp | I24: investment
A25: TD Canada Trust | B25: 13 | E25: 9W9V | F25: RESP ACCOUNT | G25: 8w3Oy0K6PvcjZd8gQV6YupxXQD0xPmHxVMokd | H25: resp | I25: investment
A26: RBC Royal Bank | B26: 14 | C26: CAESJVhwOGplemFuTnlUQk5vNkFSWG5wVUJWWm1yNm41VkN6M2dtekIaCwj2qO2wBhCIxLlLIgsI9qjtsAYQiMS5SyoLCPao7bAGEIjEuUs= | D26: -429.54 | E26: 6614 | F26: RBC Staff Banking | G26: eOMxkwaqNZH7Vznj6o6XTA4KJOvewbhnEVmgd | H26: checking | I26: depository
A27: RBC Royal Bank | B27: 14 | C27: CAESJVhwOGplemFuTnlUQk5vNkFSWG5wVUJWWm1yNm41VkN6M2dtekIaCwj2qO2wBhCIxLlLIgsI9qjtsAYQiMS5SyoLCPao7bAGEIjEuUs= | D27: 102.46 | E27: 9669 | F27: WestJet RBC World Elite Mastercard | G27: NpJvYzRnNdTaNZ0XOMOATOvYmey8M7ioaPe7Y | H27: credit card | I27: credit

Sheet Transactions
A1: Account ID | B1: Action | C1: Amount | D1: Categories | E1: Date | F1: ISO Currency Code | G1: Merchant Name | H1: Name | I1: Payment Channel | J1: Pending | K1: Transaction ID | L1: Account Name | M1: Bank | N1: Operation | O1: Custom Category | P1: Datetime | Q1: Month | R1: Recent | S1: 6M AVG | T1: Month's Total | U1: Budget | V1: Sel Month
A2: eOMxkwaqNZH7Vznj6o6XTA4KJOvewbhnEVmgd | B2: added | C2: 2000 | D2: Transfer, Debit | E2: 2022-04-03, 8:00:00 p.m. | F2: CAD | H2: Online Banking transfer - 8102 | I2: other | J2: FALSE | K2: BXVyezjPrgSxXRna9M9wIa65QjPRpru3BPr6o | L2: =_xlfn.XLOOKUP(Transactions[[#This Row],[Account ID]],Accounts[Plaid Account ID],Accounts[Name],"Not Found",0) -> RBC Staff Banking | M2: =_xlfn.XLOOKUP(Transactions[[#This Row],[Account ID]],Accounts[Plaid Account ID],Accounts[Institution Name],"Not Found",0) -> RBC Royal Bank | N2: =IF(Transactions[[#This Row],[Amount]]<0,"credit","debit") -> debit | O2: {=IF( ISNUMBER(MATCH(Transactions[[#This Row],[Categories]], _xlfn._xlws.FILTER(Custom_Cat[Name], LEN(Custom_Cat[Name]) >= 3), 0)), INDEX(Custom_Cat[Custom Category], MATCH(Transactions[[#This Row],[Categories]], _xlfn._xlws.FILTER(Custom_Cat[Name], LEN(Custom_Cat[Name]) >= 3), 0)), IFERROR( INDEX( Custom_Cat[Custom Category], MATCH( 1, (ISNUMBER(SEARCH(LOWER(Custom_Cat[Name]), LOWER(Transactions[[#This Row],[Name]])))) * (LEN(Custom_Cat[Name]) >= 3) * ( (IF(LEFT(Custom_Cat[Amount],1)="<",Transactions[[#This Row],[Amount]]<VALUE(MID(Custom_Cat[Amount], 2, LEN(Custom_Cat[Amount])-1)),TRUE)) * (IF(LEFT(Custom_Cat[Amount],1)=">",Transactions[[#This Row],[Amount]]>VALUE(MID(Custom_Cat[Amount], 2, LEN(Custom_Cat[Amount])-1)),TRUE)) ), 0 ) ), Transactions[[#This Row],[Categories]] ) )} -> Transfer, Debit | P2: =DATE(LEFT(Transactions[[#This Row],[Date]],4),MID(Transactions[[#This Row],[Date]],6,2),MID(Transactions[[#This Row],[Date]],9,2))+IF(RIGHT(Transactions[[#This Row],[Date]],2)="pm",IF(MID(Transactions[[#This Row],[Date]],12,2)<12,0.5,0),IF(MID(Transactions[[#This Row],[Date]],12,2)=12,-0.5,0)) -> 44654 | Q2: =DATE(YEAR(Transactions[[#This Row],[Datetime]]),MONTH(Transactions[[#This Row],[Datetime]]),1) -> 44652 | R2: =AND(Transactions[[#This Row],[Datetime]]>=EDATE(MAX(Transactions[Datetime]),-6),Transactions[[#This Row],[Datetime]]<=TODAY()) -> FALSE | S2: =AVERAGEIFS(Transactions[Month''s Total],Transactions[Recent],TRUE,Transactions[Custom Category],Transactions[[#This Row],[Custom Category]]) -> 12758.461 | T2: =SUMIFS(Transactions[Amount],Transactions[Month],Transactions[[#This Row],[Month]],Transactions[Custom Category],Transactions[[#This Row],[Custom Category]]) -> 5295.62 | U2: =IF(COUNTIF(Budgets[Custom Category],Transactions[[#This Row],[Custom Category]])=0,Transactions[[#This Row],[6M AVG]],_xlfn.XLOOKUP(Transactions[[#This Row],[Custom Category]],Budgets[Custom Category],Budgets[Monthly],0,0)) -> 12758.461 | V2: =IF(Transactions[[#This Row],[Month]]=Sel_Month,Transactions[[#This Row],[Amount]],0) -> 0
A3: eOMxkwaqNZH7Vznj6o6XTA4KJOvewbhnEVmgd | B3: added | C3: 1444.17 | D3: Transfer, Debit | E3: 2022-04-03, 8:00:00 p.m. | F3: CAD | H3: Online Banking transfer - 0349 | I3: other | J3: FALSE | K3: 3XqR5pwB6kSDXQKBzEzJcMaqRzJov7Io13Rbp | L3: =_xlfn.XLOOKUP(Transactions[[#This Row],[Account ID]],Accounts[Plaid Account ID],Accounts[Name],"Not Found",0) -> RBC Staff Banking | M3: =_xlfn.XLOOKUP(Transactions[[#This Row],[Account ID]],Accounts[Plaid Account ID],Accounts[Institution Name],"Not Found",0) -> RBC Royal Bank | N3: =IF(Transactions[[#This Row],[Amount]]<0,"credit","debit") -> debit | O3: {=IF( ISNUMBER(MATCH(Transactions[[#This Row],[Categories]], _xlfn._xlws.FILTER(Custom_Cat[Name], LEN(Custom_Cat[Name]) >= 3), 0)), INDEX(Custom_Cat[Custom Category], MATCH(Transactions[[#This Row],[Categories]], _xlfn._xlws.FILTER(Custom_Cat[Name], LEN(Custom_Cat[Name]) >= 3), 0)), IFERROR( INDEX( Custom_Cat[Custom Category], MATCH( 1, (ISNUMBER(SEARCH(LOWER(Custom_Cat[Name]), LOWER(Transactions[[#This Row],[Name]])))) * (LEN(Custom_Cat[Name]) >= 3) * ( (IF(LEFT(Custom_Cat[Amount],1)="<",Transactions[[#This Row],[Amount]]<VALUE(MID(Custom_Cat[Amount], 2, LEN(Custom_Cat[Amount])-1)),TRUE)) * (IF(LEFT(Custom_Cat[Amount],1)=">",Transactions[[#This Row],[Amount]]>VALUE(MID(Custom_Cat[Amount], 2, LEN(Custom_Cat[Amount])-1)),TRUE)) ), 0 ) ), Transactions[[#This Row],[Categories]] ) )} -> Transfer, Debit | P3: =DATE(LEFT(Transactions[[#This Row],[Date]],4),MID(Transactions[[#This Row],[Date]],6,2),MID(Transactions[[#This Row],[Date]],9,2))+IF(RIGHT(Transactions[[#This Row],[Date]],2)="pm",IF(MID(Transactions[[#This Row],[Date]],12,2)<12,0.5,0),IF(MID(Transactions[[#This Row],[Date]],12,2)=12,-0.5,0)) -> 44654 | Q3: =DATE(YEAR(Transactions[[#This Row],[Datetime]]),MONTH(Transactions[[#This Row],[Datetime]]),1) -> 44652 | R3: =AND(Transactions[[#This Row],[Datetime]]>=EDATE(MAX(Transactions[Datetime]),-6),Transactions[[#This Row],[Datetime]]<=TODAY()) -> FALSE | S3: =AVERAGEIFS(Transactions[Month''s Total],Transactions[Recent],TRUE,Transactions[Custom Category],Transactions[[#This Row],[Custom Category]]) -> 12758.461 | T3: =SUMIFS(Transactions[Amount],Transactions[Month],Transactions[[#This Row],[Month]],Transactions[Custom Category],Transactions[[#This Row],[Custom Category]]) -> 5295.62 | U3: =IF(COUNTIF(Budgets[Custom Category],Transactions[[#This Row],[Custom Category]])=0,Transactions[[#This Row],[6M AVG]],_xlfn.XLOOKUP(Transactions[[#This Row],[Custom Category]],Budgets[Custom Category],Budgets[Monthly],0,0)) -> 12758.461 | V3: =IF(Transactions[[#This Row],[Month]]=Sel_Month,Transactions[[#This Row],[Amount]],0) -> 0
A4: eOMxkwaqNZH7Vznj6o6XTA4KJOvewbhnEVmgd | B4: added | C4: 1500 | D4: Transfer, Debit | E4: 2022-04-03, 8:00:00 p.m. | F4: CAD | H4: e-Transfer sent Manuel CIBC | I4: other | J4: FALSE | K4: yb6XYJp8zDT3z0Oj6P61uAR95LwZj7TpQev04 | L4: =_xlfn.XLOOKUP(Transactions[[#This Row],[Account ID]],Accounts[Plaid Account ID],Accounts[Name],"Not Found",0) -> RBC Staff Banking | M4: =_xlfn.XLOOKUP(Transactions[[#This Row],[Account ID]],Accounts[Plaid Account ID],Accounts[Institution Name],"Not Found",0) -> RBC Royal Bank | N4: =IF(Transactions[[#This Row],[Amount]]<0,"credit","debit") -> debit | O4: {=IF( ISNUMBER(MATCH(Transactions[[#This Row],[Categories]], _xlfn._xlws.FILTER(Custom_Cat[Name], LEN(Custom_Cat[Name]) >= 3), 0)), INDEX(Custom_Cat[Custom Category], MATCH(Transactions[[#This Row],[Categories]], _xlfn._xlws.FILTER(Custom_Cat[Name], LEN(Custom_Cat[Name]) >= 3), 0)), IFERROR( INDEX( Custom_Cat[Custom Category], MATCH( 1, (ISNUMBER(SEARCH(LOWER(Custom_Cat[Name]), LOWER(Transactions[[#This Row],[Name]])))) * (LEN(Custom_Cat[Name]) >= 3) * ( (IF(LEFT(Custom_Cat[Amount],1)="<",Transactions[[#This Row],[Amount]]<VALUE(MID(Custom_Cat[Amount], 2, LEN(Custom_Cat[Amount])-1)),TRUE)) * (IF(LEFT(Custom_Cat[Amount],1)=">",Transactions[[#This Row],[Amount]]>VALUE(MID(Custom_Cat[Amount], 2, LEN(Custom_Cat[Amount])-1)),TRUE)) ), 0 ) ), Transactions[[#This Row],[Categories]] ) )} -> Transfer,Internal | P4: =DATE(LEFT(Transactions[[#This Row],[Date]],4),MID(Transactions[[#This Row],[Date]],6,2),MID(Transactions[[#This Row],[Date]],9,2))+IF(RIGHT(Transactions[[#This Row],[Date]],2)="pm",IF(MID(Transactions[[#This Row],[Date]],12,2)<12,0.5,0),IF(MID(Transactions[[#This Row],[Date]],12,2)=12,-0.5,0)) -> 44654 | Q4: =DATE(YEAR(Transactions[[#This Row],[Datetime]]),MONTH(Transactions[[#This Row],[Datetime]]),1) -> 44652 | R4: =AND(Transactions[[#This Row],[Datetime]]>=EDATE(MAX(Transactions[Datetime]),-6),Transactions[[#This Row],[Datetime]]<=TODAY()) -> FALSE | S4: =AVERAGEIFS(Transactions[Month''s Total],Transactions[Recent],TRUE,Transactions[Custom Category],Transactions[[#This Row],[Custom Category]]) -> 14532.99 | T4: =SUMIFS(Transactions[Amount],Transactions[Month],Transactions[[#This Row],[Month]],Transactions[Custom Category],Transactions[[#This Row],[Custom Category]]) -> 8446.13 | U4: =IF(COUNTIF(Budgets[Custom Category],Transactions[[#This Row],[Custom Category]])=0,Transactions[[#This Row],[6M AVG]],_xlfn.XLOOKUP(Transactions[[#This Row],[Custom Category]],Budgets[Custom Category],Budgets[Monthly],0,0)) -> 14532.99 | V4: =IF(Transactions[[#This Row],[Month]]=Sel_Month,Transactions[[#This Row],[Amount]],0) -> 0
A5: eOMxkwaqNZH7Vznj6o6XTA4KJOvewbhnEVmgd | B5: added | C5: 1100 | D5: Transfer, Debit | E5: 2022-04-03, 8:00:00 p.m. | F5: CAD | H5: e-Transfer sent Mon Petit Univers | I5: other | J5: FALSE | K5: KYmvezN0bnso8Rk5dDdyTx4XOVejyKUE9a60r | L5: =_xlfn.XLOOKUP(Transactions[[#This Row],[Account ID]],Accounts[Plaid Account ID],Accounts[Name],"Not Found",0) -> RBC Staff Banking | M5: =_xlfn.XLOOKUP(Transactions[[#This Row],[Account ID]],Accounts[Plaid Account ID],Accounts[Institution Name],"Not Found",0) -> RBC Royal Bank | N5: =IF(Transactions[[#This Row],[Amount]]<0,"credit","debit") -> debit | O5: {=IF( ISNUMBER(MATCH(Transactions[[#This Row],[Categories]], _xlfn._xlws.FILTER(Custom_Cat[Name], LEN(Custom_Cat[Name]) >= 3), 0)), INDEX(Custom_Cat[Custom Category], MATCH(Transactions[[#This Row],[Categories]], _xlfn._xlws.FILTER(Custom_Cat[Name], LEN(Custom_Cat[Name]) >= 3), 0)), IFERROR( INDEX( Custom_Cat[Custom Category], MATCH( 1, (ISNUMBER(SEARCH(LOWER(Custom_Cat[Name]), LOWER(Transactions[[#This Row],[Name]])))) * (LEN(Custom_Cat[Name]) >= 3) * ( (IF(LEFT(Custom_Cat[Amount],1)="<",Transactions[[#This Row],[Amount]]<VALUE(MID(Custom_Cat[Amount], 2, LEN(Custom_Cat[Amount])-1)),TRUE)) * (IF(LEFT(Custom_Cat[Amount],1)=">",Transactions[[#This Row],[Amount]]>VALUE(MID(Custom_Cat[Amount], 2, LEN(Custom_Cat[Amount])-1)),TRUE)) ), 0 ) ), Transactions[[#This Row],[Categories]] ) )} -> Transfer, Debit | P5: =DATE(LEFT(Transactions[[#This Row],[Date]],4),MID(Transactions[[#This Row],[Date]],6,2),MID(Transactions[[#This Row],[Date]],9,2))+IF(RIGHT(Transactions[[#This Row],[Date]],2)="pm",IF(MID(Transactions[[#This Row],[Date]],12,2)<12,0.5,0),IF(MID(Transactions[[#This Row],[Date]],12,2)=12,-0.5,0)) -> 44654 | Q5: =DATE(YEAR(Transactions[[#This Row],[Datetime]]),MONTH(Transactions[[#This Row],[Datetime]]),1) -> 44652 | R5: =AND(Transactions[[#This Row],[Datetime]]>=EDATE(MAX(Transactions[Datetime]),-6),Transactions[[#This Row],[Datetime]]<=TODAY()) -> FALSE | S5: =AVERAGEIFS(Transactions[Month''s Total],Transactions[Recent],TRUE,Transactions[Custom Category],Transactions[[#This Row],[Custom Category]]) -> 12758.461 | T5: =SUMIFS(Transactions[Amount],Transactions[Month],Transactions[[#This Row],[Month]],Transactions[Custom Category],Transactions[[#This Row],[Custom Category]]) -> 5295.62 | U5: =IF(COUNTIF(Budgets[Custom Category],Transactions[[#This Row],[Custom Category]])=0,Transactions[[#This Row],[6M AVG]],_xlfn.XLOOKUP(Transactions[[#This Row],[Custom Category]],Budgets[Custom Category],Budgets[Monthly],0,0)) -> 12758.461 | V5: =IF(Transactions[[#This Row],[Month]]=Sel_Month,Transactions[[#This Row],[Amount]],0) -> 0
A6: eOMxkwaqNZH7Vznj6o6XTA4KJOvewbhnEVmgd | B6: added | C6: 800 | D6: Transfer, Debit | E6: 2022-04-03, 8:00:00 p.m. | F6: CAD | H6: e-Transfer sent Paula Amariles | I6: other | J6: FALSE | K6: kObx4qpAm9HOVm5g9D90iNbgweVADmHo5znM5 | L6: =_xlfn.XLOOKUP(Transactions[[#This Row],[Account ID]],Accounts[Plaid Account ID],Accounts[Name],"Not Found",0) -> RBC Staff Banking | M6: =_xlfn.XLOOKUP(Transactions[[#This Row],[Account ID]],Accounts[Plaid Account ID],Accounts[Institution Name],"Not Found",0) -> RBC Royal Bank | N6: =IF(Transactions[[#This Row],[Amount]]<0,"credit","debit") -> debit | O6: {=IF( ISNUMBER(MATCH(Transactions[[#This Row],[Categories]], _xlfn._xlws.FILTER(Custom_Cat[Name], LEN(Custom_Cat[Name]) >= 3), 0)), INDEX(Custom_Cat[Custom Category], MATCH(Transactions[[#This Row],[Categories]], _xlfn._xlws.FILTER(Custom_Cat[Name], LEN(Custom_Cat[Name]) >= 3), 0)), IFERROR( INDEX( Custom_Cat[Custom Category], MATCH( 1, (ISNUMBER(SEARCH(LOWER(Custom_Cat[Name]), LOWER(Transactions[[#This Row],[Name]])))) * (LEN(Custom_Cat[Name]) >= 3) * ( (IF(LEFT(Custom_Cat[Amount],1)="<",Transactions[[#This Row],[Amount]]<VALUE(MID(Custom_Cat[Amount], 2, LEN(Custom_Cat[Amount])-1)),TRUE)) * (IF(LEFT(Custom_Cat[Amount],1)=">",Transactions[[#This Row],[Amount]]>VALUE(MID(Custom_Cat[Amount], 2, LEN(Custom_Cat[Amount])-1)),TRUE)) ), 0 ) ), Transactions[[#This Row],[Categories]] ) )} -> Transfer,Internal | P6: =DATE(LEFT(Transactions[[#This Row],[Date]],4),MID(Transactions[[#This Row],[Date]],6,2),MID(Transactions[[#This Row],[Date]],9,2))+IF(RIGHT(Transactions[[#This Row],[Date]],2)="pm",IF(MID(Transactions[[#This Row],[Date]],12,2)<12,0.5,0),IF(MID(Transactions[[#This Row],[Date]],12,2)=12,-0.5,0)) -> 44654 | Q6: =DATE(YEAR(Transactions[[#This Row],[Datetime]]),MONTH(Transactions[[#This Row],[Datetime]]),1) -> 44652 | R6: =AND(Transactions[[#This Row],[Datetime]]>=EDATE(MAX(Transactions[Datetime]),-6),Transactions[[#This Row],[Datetime]]<=TODAY()) -> FALSE | S6: =AVERAGEIFS(Transactions[Month''s Total],Transactions[Recent],TRUE,Transactions[Custom Category],Transactions[[#This Row],[Custom Category]]) -> 14532.99 | T6: =SUMIFS(Transactions[Amount],Transactions[Month],Transactions[[#This Row],[Month]],Transactions[Custom Category],Transactions[[#This Row],[Custom Category]]) -> 8446.13 | U6: =IF(COUNTIF(Budgets[Custom Category],Transactions[[#This Row],[Custom Category]])=0,Transactions[[#This Row],[6M AVG]],_xlfn.XLOOKUP(Transactions[[#This Row],[Custom Category]],Budgets[Custom Category],Budgets[Monthly],0,0)) -> 14532.99 | V6: =IF(Transactions[[#This Row],[Month]]=Sel_Month,Transactions[[#This Row],[Amount]],0) -> 0
A7: eOMxkwaqNZH7Vznj6o6XTA4KJOvewbhnEVmgd | B7: added | C7: 359.58 | D7: Transfer, Debit | E7: 2022-04-03, 8:00:00 p.m. | F7: CAD | H7: e-Transfer sent Manuel CIBC | I7: other | J7: FALSE | K7: AXN3ez01jbS3APoek4kdu09LwN1vAaCMVrzdy | L7: =_xlfn.XLOOKUP(Transactions[[#This Row],[Account ID]],Accounts[Plaid Account ID],Accounts[Name],"Not Found",0) -> RBC Staff Banking | M7: =_xlfn.XLOOKUP(Transactions[[#This Row],[Account ID]],Accounts[Plaid Account ID],Accounts[Institution Name],"Not Found",0) -> RBC Royal Bank | N7: =IF(Transactions[[#This Row],[Amount]]<0,"credit","debit") -> debit | O7: {=IF( ISNUMBER(MATCH(Transactions[[#This Row],[Categories]], _xlfn._xlws.FILTER(Custom_Cat[Name], LEN(Custom_Cat[Name]) >= 3), 0)), INDEX(Custom_Cat[Custom Category], MATCH(Transactions[[#This Row],[Categories]], _xlfn._xlws.FILTER(Custom_Cat[Name], LEN(Custom_Cat[Name]) >= 3), 0)), IFERROR( INDEX( Custom_Cat[Custom Category], MATCH( 1, (ISNUMBER(SEARCH(LOWER(Custom_Cat[Name]), LOWER(Transactions[[#This Row],[Name]])))) * (LEN(Custom_Cat[Name]) >= 3) * ( (IF(LEFT(Custom_Cat[Amount],1)="<",Transactions[[#This Row],[Amount]]<VALUE(MID(Custom_Cat[Amount], 2, LEN(Custom_Cat[Amount])-1)),TRUE)) * (IF(LEFT(Custom_Cat[Amount],1)=">",Transactions[[#This Row],[Amount]]>VALUE(MID(Custom_Cat[Amount], 2, LEN(Custom_Cat[Amount])-1)),TRUE)) ), 0 ) ), Transactions[[#This Row],[Categories]] ) )} -> Transfer,Internal | P7: =DATE(LEFT(Transactions[[#This Row],[Date]],4),MID(Transactions[[#This Row],[Date]],6,2),MID(Transactions[[#This Row],[Date]],9,2))+IF(RIGHT(Transactions[[#This Row],[Date]],2)="pm",IF(MID(Transactions[[#This Row],[Date]],12,2)<12,0.5,0),IF(MID(Transactions[[#This Row],[Date]],12,2)=12,-0.5,0)) -> 44654 | Q7: =DATE(YEAR(Transactions[[#This Row],[Datetime]]),MONTH(Transactions[[#This Row],[Datetime]]),1) -> 44652 | R7: =AND(Transactions[[#This Row],[Datetime]]>=EDATE(MAX(Transactions[Datetime]),-6),Transactions[[#This Row],[Datetime]]<=TODAY()) -> FALSE | S7: =AVERAGEIFS(Transactions[Month''s Total],Transactions[Recent],TRUE,Transactions[Custom Category],Transactions[[#This Row],[Custom Category]]) -> 14532.99 | T7: =SUMIFS(Transactions[Amount],Transactions[Month],Transactions[[#This Row],[Month]],Transactions[Custom Category],Transactions[[#This Row],[Custom Category]]) -> 8446.13 | U7: =IF(COUNTIF(Budgets[Custom Category],Transactions[[#This Row],[Custom Category]])=0,Transactions[[#This Row],[6M AVG]],_xlfn.XLOOKUP(Transactions[[#This Row],[Custom Category]],Budgets[Custom Category],Budgets[Monthly],0,0)) -> 14532.99 | V7: =IF(Transactions[[#This Row],[Month]]=Sel_Month,Transactions[[#This Row],[Amount]],0) -> 0
A8: eOMxkwaqNZH7Vznj6o6XTA4KJOvewbhnEVmgd | B8: added | C8: -2000 | D8: Transfer, Credit | E8: 2022-04-03, 8:00:00 p.m. | F8: CAD | H8: Online transfer received - 5342 AUTOMATOS CONSULTING INC. | I8: other | J8: FALSE | K8: 0XDrJpO173S7XKVnMwM4TZO9yeN74wCApZmgq | L8: =_xlfn.XLOOKUP(Transactions[[#This Row],[Account ID]],Accounts[Plaid Account ID],Accounts[Name],"Not Found",0) -> RBC Staff Banking | M8: =_xlfn.XLOOKUP(Transactions[[#This Row],[Account ID]],Accounts[Plaid Account ID],Accounts[Institution Name],"Not Found",0) -> RBC Royal Bank | N8: =IF(Transactions[[#This Row],[Amount]]<0,"credit","debit") -> credit | O8: {=IF( ISNUMBER(MATCH(Transactions[[#This Row],[Categories]], _xlfn._xlws.FILTER(Custom_Cat[Name], LEN(Custom_Cat[Name]) >= 3), 0)), INDEX(Custom_Cat[Custom Category], MATCH(Transactions[[#This Row],[Categories]], _xlfn._xlws.FILTER(Custom_Cat[Name], LEN(Custom_Cat[Name]) >= 3), 0)), IFERROR( INDEX( Custom_Cat[Custom Category], MATCH( 1, (ISNUMBER(SEARCH(LOWER(Custom_Cat[Name]), LOWER(Transactions[[#This Row],[Name]])))) * (LEN(Custom_Cat[Name]) >= 3) * ( (IF(LEFT(Custom_Cat[Amount],1)="<",Transactions[[#This Row],[Amount]]<VALUE(MID(Custom_Cat[Amount], 2, LEN(Custom_Cat[Amount])-1)),TRUE)) * (IF(LEFT(Custom_Cat[Amount],1)=">",Transactions[[#This Row],[Amount]]>VALUE(MID(Custom_Cat[Amount], 2, LEN(Custom_Cat[Amount])-1)),TRUE)) ), 0 ) ), Transactions[[#This Row],[Categories]] ) )} -> Income,Salary | P8: =DATE(LEFT(Transactions[[#This Row],[Date]],4),MID(Transactions[[#This Row],[Date]],6,2),MID(Transactions[[#This Row],[Date]],9,2))+IF(RIGHT(Transactions[[#This Row],[Date]],2)="pm",IF(MID(Transactions[[#This Row],[Date]],12,2)<12,0.5,0),IF(MID(Transactions[[#This Row],[Date]],12,2)=12,-0.5,0)) -> 44654 | Q8: =DATE(YEAR(Transactions[[#This Row],[Datetime]]),MONTH(Transactions[[#This Row],[Datetime]]),1) -> 44652 | R8: =AND(Transactions[[#This Row],[Datetime]]>=EDATE(MAX(Transactions[Datetime]),-6),Transactions[[#This Row],[Datetime]]<=TODAY()) -> FALSE | S8: =AVERAGEIFS(Transactions[Month''s Total],Transactions[Recent],TRUE,Transactions[Custom Category],Transactions[[#This Row],[Custom Category]]) -> -18125.097 | T8: =SUMIFS(Transactions[Amount],Transactions[Month],Transactions[[#This Row],[Month]],Transactions[Custom Category],Transactions[[#This Row],[Custom Category]]) -> -11741.75 | U8: =IF(COUNTIF(Budgets[Custom Category],Transactions[[#This Row],[Custom Category]])=0,Transactions[[#This Row],[6M AVG]],_xlfn.XLOOKUP(Transactions[[#This Row],[Custom Category]],Budgets[Custom Category],Budgets[Monthly],0,0)) -> -18125.097 | V8: =IF(Transactions[[#This Row],[Month]]=Sel_Month,Transactions[[#This Row],[Amount]],0) -> 0
A9: eOMxkwaqNZH7Vznj6o6XTA4KJOvewbhnEVmgd | B9: added | C9: -2000 | D9: Transfer, Credit | E9: 2022-04-03, 8:00:00 p.m. | F9: CAD | H9: Online transfer received - 2148 AUTOMATOS CONSULTING INC. | I9: other | J9: FALSE | K9: jOoXrPpkN7HKQmxMzAzLTXvM6gnwZYHexgJ0n | L9: =_xlfn.XLOOKUP(Transactions[[#This Row],[Account ID]],Accounts[Plaid Account ID],Accounts[Name],"Not Found",0) -> RBC Staff Banking | M9: =_xlfn.XLOOKUP(Transactions[[#This Row],[Account ID]],Accounts[Plaid Account ID],Accounts[Institution Name],"Not Found",0) -> RBC Royal Bank | N9: =IF(Transactions[[#This Row],[Amount]]<0,"credit","debit") -> credit | O9: {=IF( ISNUMBER(MATCH(Transactions[[#This Row],[Categories]], _xlfn._xlws.FILTER(Custom_Cat[Name], LEN(Custom_Cat[Name]) >= 3), 0)), INDEX(Custom_Cat[Custom Category], MATCH(Transactions[[#This Row],[Categories]], _xlfn._xlws.FILTER(Custom_Cat[Name], LEN(Custom_Cat[Name]) >= 3), 0)), IFERROR( INDEX( Custom_Cat[Custom Category], MATCH( 1, (ISNUMBER(SEARCH(LOWER(Custom_Cat[Name]), LOWER(Transactions[[#This Row],[Name]])))) * (LEN(Custom_Cat[Name]) >= 3) * ( (IF(LEFT(Custom_Cat[Amount],1)="<",Transactions[[#This Row],[Amount]]<VALUE(MID(Custom_Cat[Amount], 2, LEN(Custom_Cat[Amount])-1)),TRUE)) * (IF(LEFT(Custom_Cat[Amount],1)=">",Transactions[[#This Row],[Amount]]>VALUE(MID(Custom_Cat[Amount], 2, LEN(Custom_Cat[Amount])-1)),TRUE)) ), 0 ) ), Transactions[[#This Row],[Categories]] ) )} -> Income,Salary | P9: =DATE(LEFT(Transactions[[#This Row],[Date]],4),MID(Transactions[[#This Row],[Date]],6,2),MID(Transactions[[#This Row],[Date]],9,2))+IF(RIGHT(Transactions[[#This Row],[Date]],2)="pm",IF(MID(Transactions[[#This Row],[Date]],12,2)<12,0.5,0),IF(MID(Transactions[[#This Row],[Date]],12,2)=12,-0.5,0)) -> 44654 | Q9: =DATE(YEAR(Transactions[[#This Row],[Datetime]]),MONTH(Transactions[[#This Row],[Datetime]]),1) -> 44652 | R9: =AND(Transactions[[#This Row],[Datetime]]>=EDATE(MAX(Transactions[Datetime]),-6),Transactions[[#This Row],[Datetime]]<=TODAY()) -> FALSE | S9: =AVERAGEIFS(Transactions[Month''s Total],Transactions[Recent],TRUE,Transactions[Custom Category],Transactions[[#This Row],[Custom Category]]) -> -18125.097 | T9: =SUMIFS(Transactions[Amount],Transactions[Month],Transactions[[#This Row],[Month]],Transactions[Custom Category],Transactions[[#This Row],[Custom Category]]) -> -11741.75 | U9: =IF(COUNTIF(Budgets[Custom Category],Transactions[[#This Row],[Custom Category]])=0,Transactions[[#This Row],[6M AVG]],_xlfn.XLOOKUP(Transactions[[#This Row],[Custom Category]],Budgets[Custom Category],Budgets[Monthly],0,0)) -> -18125.097 | V9: =IF(Transactions[[#This Row],[Month]]=Sel_Month,Transactions[[#This Row],[Amount]],0) -> 0
A10: eOMxkwaqNZH7Vznj6o6XTA4KJOvewbhnEVmgd | B10: added | C10: -1203.75 | D10: Transfer, Credit | E10: 2022-04-03, 8:00:00 p.m. | F10: CAD | H10: Online transfer received - 4899 AUTOMATOS CONSULTING INC. | I10: other | J10: FALSE | K10: rb4Povp8znTzYwXg9A9rIP8EwJAjozHVXqz3k | L10: =_xlfn.XLOOKUP(Transactions[[#This Row],[Account ID]],Accounts[Plaid Account ID],Accounts[Name],"Not Found",0) -> RBC Staff Banking | M10: =_xlfn.XLOOKUP(Transactions[[#This Row],[Account ID]],Accounts[Plaid Account ID],Accounts[Institution Name],"Not Found",0) -> RBC Royal Bank | N10: =IF(Transactions[[#This Row],[Amount]]<0,"credit","debit") -> credit | O10: {=IF( ISNUMBER(MATCH(Transactions[[#This Row],[Categories]], _xlfn._xlws.FILTER(Custom_Cat[Name], LEN(Custom_Cat[Name]) >= 3), 0)), INDEX(Custom_Cat[Custom Category], MATCH(Transactions[[#This Row],[Categories]], _xlfn._xlws.FILTER(Custom_Cat[Name], LEN(Custom_Cat[Name]) >= 3), 0)), IFERROR( INDEX( Custom_Cat[Custom Category], MATCH( 1, (ISNUMBER(SEARCH(LOWER(Custom_Cat[Name]), LOWER(Transactions[[#This Row],[Name]])))) * (LEN(Custom_Cat[Name]) >= 3) * ( (IF(LEFT(Custom_Cat[Amount],1)="<",Transactions[[#This Row],[Amount]]<VALUE(MID(Custom_Cat[Amount], 2, LEN(Custom_Cat[Amount])-1)),TRUE)) * (IF(LEFT(Custom_Cat[Amount],1)=">",Transactions[[#This Row],[Amount]]>VALUE(MID(Custom_Cat[Amount], 2, LEN(Custom_Cat[Amount])-1)),TRUE)) ), 0 ) ), Transactions[[#This Row],[Categories]] ) )} -> Income,Salary | P10: =DATE(LEFT(Transactions[[#This Row],[Date]],4),MID(Transactions[[#This Row],[Date]],6,2),MID(Transactions[[#This Row],[Date]],9,2))+IF(RIGHT(Transactions[[#This Row],[Date]],2)="pm",IF(MID(Transactions[[#This Row],[Date]],12,2)<12,0.5,0),IF(MID(Transactions[[#This Row],[Date]],12,2)=12,-0.5,0)) -> 44654 | Q10: =DATE(YEAR(Transactions[[#This Row],[Datetime]]),MONTH(Transactions[[#This Row],[Datetime]]),1) -> 44652 | R10: =AND(Transactions[[#This Row],[Datetime]]>=EDATE(MAX(Transactions[Datetime]),-6),Transactions[[#This Row],[Datetime]]<=TODAY()) -> FALSE | S10: =AVERAGEIFS(Transactions[Month''s Total],Transactions[Recent],TRUE,Transactions[Custom Category],Transactions[[#This Row],[Custom Category]]) -> -18125.097 | T10: =SUMIFS(Transactions[Amount],Transactions[Month],Transactions[[#This Row],[Month]],Transactions[Custom Category],Transactions[[#This Row],[Custom Category]]) -> -11741.75 | U10: =IF(COUNTIF(Budgets[Custom Category],Transactions[[#This Row],[Custom Category]])=0,Transactions[[#This Row],[6M AVG]],_xlfn.XLOOKUP(Transactions[[#This Row],[Custom Category]],Budgets[Custom Category],Budgets[Monthly],0,0)) -> -18125.097 | V10: =IF(Transactions[[#This Row],[Month]]=Sel_Month,Transactions[[#This Row],[Amount]],0) -> 0
A11: eOMxkwaqNZH7Vznj6o6XTA4KJOvewbhnEVmgd | B11: added | C11: 2000 | D11: Transfer, Debit | E11: 2022-04-13, 8:00:00 p.m. | F11: CAD | H11: e-Transfer sent Manuel CIBC | I11: other | J11: FALSE | K11: PpbjezRnN6TVNZrBQMQ0UYbVLx7r4zIo90BXz | L11: =_xlfn.XLOOKUP(Transactions[[#This Row],[Account ID]],Accounts[Plaid Account ID],Accounts[Name],"Not Found",0) -> RBC Staff Banking | M11: =_xlfn.XLOOKUP(Transactions[[#This Row],[Account ID]],Accounts[Plaid Account ID],Accounts[Institution Name],"Not Found",0) -> RBC Royal Bank | N11: =IF(Transactions[[#This Row],[Amount]]<0,"credit","debit") -> debit | O11: {=IF( ISNUMBER(MATCH(Transactions[[#This Row],[Categories]], _xlfn._xlws.FILTER(Custom_Cat[Name], LEN(Custom_Cat[Name]) >= 3), 0)), INDEX(Custom_Cat[Custom Category], MATCH(Transactions[[#This Row],[Categories]], _xlfn._xlws.FILTER(Custom_Cat[Name], LEN(Custom_Cat[Name]) >= 3), 0)), IFERROR( INDEX( Custom_Cat[Custom Category], MATCH( 1, (ISNUMBER(SEARCH(LOWER(Custom_Cat[Name]), LOWER(Transactions[[#This Row],[Name]])))) * (LEN(Custom_Cat[Name]) >= 3) * ( (IF(LEFT(Custom_Cat[Amount],1)="<",Transactions[[#This Row],[Amount]]<VALUE(MID(Custom_Cat[Amount], 2, LEN(Custom_Cat[Amount])-1)),TRUE)) * (IF(LEFT(Custom_Cat[Amount],1)=">",Transactions[[#This Row],[Amount]]>VALUE(MID(Custom_Cat[Amount], 2, LEN(Custom_Cat[Amount])-1)),TRUE)) ), 0 ) ), Transactions[[#This Row],[Categories]] ) )} -> Transfer,Internal | P11: =DATE(LEFT(Transactions[[#This Row],[Date]],4),MID(Transactions[[#This Row],[Date]],6,2),MID(Transactions[[#This Row],[Date]],9,2))+IF(RIGHT(Transactions[[#This Row],[Date]],2)="pm",IF(MID(Transactions[[#This Row],[Date]],12,2)<12,0.5,0),IF(MID(Transactions[[#This Row],[Date]],12,2)=12,-0.5,0)) -> 44664 | Q11: =DATE(YEAR(Transactions[[#This Row],[Datetime]]),MONTH(Transactions[[#This Row],[Datetime]]),1) -> 44652 | R11: =AND(Transactions[[#This Row],[Datetime]]>=EDATE(MAX(Transactions[Datetime]),-6),Transactions[[#This Row],[Datetime]]<=TODAY()) -> FALSE | S11: =AVERAGEIFS(Transactions[Month''s Total],Transactions[Recent],TRUE,Transactions[Custom Category],Transactions[[#This Row],[Custom Category]]) -> 14532.99 | T11: =SUMIFS(Transactions[Amount],Transactions[Month],Transactions[[#This Row],[Month]],Transactions[Custom Category],Transactions[[#This Row],[Custom Category]]) -> 8446.13 | U11: =IF(COUNTIF(Budgets[Custom Category],Transactions[[#This Row],[Custom Category]])=0,Transactions[[#This Row],[6M AVG]],_xlfn.XLOOKUP(Transactions[[#This Row],[Custom Category]],Budgets[Custom Category],Budgets[Monthly],0,0)) -> 14532.99 | V11: =IF(Transactions[[#This Row],[Month]]=Sel_Month,Transactions[[#This Row],[Amount]],0) -> 0
A12: eOMxkwaqNZH7Vznj6o6XTA4KJOvewbhnEVmgd | B12: added | C12: -2000 | D12: Transfer, Credit | E12: 2022-04-13, 8:00:00 p.m. | F12: CAD | H12: Online transfer received - 8625 AUTOMATOS CONSULTING INC. | I12: other | J12: FALSE | K12: qbx15Ap8zQTerAqKYXY1SVoL9aNBdRIDdm7ej | L12: =_xlfn.XLOOKUP(Transactions[[#This Row],[Account ID]],Accounts[Plaid Account ID],Accounts[Name],"Not Found",0) -> RBC Staff Banking | M12: =_xlfn.XLOOKUP(Transactions[[#This Row],[Account ID]],Accounts[Plaid Account ID],Accounts[Institution Name],"Not Found",0) -> RBC Royal Bank | N12: =IF(Transactions[[#This Row],[Amount]]<0,"credit","debit") -> credit | O12: {=IF( ISNUMBER(MATCH(Transactions[[#This Row],[Categories]], _xlfn._xlws.FILTER(Custom_Cat[Name], LEN(Custom_Cat[Name]) >= 3), 0)), INDEX(Custom_Cat[Custom Category], MATCH(Transactions[[#This Row],[Categories]], _xlfn._xlws.FILTER(Custom_Cat[Name], LEN(Custom_Cat[Name]) >= 3), 0)), IFERROR( INDEX( Custom_Cat[Custom Category], MATCH( 1, (ISNUMBER(SEARCH(LOWER(Custom_Cat[Name]), LOWER(Transactions[[#This Row],[Name]])))) * (LEN(Custom_Cat[Name]) >= 3) * ( (IF(LEFT(Custom_Cat[Amount],1)="<",Transactions[[#This Row],[Amount]]<VALUE(MID(Custom_Cat[Amount], 2, LEN(Custom_Cat[Amount])-1)),TRUE)) * (IF(LEFT(Custom_Cat[Amount],1)=">",Transactions[[#This Row],[Amount]]>VALUE(MID(Custom_Cat[Amount], 2, LEN(Custom_Cat[Amount])-1)),TRUE)) ), 0 ) ), Transactions[[#This Row],[Categories]] ) )} -> Income,Salary | P12: =DATE(LEFT(Transactions[[#This Row],[Date]],4),MID(Transactions[[#This Row],[Date]],6,2),MID(Transactions[[#This Row],[Date]],9,2))+IF(RIGHT(Transactions[[#This Row],[Date]],2)="pm",IF(MID(Transactions[[#This Row],[Date]],12,2)<12,0.5,0),IF(MID(Transactions[[#This Row],[Date]],12,2)=12,-0.5,0)) -> 44664 | Q12: =DATE(YEAR(Transactions[[#This Row],[Datetime]]),MONTH(Transactions[[#This Row],[Datetime]]),1) -> 44652 | R12: =AND(Transactions[[#This Row],[Datetime]]>=EDATE(MAX(Transactions[Datetime]),-6),Transactions[[#This Row],[Datetime]]<=TODAY()) -> FALSE | S12: =AVERAGEIFS(Transactions[Month''s Total],Transactions[Recent],TRUE,Transactions[Custom Category],Transactions[[#This Row],[Custom Category]]) -> -18125.097 | T12: =SUMIFS(Transactions[Amount],Transactions[Month],Transactions[[#This Row],[Month]],Transactions[Custom Category],Transactions[[#This Row],[Custom Category]]) -> -11741.75 | U12: =IF(COUNTIF(Budgets[Custom Category],Transactions[[#This Row],[Custom Category]])=0,Transactions[[#This Row],[6M AVG]],_xlfn.XLOOKUP(Transactions[[#This Row],[Custom Category]],Budgets[Custom Category],Budgets[Monthly],0,0)) -> -18125.097 | V12: =IF(Transactions[[#This Row],[Month]]=Sel_Month,Transactions[[#This Row],[Amount]],0) -> 0
A13: eOMxkwaqNZH7Vznj6o6XTA4KJOvewbhnEVmgd | B13: added | C13: 1749 | D13: Transfer, Debit | E13: 2022-04-21, 8:00:00 p.m. | F13: CAD | H13: e-Transfer sent Manuel CIBC | I13: other | J13: FALSE | K13: LNJEezRjgpuv83A7wmwKTZaP56woj1CZqbn9b | L13: =_xlfn.XLOOKUP(Transactions[[#This Row],[Account ID]],Accounts[Plaid Account ID],Accounts[Name],"Not Found",0) -> RBC Staff Banking | M13: =_xlfn.XLOOKUP(Transactions[[#This Row],[Account ID]],Accounts[Plaid Account ID],Accounts[Institution Name],"Not Found",0) -> RBC Royal Bank | N13: =IF(Transactions[[#This Row],[Amount]]<0,"credit","debit") -> debit | O13: {=IF( ISNUMBER(MATCH(Transactions[[#This Row],[Categories]], _xlfn._xlws.FILTER(Custom_Cat[Name], LEN(Custom_Cat[Name]) >= 3), 0)), INDEX(Custom_Cat[Custom Category], MATCH(Transactions[[#This Row],[Categories]], _xlfn._xlws.FILTER(Custom_Cat[Name], LEN(Custom_Cat[Name]) >= 3), 0)), IFERROR( INDEX( Custom_Cat[Custom Category], MATCH( 1, (ISNUMBER(SEARCH(LOWER(Custom_Cat[Name]), LOWER(Transactions[[#This Row],[Name]])))) * (LEN(Custom_Cat[Name]) >= 3) * ( (IF(LEFT(Custom_Cat[Amount],1)="<",Transactions[[#This Row],[Amount]]<VALUE(MID(Custom_Cat[Amount], 2, LEN(Custom_Cat[Amount])-1)),TRUE)) * (IF(LEFT(Custom_Cat[Amount],1)=">",Transactions[[#This Row],[Amount]]>VALUE(MID(Custom_Cat[Amount], 2, LEN(Custom_Cat[Amount])-1)),TRUE)) ), 0 ) ), Transactions[[#This Row],[Categories]] ) )} -> Transfer,Internal | P13: =DATE(LEFT(Transactions[[#This Row],[Date]],4),MID(Transactions[[#This Row],[Date]],6,2),MID(Transactions[[#This Row],[Date]],9,2))+IF(RIGHT(Transactions[[#This Row],[Date]],2)="pm",IF(MID(Transactions[[#This Row],[Date]],12,2)<12,0.5,0),IF(MID(Transactions[[#This Row],[Date]],12,2)=12,-0.5,0)) -> 44672 | Q13: =DATE(YEAR(Transactions[[#This Row],[Datetime]]),MONTH(Transactions[[#This Row],[Datetime]]),1) -> 44652 | R13: =AND(Transactions[[#This Row],[Datetime]]>=EDATE(MAX(Transactions[Datetime]),-6),Transactions[[#This Row],[Datetime]]<=TODAY()) -> FALSE | S13: =AVERAGEIFS(Transactions[Month''s Total],Transactions[Recent],TRUE,Transactions[Custom Category],Transactions[[#This Row],[Custom Category]]) -> 14532.99 | T13: =SUMIFS(Transactions[Amount],Transactions[Month],Transactions[[#This Row],[Month]],Transactions[Custom Category],Transactions[[#This Row],[Custom Category]]) -> 8446.13 | U13: =IF(COUNTIF(Budgets[Custom Category],Transactions[[#This Row],[Custom Category]])=0,Transactions[[#This Row],[6M AVG]],_xlfn.XLOOKUP(Transactions[[#This Row],[Custom Category]],Budgets[Custom Category],Budgets[Monthly],0,0)) -> 14532.99 | V13: =IF(Transactions[[#This Row],[Month]]=Sel_Month,Transactions[[#This Row],[Amount]],0) -> 0
... A202: eOMxkwaqNZH7Vznj6o6XTA4KJOvewbhnEVmgd | B202: added | C202: -3000 | D202: Transfer, Credit | E202: 2023-09-10, 8:00:00 p.m. | F202: CAD | H202: e-Transfer - Autodeposit PAULA ANDREA AMARILES RESTREPO C1Avy9FkM43a | I202: other | J202: FALSE | K202: xbwkYxX7zLT9rJvXa0a1swmEBLdAn0hOdw7Yo | L202: =_xlfn.XLOOKUP(Transactions[[#This Row],[Account ID]],Accounts[Plaid Account ID],Accounts[Name],"Not Found",0) -> RBC Staff Banking | M202: =_xlfn.XLOOKUP(Transactions[[#This Row],[Account ID]],Accounts[Plaid Account ID],Accounts[Institution Name],"Not Found",0) -> RBC Royal Bank | N202: =IF(Transactions[[#This Row],[Amount]]<0,"credit","debit") -> credit | O202: {=IF( ISNUMBER(MATCH(Transactions[[#This Row],[Categories]], _xlfn._xlws.FILTER(Custom_Cat[Name], LEN(Custom_Cat[Name]) >= 3), 0)), INDEX(Custom_Cat[Custom Category], MATCH(Transactions[[#This Row],[Categories]], _xlfn._xlws.FILTER(Custom_Cat[Name], LEN(Custom_Cat[Name]) >= 3), 0)), IFERROR( INDEX( Custom_Cat[Custom Category], MATCH( 1, (ISNUMBER(SEARCH(LOWER(Custom_Cat[Name]), LOWER(Transactions[[#This Row],[Name]])))) * (LEN(Custom_Cat[Name]) >= 3) * ( (IF(LEFT(Custom_Cat[Amount],1)="<",Transactions[[#This Row],[Amount]]<VALUE(MID(Custom_Cat[Amount], 2, LEN(Custom_Cat[Amount])-1)),TRUE)) * (IF(LEFT(Custom_Cat[Amount],1)=">",Transactions[[#This Row],[Amount]]>VALUE(MID(Custom_Cat[Amount], 2, LEN(Custom_Cat[Amount])-1)),TRUE)) ), 0 ) ), Transactions[[#This Row],[Categories]] ) )} -> Transfer,Internal | P202: =DATE(LEFT(Transactions[[#This Row],[Date]],4),MID(Transactions[[#This Row],[Date]],6,2),MID(Transactions[[#This Row],[Date]],9,2))+IF(RIGHT(Transactions[[#This Row],[Date]],2)="pm",IF(MID(Transactions[[#This Row],[Date]],12,2)<12,0.5,0),IF(MID(Transactions[[#This Row],[Date]],12,2)=12,-0.5,0)) -> 45179 | Q202: =DATE(YEAR(Transactions[[#This Row],[Datetime]]),MONTH(Transactions[[#This Row],[Datetime]]),1) -> 45170 | R202: =AND(Transactions[[#This Row],[Datetime]]>=EDATE(MAX(Transactions[Datetime]),-6),Transactions[[#This Row],[Datetime]]<=TODAY()) -> FALSE | S202: =AVERAGEIFS(Transactions[Month''s Total],Transactions[Recent],TRUE,Transactions[Custom Category],Transactions[[#This Row],[Custom Category]]) -> 14532.99 | T202: =SUMIFS(Transactions[Amount],Transactions[Month],Transactions[[#This Row],[Month]],Transactions[Custom Category],Transactions[[#This Row],[Custom Category]]) -> -9151.03 | U202: =IF(COUNTIF(Budgets[Custom Category],Transactions[[#This Row],[Custom Category]])=0,Transactions[[#This Row],[6M AVG]],_xlfn.XLOOKUP(Transactions[[#This Row],[Custom Category]],Budgets[Custom Category],Budgets[Monthly],0,0)) -> 14532.99 | V202: =IF(Transactions[[#This Row],[Month]]=Sel_Month,Transactions[[#This Row],[Amount]],0) -> 0
A203: eOMxkwaqNZH7Vznj6o6XTA4KJOvewbhnEVmgd | B203: added | C203: 74.62 | D203: Service, Utilities, Gas | E203: 2023-09-11, 8:00:00 p.m. | F203: CAD | G203: Enbridge Gas | H203: Utility Bill Pmt Enbridge Gas | I203: online | J203: FALSE | K203: 4XBJop63LASgpJk40108SNX9nADgJBHR3Pae1 | L203: =_xlfn.XLOOKUP(Transactions[[#This Row],[Account ID]],Accounts[Plaid Account ID],Accounts[Name],"Not Found",0) -> RBC Staff Banking | M203: =_xlfn.XLOOKUP(Transactions[[#This Row],[Account ID]],Accounts[Plaid Account ID],Accounts[Institution Name],"Not Found",0) -> RBC Royal Bank | N203: =IF(Transactions[[#This Row],[Amount]]<0,"credit","debit") -> debit | O203: {=IF( ISNUMBER(MATCH(Transactions[[#This Row],[Categories]], _xlfn._xlws.FILTER(Custom_Cat[Name], LEN(Custom_Cat[Name]) >= 3), 0)), INDEX(Custom_Cat[Custom Category], MATCH(Transactions[[#This Row],[Categories]], _xlfn._xlws.FILTER(Custom_Cat[Name], LEN(Custom_Cat[Name]) >= 3), 0)), IFERROR( INDEX( Custom_Cat[Custom Category], MATCH( 1, (ISNUMBER(SEARCH(LOWER(Custom_Cat[Name]), LOWER(Transactions[[#This Row],[Name]])))) * (LEN(Custom_Cat[Name]) >= 3) * ( (IF(LEFT(Custom_Cat[Amount],1)="<",Transactions[[#This Row],[Amount]]<VALUE(MID(Custom_Cat[Amount], 2, LEN(Custom_Cat[Amount])-1)),TRUE)) * (IF(LEFT(Custom_Cat[Amount],1)=">",Transactions[[#This Row],[Amount]]>VALUE(MID(Custom_Cat[Amount], 2, LEN(Custom_Cat[Amount])-1)),TRUE)) ), 0 ) ), Transactions[[#This Row],[Categories]] ) )} -> Utilities,Gas | P203: =DATE(LEFT(Transactions[[#This Row],[Date]],4),MID(Transactions[[#This Row],[Date]],6,2),MID(Transactions[[#This Row],[Date]],9,2))+IF(RIGHT(Transactions[[#This Row],[Date]],2)="pm",IF(MID(Transactions[[#This Row],[Date]],12,2)<12,0.5,0),IF(MID(Transactions[[#This Row],[Date]],12,2)=12,-0.5,0)) -> 45180 | Q203: =DATE(YEAR(Transactions[[#This Row],[Datetime]]),MONTH(Transactions[[#This Row],[Datetime]]),1) -> 45170 | R203: =AND(Transactions[[#This Row],[Datetime]]>=EDATE(MAX(Transactions[Datetime]),-6),Transactions[[#This Row],[Datetime]]<=TODAY()) -> FALSE | S203: =AVERAGEIFS(Transactions[Month''s Total],Transactions[Recent],TRUE,Transactions[Custom Category],Transactions[[#This Row],[Custom Category]]) -> 153.08333 | T203: =SUMIFS(Transactions[Amount],Transactions[Month],Transactions[[#This Row],[Month]],Transactions[Custom Category],Transactions[[#This Row],[Custom Category]]) -> 74.62 | U203: =IF(COUNTIF(Budgets[Custom Category],Transactions[[#This Row],[Custom Category]])=0,Transactions[[#This Row],[6M AVG]],_xlfn.XLOOKUP(Transactions[[#This Row],[Custom Category]],Budgets[Custom Category],Budgets[Monthly],0,0)) -> 153.08333 | V203: =IF(Transactions[[#This Row],[Month]]=Sel_Month,Transactions[[#This Row],[Amount]],0) -> 0
A204: eOMxkwaqNZH7Vznj6o6XTA4KJOvewbhnEVmgd | B204: added | C204: 31.38 | D204: Transfer, Debit | E204: 2023-09-12, 8:00:00 p.m. | F204: CAD | H204: e-Transfer sent Manuel Avila TD | I204: other | J204: FALSE | K204: rb4Povp8znTzYwXg9A9rIP8EwJAjozHVXqoYa | L204: =_xlfn.XLOOKUP(Transactions[[#This Row],[Account ID]],Accounts[Plaid Account ID],Accounts[Name],"Not Found",0) -> RBC Staff Banking | M204: =_xlfn.XLOOKUP(Transactions[[#This Row],[Account ID]],Accounts[Plaid Account ID],Accounts[Institution Name],"Not Found",0) -> RBC Royal Bank | N204: =IF(Transactions[[#This Row],[Amount]]<0,"credit","debit") -> debit | O204: {=IF( ISNUMBER(MATCH(Transactions[[#This Row],[Categories]], _xlfn._xlws.FILTER(Custom_Cat[Name], LEN(Custom_Cat[Name]) >= 3), 0)), INDEX(Custom_Cat[Custom Category], MATCH(Transactions[[#This Row],[Categories]], _xlfn._xlws.FILTER(Custom_Cat[Name], LEN(Custom_Cat[Name]) >= 3), 0)), IFERROR( INDEX( Custom_Cat[Custom Category], MATCH( 1, (ISNUMBER(SEARCH(LOWER(Custom_Cat[Name]), LOWER(Transactions[[#This Row],[Name]])))) * (LEN(Custom_Cat[Name]) >= 3) * ( (IF(LEFT(Custom_Cat[Amount],1)="<",Transactions[[#This Row],[Amount]]<VALUE(MID(Custom_Cat[Amount], 2, LEN(Custom_Cat[Amount])-1)),TRUE)) * (IF(LEFT(Custom_Cat[Amount],1)=">",Transactions[[#This Row],[Amount]]>VALUE(MID(Custom_Cat[Amount], 2, LEN(Custom_Cat[Amount])-1)),TRUE)) ), 0 ) ), Transactions[[#This Row],[Categories]] ) )} -> Transfer,Internal | P204: =DATE(LEFT(Transactions[[#This Row],[Date]],4),MID(Transactions[[#This Row],[Date]],6,2),MID(Transactions[[#This Row],[Date]],9,2))+IF(RIGHT(Transactions[[#This Row],[Date]],2)="pm",IF(MID(Transactions[[#This Row],[Date]],12,2)<12,0.5,0),IF(MID(Transactions[[#This Row],[Date]],12,2)=12,-0.5,0)) -> 45181 | Q204: =DATE(YEAR(Transactions[[#This Row],[Datetime]]),MONTH(Transactions[[#This Row],[Datetime]]),1) -> 45170 | R204: =AND(Transactions[[#This Row],[Datetime]]>=EDATE(MAX(Transactions[Datetime]),-6),Transactions[[#This Row],[Datetime]]<=TODAY()) -> FALSE | S204: =AVERAGEIFS(Transactions[Month''s Total],Transactions[Recent],TRUE,Transactions[Custom Category],Transactions[[#This Row],[Custom Category]]) -> 14532.99 | T204: =SUMIFS(Transactions[Amount],Transactions[Month],Transactions[[#This Row],[Month]],Transactions[Custom Category],Transactions[[#This Row],[Custom Category]]) -> -9151.03 | U204: =IF(COUNTIF(Budgets[Custom Category],Transactions[[#This Row],[Custom Category]])=0,Transactions[[#This Row],[6M AVG]],_xlfn.XLOOKUP(Transactions[[#This Row],[Custom Category]],Budgets[Custom Category],Budgets[Monthly],0,0)) -> 14532.99 | V204: =IF(Transactions[[#This Row],[Month]]=Sel_Month,Transactions[[#This Row],[Amount]],0) -> 0
A205: eOMxkwaqNZH7Vznj6o6XTA4KJOvewbhnEVmgd | B205: added | C205: 1505 | D205: Payment | E205: 2023-09-17, 8:00:00 p.m. | F205: CAD | H205: Online Banking payment - 0118 AMEX REGULAR | I205: other | J205: FALSE | K205: 0XDrJpO173S7XKVnMwM4TZO9yeN74wCApZ6y9 | L205: =_xlfn.XLOOKUP(Transactions[[#This Row],[Account ID]],Accounts[Plaid Account ID],Accounts[Name],"Not Found",0) -> RBC Staff Banking | M205: =_xlfn.XLOOKUP(Transactions[[#This Row],[Account ID]],Accounts[Plaid Account ID],Accounts[Institution Name],"Not Found",0) -> RBC Royal Bank | N205: =IF(Transactions[[#This Row],[Amount]]<0,"credit","debit") -> debit | O205: {=IF( ISNUMBER(MATCH(Transactions[[#This Row],[Categories]], _xlfn._xlws.FILTER(Custom_Cat[Name], LEN(Custom_Cat[Name]) >= 3), 0)), INDEX(Custom_Cat[Custom Category], MATCH(Transactions[[#This Row],[Categories]], _xlfn._xlws.FILTER(Custom_Cat[Name], LEN(Custom_Cat[Name]) >= 3), 0)), IFERROR( INDEX( Custom_Cat[Custom Category], MATCH( 1, (ISNUMBER(SEARCH(LOWER(Custom_Cat[Name]), LOWER(Transactions[[#This Row],[Name]])))) * (LEN(Custom_Cat[Name]) >= 3) * ( (IF(LEFT(Custom_Cat[Amount],1)="<",Transactions[[#This Row],[Amount]]<VALUE(MID(Custom_Cat[Amount], 2, LEN(Custom_Cat[Amount])-1)),TRUE)) * (IF(LEFT(Custom_Cat[Amount],1)=">",Transactions[[#This Row],[Amount]]>VALUE(MID(Custom_Cat[Amount], 2, LEN(Custom_Cat[Amount])-1)),TRUE)) ), 0 ) ), Transactions[[#This Row],[Categories]] ) )} -> Transfer,Internal | P205: =DATE(LEFT(Transactions[[#This Row],[Date]],4),MID(Transactions[[#This Row],[Date]],6,2),MID(Transactions[[#This Row],[Date]],9,2))+IF(RIGHT(Transactions[[#This Row],[Date]],2)="pm",IF(MID(Transactions[[#This Row],[Date]],12,2)<12,0.5,0),IF(MID(Transactions[[#This Row],[Date]],12,2)=12,-0.5,0)) -> 45186 | Q205: =DATE(YEAR(Transactions[[#This Row],[Datetime]]),MONTH(Transactions[[#This Row],[Datetime]]),1) -> 45170 | R205: =AND(Transactions[[#This Row],[Datetime]]>=EDATE(MAX(Transactions[Datetime]),-6),Transactions[[#This Row],[Datetime]]<=TODAY()) -> FALSE | S205: =AVERAGEIFS(Transactions[Month''s Total],Transactions[Recent],TRUE,Transactions[Custom Category],Transactions[[#This Row],[Custom Category]]) -> 14532.99 | T205: =SUMIFS(Transactions[Amount],Transactions[Month],Transactions[[#This Row],[Month]],Transactions[Custom Category],Transactions[[#This Row],[Custom Category]]) -> -9151.03 | U205: =IF(COUNTIF(Budgets[Custom Category],Transactions[[#This Row],[Custom Category]])=0,Transactions[[#This Row],[6M AVG]],_xlfn.XLOOKUP(Transactions[[#This Row],[Custom Category]],Budgets[Custom Category],Budgets[Monthly],0,0)) -> 14532.99 | V205: =IF(Transactions[[#This Row],[Month]]=Sel_Month,Transactions[[#This Row],[Amount]],0) -> 0
A206: eOMxkwaqNZH7Vznj6o6XTA4KJOvewbhnEVmgd | B206: added | C206: -1000 | D206: Transfer, Credit | E206: 2023-09-17, 8:00:00 p.m. | F206: CAD | H206: e-Transfer - Autodeposit PAULA ANDREA AMARILES RESTREPO C1AXk5zvYCur | I206: other | J206: FALSE | K206: jOoXrPpkN7HKQmxMzAzLTXvM6gnwZYHexgEAj | L206: =_xlfn.XLOOKUP(Transactions[[#This Row],[Account ID]],Accounts[Plaid Account ID],Accounts[Name],"Not Found",0) -> RBC Staff Banking | M206: =_xlfn.XLOOKUP(Transactions[[#This Row],[Account ID]],Accounts[Plaid Account ID],Accounts[Institution Name],"Not Found",0) -> RBC Royal Bank | N206: =IF(Transactions[[#This Row],[Amount]]<0,"credit","debit") -> credit | O206: {=IF( ISNUMBER(MATCH(Transactions[[#This Row],[Categories]], _xlfn._xlws.FILTER(Custom_Cat[Name], LEN(Custom_Cat[Name]) >= 3), 0)), INDEX(Custom_Cat[Custom Category], MATCH(Transactions[[#This Row],[Categories]], _xlfn._xlws.FILTER(Custom_Cat[Name], LEN(Custom_Cat[Name]) >= 3), 0)), IFERROR( INDEX( Custom_Cat[Custom Category], MATCH( 1, (ISNUMBER(SEARCH(LOWER(Custom_Cat[Name]), LOWER(Transactions[[#This Row],[Name]])))) * (LEN(Custom_Cat[Name]) >= 3) * ( (IF(LEFT(Custom_Cat[Amount],1)="<",Transactions[[#This Row],[Amount]]<VALUE(MID(Custom_Cat[Amount], 2, LEN(Custom_Cat[Amount])-1)),TRUE)) * (IF(LEFT(Custom_Cat[Amount],1)=">",Transactions[[#This Row],[Amount]]>VALUE(MID(Custom_Cat[Amount], 2, LEN(Custom_Cat[Amount])-1)),TRUE)) ), 0 ) ), Transactions[[#This Row],[Categories]] ) )} -> Transfer,Internal | P206: =DATE(LEFT(Transactions[[#This Row],[Date]],4),MID(Transactions[[#This Row],[Date]],6,2),MID(Transactions[[#This Row],[Date]],9,2))+IF(RIGHT(Transactions[[#This Row],[Date]],2)="pm",IF(MID(Transactions[[#This Row],[Date]],12,2)<12,0.5,0),IF(MID(Transactions[[#This Row],[Date]],12,2)=12,-0.5,0)) -> 45186 | Q206: =DATE(YEAR(Transactions[[#This Row],[Datetime]]),MONTH(Transactions[[#This Row],[Datetime]]),1) -> 45170 | R206: =AND(Transactions[[#This Row],[Datetime]]>=EDATE(MAX(Transactions[Datetime]),-6),Transactions[[#This Row],[Datetime]]<=TODAY()) -> FALSE | S206: =AVERAGEIFS(Transactions[Month''s Total],Transactions[Recent],TRUE,Transactions[Custom Category],Transactions[[#This Row],[Custom Category]]) -> 14532.99 | T206: =SUMIFS(Transactions[Amount],Transactions[Month],Transactions[[#This Row],[Month]],Transactions[Custom Category],Transactions[[#This Row],[Custom Category]]) -> -9151.03 | U206: =IF(COUNTIF(Budgets[Custom Category],Transactions[[#This Row],[Custom Category]])=0,Transactions[[#This Row],[6M AVG]],_xlfn.XLOOKUP(Transactions[[#This Row],[Custom Category]],Budgets[Custom Category],Budgets[Monthly],0,0)) -> 14532.99 | V206: =IF(Transactions[[#This Row],[Month]]=Sel_Month,Transactions[[#This Row],[Amount]],0) -> 0
A207: eOMxkwaqNZH7Vznj6o6XTA4KJOvewbhnEVmgd | B207: added | C207: 471.41 | D207: Transfer, Debit | E207: 2023-09-18, 8:00:00 p.m. | F207: CAD | H207: e-Transfer sent Manuel Avila TD | I207: other | J207: FALSE | K207: vbVy94p8zwTZVRYD787pCbvAOBy1zeFVZxwXV | L207: =_xlfn.XLOOKUP(Transactions[[#This Row],[Account ID]],Accounts[Plaid Account ID],Accounts[Name],"Not Found",0) -> RBC Staff Banking | M207: =_xlfn.XLOOKUP(Transactions[[#This Row],[Account ID]],Accounts[Plaid Account ID],Accounts[Institution Name],"Not Found",0) -> RBC Royal Bank | N207: =IF(Transactions[[#This Row],[Amount]]<0,"credit","debit") -> debit | O207: {=IF( ISNUMBER(MATCH(Transactions[[#This Row],[Categories]], _xlfn._xlws.FILTER(Custom_Cat[Name], LEN(Custom_Cat[Name]) >= 3), 0)), INDEX(Custom_Cat[Custom Category], MATCH(Transactions[[#This Row],[Categories]], _xlfn._xlws.FILTER(Custom_Cat[Name], LEN(Custom_Cat[Name]) >= 3), 0)), IFERROR( INDEX( Custom_Cat[Custom Category], MATCH( 1, (ISNUMBER(SEARCH(LOWER(Custom_Cat[Name]), LOWER(Transactions[[#This Row],[Name]])))) * (LEN(Custom_Cat[Name]) >= 3) * ( (IF(LEFT(Custom_Cat[Amount],1)="<",Transactions[[#This Row],[Amount]]<VALUE(MID(Custom_Cat[Amount], 2, LEN(Custom_Cat[Amount])-1)),TRUE)) * (IF(LEFT(Custom_Cat[Amount],1)=">",Transactions[[#This Row],[Amount]]>VALUE(MID(Custom_Cat[Amount], 2, LEN(Custom_Cat[Amount])-1)),TRUE)) ), 0 ) ), Transactions[[#This Row],[Categories]] ) )} -> Transfer,Internal | P207: =DATE(LEFT(Transactions[[#This Row],[Date]],4),MID(Transactions[[#This Row],[Date]],6,2),MID(Transactions[[#This Row],[Date]],9,2))+IF(RIGHT(Transactions[[#This Row],[Date]],2)="pm",IF(MID(Transactions[[#This Row],[Date]],12,2)<12,0.5,0),IF(MID(Transactions[[#This Row],[Date]],12,2)=12,-0.5,0)) -> 45187 | Q207: =DATE(YEAR(Transactions[[#This Row],[Datetime]]),MONTH(Transactions[[#This Row],[Datetime]]),1) -> 45170 | R207: =AND(Transactions[[#This Row],[Datetime]]>=EDATE(MAX(Transactions[Datetime]),-6),Transactions[[#This Row],[Datetime]]<=TODAY()) -> FALSE | S207: =AVERAGEIFS(Transactions[Month''s Total],Transactions[Recent],TRUE,Transactions[Custom Category],Transactions[[#This Row],[Custom Category]]) -> 14532.99 | T207: =SUMIFS(Transactions[Amount],Transactions[Month],Transactions[[#This Row],[Month]],Transactions[Custom Category],Transactions[[#This Row],[Custom Category]]) -> -9151.03 | U207: =IF(COUNTIF(Budgets[Custom Category],Transactions[[#This Row],[Custom Category]])=0,Transactions[[#This Row],[6M AVG]],_xlfn.XLOOKUP(Transactions[[#This Row],[Custom Category]],Budgets[Custom Category],Budgets[Monthly],0,0)) -> 14532.99 | V207: =IF(Transactions[[#This Row],[Month]]=Sel_Month,Transactions[[#This Row],[Amount]],0) -> 0
A208: eOMxkwaqNZH7Vznj6o6XTA4KJOvewbhnEVmgd | B208: added | C208: 2991.86 | D208: Transfer, Debit | E208: 2023-09-20, 8:00:00 p.m. | F208: CAD | H208: Online Banking transfer - 8029 | I208: other | J208: FALSE | K208: 3XqR5pwB6kSDXQKBzEzJcMaqRzJov7Io13XVR | L208: =_xlfn.XLOOKUP(Transactions[[#This Row],[Account ID]],Accounts[Plaid Account ID],Accounts[Name],"Not Found",0) -> RBC Staff Banking | M208: =_xlfn.XLOOKUP(Transactions[[#This Row],[Account ID]],Accounts[Plaid Account ID],Accounts[Institution Name],"Not Found",0) -> RBC Royal Bank | N208: =IF(Transactions[[#This Row],[Amount]]<0,"credit","debit") -> debit | O208: {=IF( ISNUMBER(MATCH(Transactions[[#This Row],[Categories]], _xlfn._xlws.FILTER(Custom_Cat[Name], LEN(Custom_Cat[Name]) >= 3), 0)), INDEX(Custom_Cat[Custom Category], MATCH(Transactions[[#This Row],[Categories]], _xlfn._xlws.FILTER(Custom_Cat[Name], LEN(Custom_Cat[Name]) >= 3), 0)), IFERROR( INDEX( Custom_Cat[Custom Category], MATCH( 1, (ISNUMBER(SEARCH(LOWER(Custom_Cat[Name]), LOWER(Transactions[[#This Row],[Name]])))) * (LEN(Custom_Cat[Name]) >= 3) * ( (IF(LEFT(Custom_Cat[Amount],1)="<",Transactions[[#This Row],[Amount]]<VALUE(MID(Custom_Cat[Amount], 2, LEN(Custom_Cat[Amount])-1)),TRUE)) * (IF(LEFT(Custom_Cat[Amount],1)=">",Transactions[[#This Row],[Amount]]>VALUE(MID(Custom_Cat[Amount], 2, LEN(Custom_Cat[Amount])-1)),TRUE)) ), 0 ) ), Transactions[[#This Row],[Categories]] ) )} -> Transfer, Debit | P208: =DATE(LEFT(Transactions[[#This Row],[Date]],4),MID(Transactions[[#This Row],[Date]],6,2),MID(Transactions[[#This Row],[Date]],9,2))+IF(RIGHT(Transactions[[#This Row],[Date]],2)="pm",IF(MID(Transactions[[#This Row],[Date]],12,2)<12,0.5,0),IF(MID(Transactions[[#This Row],[Date]],12,2)=12,-0.5,0)) -> 45189 | Q208: =DATE(YEAR(Transactions[[#This Row],[Datetime]]),MONTH(Transactions[[#This Row],[Datetime]]),1) -> 45170 | R208: =AND(Transactions[[#This Row],[Datetime]]>=EDATE(MAX(Transactions[Datetime]),-6),Transactions[[#This Row],[Datetime]]<=TODAY()) -> FALSE | S208: =AVERAGEIFS(Transactions[Month''s Total],Transactions[Recent],TRUE,Transactions[Custom Category],Transactions[[#This Row],[Custom Category]]) -> 12758.461 | T208: =SUMIFS(Transactions[Amount],Transactions[Month],Transactions[[#This Row],[Month]],Transactions[Custom Category],Transactions[[#This Row],[Custom Category]]) -> 2991.86 | U208: =IF(COUNTIF(Budgets[Custom Category],Transactions[[#This Row],[Custom Category]])=0,Transactions[[#This Row],[6M AVG]],_xlfn.XLOOKUP(Transactions[[#This Row],[Custom Category]],Budgets[Custom Category],Budgets[Monthly],0,0)) -> 12758.461 | V208: =IF(Transactions[[#This Row],[Month]]=Sel_Month,Transactions[[#This Row],[Amount]],0) -> 0
A209: eOMxkwaqNZH7Vznj6o6XTA4KJOvewbhnEVmgd | B209: added | C209: 6.5 | D209: Transfer, Debit | E209: 2023-09-20, 8:00:00 p.m. | F209: CAD | H209: e-Transfer sent Manuel CIBC | I209: other | J209: FALSE | K209: yb6XYJp8zDT3z0Oj6P61uAR95LwZj7TpQewrK | L209: =_xlfn.XLOOKUP(Transactions[[#This Row],[Account ID]],Accounts[Plaid Account ID],Accounts[Name],"Not Found",0) -> RBC Staff Banking | M209: =_xlfn.XLOOKUP(Transactions[[#This Row],[Account ID]],Accounts[Plaid Account ID],Accounts[Institution Name],"Not Found",0) -> RBC Royal Bank | N209: =IF(Transactions[[#This Row],[Amount]]<0,"credit","debit") -> debit | O209: {=IF( ISNUMBER(MATCH(Transactions[[#This Row],[Categories]], _xlfn._xlws.FILTER(Custom_Cat[Name], LEN(Custom_Cat[Name]) >= 3), 0)), INDEX(Custom_Cat[Custom Category], MATCH(Transactions[[#This Row],[Categories]], _xlfn._xlws.FILTER(Custom_Cat[Name], LEN(Custom_Cat[Name]) >= 3), 0)), IFERROR( INDEX( Custom_Cat[Custom Category], MATCH( 1, (ISNUMBER(SEARCH(LOWER(Custom_Cat[Name]), LOWER(Transactions[[#This Row],[Name]])))) * (LEN(Custom_Cat[Name]) >= 3) * ( (IF(LEFT(Custom_Cat[Amount],1)="<",Transactions[[#This Row],[Amount]]<VALUE(MID(Custom_Cat[Amount], 2, LEN(Custom_Cat[Amount])-1)),TRUE)) * (IF(LEFT(Custom_Cat[Amount],1)=">",Transactions[[#This Row],[Amount]]>VALUE(MID(Custom_Cat[Amount], 2, LEN(Custom_Cat[Amount])-1)),TRUE)) ), 0 ) ), Transactions[[#This Row],[Categories]] ) )} -> Transfer,Internal | P209: =DATE(LEFT(Transactions[[#This Row],[Date]],4),MID(Transactions[[#This Row],[Date]],6,2),MID(Transactions[[#This Row],[Date]],9,2))+IF(RIGHT(Transactions[[#This Row],[Date]],2)="pm",IF(MID(Transactions[[#This Row],[Date]],12,2)<12,0.5,0),IF(MID(Transactions[[#This Row],[Date]],12,2)=12,-0.5,0)) -> 45189 | Q209: =DATE(YEAR(Transactions[[#This Row],[Datetime]]),MONTH(Transactions[[#This Row],[Datetime]]),1) -> 45170 | R209: =AND(Transactions[[#This Row],[Datetime]]>=EDATE(MAX(Transactions[Datetime]),-6),Transactions[[#This Row],[Datetime]]<=TODAY()) -> FALSE | S209: =AVERAGEIFS(Transactions[Month''s Total],Transactions[Recent],TRUE,Transactions[Custom Category],Transactions[[#This Row],[Custom Category]]) -> 14532.99 | T209: =SUMIFS(Transactions[Amount],Transactions[Month],Transactions[[#This Row],[Month]],Transactions[Custom Category],Transactions[[#This Row],[Custom Category]]) -> -9151.03 | U209: =IF(COUNTIF(Budgets[Custom Category],Transactions[[#This Row],[Custom Category]])=0,Transactions[[#This Row],[6M AVG]],_xlfn.XLOOKUP(Transactions[[#This Row],[Custom Category]],Budgets[Custom Category],Budgets[Monthly],0,0)) -> 14532.99 | V209: =IF(Transactions[[#This Row],[Month]]=Sel_Month,Transactions[[#This Row],[Amount]],0) -> 0
A210: eOMxkwaqNZH7Vznj6o6XTA4KJOvewbhnEVmgd | B210: added | C210: 6.5 | D210: Transfer, Debit | E210: 2023-09-20, 8:00:00 p.m. | F210: CAD | H210: e-Transfer sent Manuel CIBC | I210: other | J210: FALSE | K210: KYmvezN0bnso8Rk5dDdyTx4XOVejyKUE9aOnZ | L210: =_xlfn.XLOOKUP(Transactions[[#This Row],[Account ID]],Accounts[Plaid Account ID],Accounts[Name],"Not Found",0) -> RBC Staff Banking | M210: =_xlfn.XLOOKUP(Transactions[[#This Row],[Account ID]],Accounts[Plaid Account ID],Accounts[Institution Name],"Not Found",0) -> RBC Royal Bank | N210: =IF(Transactions[[#This Row],[Amount]]<0,"credit","debit") -> debit | O210: {=IF( ISNUMBER(MATCH(Transactions[[#This Row],[Categories]], _xlfn._xlws.FILTER(Custom_Cat[Name], LEN(Custom_Cat[Name]) >= 3), 0)), INDEX(Custom_Cat[Custom Category], MATCH(Transactions[[#This Row],[Categories]], _xlfn._xlws.FILTER(Custom_Cat[Name], LEN(Custom_Cat[Name]) >= 3), 0)), IFERROR( INDEX( Custom_Cat[Custom Category], MATCH( 1, (ISNUMBER(SEARCH(LOWER(Custom_Cat[Name]), LOWER(Transactions[[#This Row],[Name]])))) * (LEN(Custom_Cat[Name]) >= 3) * ( (IF(LEFT(Custom_Cat[Amount],1)="<",Transactions[[#This Row],[Amount]]<VALUE(MID(Custom_Cat[Amount], 2, LEN(Custom_Cat[Amount])-1)),TRUE)) * (IF(LEFT(Custom_Cat[Amount],1)=">",Transactions[[#This Row],[Amount]]>VALUE(MID(Custom_Cat[Amount], 2, LEN(Custom_Cat[Amount])-1)),TRUE)) ), 0 ) ), Transactions[[#This Row],[Categories]] ) )} -> Transfer,Internal | P210: =DATE(LEFT(Transactions[[#This Row],[Date]],4),MID(Transactions[[#This Row],[Date]],6,2),MID(Transactions[[#This Row],[Date]],9,2))+IF(RIGHT(Transactions[[#This Row],[Date]],2)="pm",IF(MID(Transactions[[#This Row],[Date]],12,2)<12,0.5,0),IF(MID(Transactions[[#This Row],[Date]],12,2)=12,-0.5,0)) -> 45189 | Q210: =DATE(YEAR(Transactions[[#This Row],[Datetime]]),MONTH(Transactions[[#This Row],[Datetime]]),1) -> 45170 | R210: =AND(Transactions[[#This Row],[Datetime]]>=EDATE(MAX(Transactions[Datetime]),-6),Transactions[[#This Row],[Datetime]]<=TODAY()) -> FALSE | S210: =AVERAGEIFS(Transactions[Month''s Total],Transactions[Recent],TRUE,Transactions[Custom Category],Transactions[[#This Row],[Custom Category]]) -> 14532.99 | T210: =SUMIFS(Transactions[Amount],Transactions[Month],Transactions[[#This Row],[Month]],Transactions[Custom Category],Transactions[[#This Row],[Custom Category]]) -> -9151.03 | U210: =IF(COUNTIF(Budgets[Custom Category],Transactions[[#This Row],[Custom Category]])=0,Transactions[[#This Row],[6M AVG]],_xlfn.XLOOKUP(Transactions[[#This Row],[Custom Category]],Budgets[Custom Category],Budgets[Monthly],0,0)) -> 14532.99 | V210: =IF(Transactions[[#This Row],[Month]]=Sel_Month,Transactions[[#This Row],[Amount]],0) -> 0
A211: eOMxkwaqNZH7Vznj6o6XTA4KJOvewbhnEVmgd | B211: added | C211: -2000 | D211: Transfer, Credit | E211: 2023-09-20, 8:00:00 p.m. | F211: CAD | H211: e-Transfer - Autodeposit PAULA ANDREA AMARILES RESTREPO C1AhjycnZYz8 | I211: other | J211: FALSE | K211: kObx4qpAm9HOVm5g9D90iNbgweVADmHo5zk69 | L211: =_xlfn.XLOOKUP(Transactions[[#This Row],[Account ID]],Accounts[Plaid Account ID],Accounts[Name],"Not Found",0) -> RBC Staff Banking | M211: =_xlfn.XLOOKUP(Transactions[[#This Row],[Account ID]],Accounts[Plaid Account ID],Accounts[Institution Name],"Not Found",0) -> RBC Royal Bank | N211: =IF(Transactions[[#This Row],[Amount]]<0,"credit","debit") -> credit | O211: {=IF( ISNUMBER(MATCH(Transactions[[#This Row],[Categories]], _xlfn._xlws.FILTER(Custom_Cat[Name], LEN(Custom_Cat[Name]) >= 3), 0)), INDEX(Custom_Cat[Custom Category], MATCH(Transactions[[#This Row],[Categories]], _xlfn._xlws.FILTER(Custom_Cat[Name], LEN(Custom_Cat[Name]) >= 3), 0)), IFERROR( INDEX( Custom_Cat[Custom Category], MATCH( 1, (ISNUMBER(SEARCH(LOWER(Custom_Cat[Name]), LOWER(Transactions[[#This Row],[Name]])))) * (LEN(Custom_Cat[Name]) >= 3) * ( (IF(LEFT(Custom_Cat[Amount],1)="<",Transactions[[#This Row],[Amount]]<VALUE(MID(Custom_Cat[Amount], 2, LEN(Custom_Cat[Amount])-1)),TRUE)) * (IF(LEFT(Custom_Cat[Amount],1)=">",Transactions[[#This Row],[Amount]]>VALUE(MID(Custom_Cat[Amount], 2, LEN(Custom_Cat[Amount])-1)),TRUE)) ), 0 ) ), Transactions[[#This Row],[Categories]] ) )} -> Transfer,Internal | P211: =DATE(LEFT(Transactions[[#This Row],[Date]],4),MID(Transactions[[#This Row],[Date]],6,2),MID(Transactions[[#This Row],[Date]],9,2))+IF(RIGHT(Transactions[[#This Row],[Date]],2)="pm",IF(MID(Transactions[[#This Row],[Date]],12,2)<12,0.5,0),IF(MID(Transactions[[#This Row],[Date]],12,2)=12,-0.5,0)) -> 45189 | Q211: =DATE(YEAR(Transactions[[#This Row],[Datetime]]),MONTH(Transactions[[#This Row],[Datetime]]),1) -> 45170 | R211: =AND(Transactions[[#This Row],[Datetime]]>=EDATE(MAX(Transactions[Datetime]),-6),Transactions[[#This Row],[Datetime]]<=TODAY()) -> FALSE | S211: =AVERAGEIFS(Transactions[Month''s Total],Transactions[Recent],TRUE,Transactions[Custom Category],Transactions[[#This Row],[Custom Category]]) -> 14532.99 | T211: =SUMIFS(Transactions[Amount],Transactions[Month],Transactions[[#This Row],[Month]],Transactions[Custom Category],Transactions[[#This Row],[Custom Category]]) -> -9151.03 | U211: =IF(COUNTIF(Budgets[Custom Category],Transactions[[#This Row],[Custom Category]])=0,Transactions[[#This Row],[6M AVG]],_xlfn.XLOOKUP(Transactions[[#This Row],[Custom Category]],Budgets[Custom Category],Budgets[Monthly],0,0)) -> 14532.99 | V211: =IF(Transactions[[#This Row],[Month]]=Sel_Month,Transactions[[#This Row],[Amount]],0) -> 0
A212: eOMxkwaqNZH7Vznj6o6XTA4KJOvewbhnEVmgd | B212: added | C212: -6.5 | D212: Transfer, Credit | E212: 2023-09-20, 8:00:00 p.m. | F212: CAD | H212: e-Transfer cancel | I212: other | J212: FALSE | K212: AXN3ez01jbS3APoek4kdu09LwN1vAaCMVrmY6 | L212: =_xlfn.XLOOKUP(Transactions[[#This Row],[Account ID]],Accounts[Plaid Account ID],Accounts[Name],"Not Found",0) -> RBC Staff Banking | M212: =_xlfn.XLOOKUP(Transactions[[#This Row],[Account ID]],Accounts[Plaid Account ID],Accounts[Institution Name],"Not Found",0) -> RBC Royal Bank | N212: =IF(Transactions[[#This Row],[Amount]]<0,"credit","debit") -> credit | O212: {=IF( ISNUMBER(MATCH(Transactions[[#This Row],[Categories]], _xlfn._xlws.FILTER(Custom_Cat[Name], LEN(Custom_Cat[Name]) >= 3), 0)), INDEX(Custom_Cat[Custom Category], MATCH(Transactions[[#This Row],[Categories]], _xlfn._xlws.FILTER(Custom_Cat[Name], LEN(Custom_Cat[Name]) >= 3), 0)), IFERROR( INDEX( Custom_Cat[Custom Category], MATCH( 1, (ISNUMBER(SEARCH(LOWER(Custom_Cat[Name]), LOWER(Transactions[[#This Row],[Name]])))) * (LEN(Custom_Cat[Name]) >= 3) * ( (IF(LEFT(Custom_Cat[Amount],1)="<",Transactions[[#This Row],[Amount]]<VALUE(MID(Custom_Cat[Amount], 2, LEN(Custom_Cat[Amount])-1)),TRUE)) * (IF(LEFT(Custom_Cat[Amount],1)=">",Transactions[[#This Row],[Amount]]>VALUE(MID(Custom_Cat[Amount], 2, LEN(Custom_Cat[Amount])-1)),TRUE)) ), 0 ) ), Transactions[[#This Row],[Categories]] ) )} -> Transfer, Credit | P212: =DATE(LEFT(Transactions[[#This Row],[Date]],4),MID(Transactions[[#This Row],[Date]],6,2),MID(Transactions[[#This Row],[Date]],9,2))+IF(RIGHT(Transactions[[#This Row],[Date]],2)="pm",IF(MID(Transactions[[#This Row],[Date]],12,2)<12,0.5,0),IF(MID(Transactions[[#This Row],[Date]],12,2)=12,-0.5,0)) -> 45189 | Q212: =DATE(YEAR(Transactions[[#This Row],[Datetime]]),MONTH(Transactions[[#This Row],[Datetime]]),1) -> 45170 | R212: =AND(Transactions[[#This Row],[Datetime]]>=EDATE(MAX(Transactions[Datetime]),-6),Transactions[[#This Row],[Datetime]]<=TODAY()) -> FALSE | S212: =AVERAGEIFS(Transactions[Month''s Total],Transactions[Recent],TRUE,Transactions[Custom Category],Transactions[[#This Row],[Custom Category]]) -> -333.34667 | T212: =SUMIFS(Transactions[Amount],Transactions[Month],Transactions[[#This Row],[Month]],Transactions[Custom Category],Transactions[[#This Row],[Custom Category]]) -> -6.5 | U212: =IF(COUNTIF(Budgets[Custom Category],Transactions[[#This Row],[Custom Category]])=0,Transactions[[#This Row],[6M AVG]],_xlfn.XLOOKUP(Transactions[[#This Row],[Custom Category]],Budgets[Custom Category],Budgets[Monthly],0,0)) -> -333.34667 | V212: =IF(Transactions[[#This Row],[Month]]=Sel_Month,Transactions[[#This Row],[Amount]],0) -> 0
A213: eOMxkwaqNZH7Vznj6o6XTA4KJOvewbhnEVmgd | B213: added | C213: 376.27 | D213: Transfer, Debit | E213: 2023-09-28, 8:00:00 p.m. | F213: CAD | H213: e-Transfer sent Manuel Avila TD | I213: other | J213: FALSE | K213: BXVyezjPrgSxXRna9M9wIa65QjPRpru3BPmgm | L213: =_xlfn.XLOOKUP(Transactions[[#This Row],[Account ID]],Accounts[Plaid Account ID],Accounts[Name],"Not Found",0) -> RBC Staff Banking | M213: =_xlfn.XLOOKUP(Transactions[[#This Row],[Account ID]],Accounts[Plaid Account ID],Accounts[Institution Name],"Not Found",0) -> RBC Royal Bank | N213: =IF(Transactions[[#This Row],[Amount]]<0,"credit","debit") -> debit | O213: {=IF( ISNUMBER(MATCH(Transactions[[#This Row],[Categories]], _xlfn._xlws.FILTER(Custom_Cat[Name], LEN(Custom_Cat[Name]) >= 3), 0)), INDEX(Custom_Cat[Custom Category], MATCH(Transactions[[#This Row],[Categories]], _xlfn._xlws.FILTER(Custom_Cat[Name], LEN(Custom_Cat[Name]) >= 3), 0)), IFERROR( INDEX( Custom_Cat[Custom Category], MATCH( 1, (ISNUMBER(SEARCH(LOWER(Custom_Cat[Name]), LOWER(Transactions[[#This Row],[Name]])))) * (LEN(Custom_Cat[Name]) >= 3) * ( (IF(LEFT(Custom_Cat[Amount],1)="<",Transactions[[#This Row],[Amount]]<VALUE(MID(Custom_Cat[Amount], 2, LEN(Custom_Cat[Amount])-1)),TRUE)) * (IF(LEFT(Custom_Cat[Amount],1)=">",Transactions[[#This Row],[Amount]]>VALUE(MID(Custom_Cat[Amount], 2, LEN(Custom_Cat[Amount])-1)),TRUE)) ), 0 ) ), Transactions[[#This Row],[Categories]] ) )} -> Transfer,Internal | P213: =DATE(LEFT(Transactions[[#This Row],[Date]],4),MID(Transactions[[#This Row],[Date]],6,2),MID(Transactions[[#This Row],[Date]],9,2))+IF(RIGHT(Transactions[[#This Row],[Date]],2)="pm",IF(MID(Transactions[[#This Row],[Date]],12,2)<12,0.5,0),IF(MID(Transactions[[#This Row],[Date]],12,2)=12,-0.5,0)) -> 45197 | Q213: =DATE(YEAR(Transactions[[#This Row],[Datetime]]),MONTH(Transactions[[#This Row],[Datetime]]),1) -> 45170 | R213: =AND(Transactions[[#This Row],[Datetime]]>=EDATE(MAX(Transactions[Datetime]),-6),Transactions[[#This Row],[Datetime]]<=TODAY()) -> FALSE | S213: =AVERAGEIFS(Transactions[Month''s Total],Transactions[Recent],TRUE,Transactions[Custom Category],Transactions[[#This Row],[Custom Category]]) -> 14532.99 | T213: =SUMIFS(Transactions[Amount],Transactions[Month],Transactions[[#This Row],[Month]],Transactions[Custom Category],Transactions[[#This Row],[Custom Category]]) -> -9151.03 | U213: =IF(COUNTIF(Budgets[Custom Category],Transactions[[#This Row],[Custom Category]])=0,Transactions[[#This Row],[6M AVG]],_xlfn.XLOOKUP(Transactions[[#This Row],[Custom Category]],Budgets[Custom Category],Budgets[Monthly],0,0)) -> 14532.99 | V213: =IF(Transactions[[#This Row],[Month]]=Sel_Month,Transactions[[#This Row],[Amount]],0) -> 0
A214: eOMxkwaqNZH7Vznj6o6XTA4KJOvewbhnEVmgd | B214: added | C214: 2500 | D214: Transfer, Debit | E214: 2023-10-02, 8:00:00 p.m. | F214: CAD | H214: e-Transfer sent Manuel Avila TD | I214: other | J214: FALSE | K214: 6XyrgpDK10SB8yvazqz5CNov40aVwOHw8gnqX | L214: =_xlfn.XLOOKUP(Transactions[[#This Row],[Account ID]],Accounts[Plaid Account ID],Accounts[Name],"Not Found",0) -> RBC Staff Banking | M214: =_xlfn.XLOOKUP(Transactions[[#This Row],[Account ID]],Accounts[Plaid Account ID],Accounts[Institution Name],"Not Found",0) -> RBC Royal Bank | N214: =IF(Transactions[[#This Row],[Amount]]<0,"credit","debit") -> debit | O214: {=IF( ISNUMBER(MATCH(Transactions[[#This Row],[Categories]], _xlfn._xlws.FILTER(Custom_Cat[Name], LEN(Custom_Cat[Name]) >= 3), 0)), INDEX(Custom_Cat[Custom Category], MATCH(Transactions[[#This Row],[Categories]], _xlfn._xlws.FILTER(Custom_Cat[Name], LEN(Custom_Cat[Name]) >= 3), 0)), IFERROR( INDEX( Custom_Cat[Custom Category], MATCH( 1, (ISNUMBER(SEARCH(LOWER(Custom_Cat[Name]), LOWER(Transactions[[#This Row],[Name]])))) * (LEN(Custom_Cat[Name]) >= 3) * ( (IF(LEFT(Custom_Cat[Amount],1)="<",Transactions[[#This Row],[Amount]]<VALUE(MID(Custom_Cat[Amount], 2, LEN(Custom_Cat[Amount])-1)),TRUE)) * (IF(LEFT(Custom_Cat[Amount],1)=">",Transactions[[#This Row],[Amount]]>VALUE(MID(Custom_Cat[Amount], 2, LEN(Custom_Cat[Amount])-1)),TRUE)) ), 0 ) ), Transactions[[#This Row],[Categories]] ) )} -> Transfer,Internal | P214: =DATE(LEFT(Transactions[[#This Row],[Date]],4),MID(Transactions[[#This Row],[Date]],6,2),MID(Transactions[[#This Row],[Date]],9,2))+IF(RIGHT(Transactions[[#This Row],[Date]],2)="pm",IF(MID(Transactions[[#This Row],[Date]],12,2)<12,0.5,0),IF(MID(Transactions[[#This Row],[Date]],12,2)=12,-0.5,0)) -> 45201 | Q214: =DATE(YEAR(Transactions[[#This Row],[Datetime]]),MONTH(Transactions[[#This Row],[Datetime]]),1) -> 45200 | R214: =AND(Transactions[[#This Row],[Datetime]]>=EDATE(MAX(Transactions[Datetime]),-6),Transactions[[#This Row],[Datetime]]<=TODAY()) -> FALSE | S214: =AVERAGEIFS(Transactions[Month''s Total],Transactions[Recent],TRUE,Transactions[Custom Category],Transactions[[#This Row],[Custom Category]]) -> 14532.99 | T214: =SUMIFS(Transactions[Amount],Transactions[Month],Transactions[[#This Row],[Month]],Transactions[Custom Category],Transactions[[#This Row],[Custom Category]]) -> 3947.82 | U214: =IF(COUNTIF(Budgets[Custom Category],Transactions[[#This Row],[Custom Category]])=0,Transactions[[#This Row],[6M AVG]],_xlfn.XLOOKUP(Transactions[[#This Row],[Custom Category]],Budgets[Custom Category],Budgets[Monthly],0,0)) -> 14532.99 | V214: =IF(Transactions[[#This Row],[Month]]=Sel_Month,Transactions[[#This Row],[Amount]],0) -> 0
A215: eOMxkwaqNZH7Vznj6o6XTA4KJOvewbhnEVmgd | B215: added | C215: 2292.07 | D215: Transfer, Debit | E215: 2023-10-02, 8:00:00 p.m. | F215: CAD | H215: e-Transfer sent Manuel CIBC | I215: other | J215: FALSE | K215: LNJEezRjgpuv83A7wmwKTZaP56woj1CZqb5NV | L215: =_xlfn.XLOOKUP(Transactions[[#This Row],[Account ID]],Accounts[Plaid Account ID],Accounts[Name],"Not Found",0) -> RBC Staff Banking | M215: =_xlfn.XLOOKUP(Transactions[[#This Row],[Account ID]],Accounts[Plaid Account ID],Accounts[Institution Name],"Not Found",0) -> RBC Royal Bank | N215: =IF(Transactions[[#This Row],[Amount]]<0,"credit","debit") -> debit | O215: {=IF( ISNUMBER(MATCH(Transactions[[#This Row],[Categories]], _xlfn._xlws.FILTER(Custom_Cat[Name], LEN(Custom_Cat[Name]) >= 3), 0)), INDEX(Custom_Cat[Custom Category], MATCH(Transactions[[#This Row],[Categories]], _xlfn._xlws.FILTER(Custom_Cat[Name], LEN(Custom_Cat[Name]) >= 3), 0)), IFERROR( INDEX( Custom_Cat[Custom Category], MATCH( 1, (ISNUMBER(SEARCH(LOWER(Custom_Cat[Name]), LOWER(Transactions[[#This Row],[Name]])))) * (LEN(Custom_Cat[Name]) >= 3) * ( (IF(LEFT(Custom_Cat[Amount],1)="<",Transactions[[#This Row],[Amount]]<VALUE(MID(Custom_Cat[Amount], 2, LEN(Custom_Cat[Amount])-1)),TRUE)) * (IF(LEFT(Custom_Cat[Amount],1)=">",Transactions[[#This Row],[Amount]]>VALUE(MID(Custom_Cat[Amount], 2, LEN(Custom_Cat[Amount])-1)),TRUE)) ), 0 ) ), Transactions[[#This Row],[Categories]] ) )} -> Transfer,Internal | P215: =DATE(LEFT(Transactions[[#This Row],[Date]],4),MID(Transactions[[#This Row],[Date]],6,2),MID(Transactions[[#This Row],[Date]],9,2))+IF(RIGHT(Transactions[[#This Row],[Date]],2)="pm",IF(MID(Transactions[[#This Row],[Date]],12,2)<12,0.5,0),IF(MID(Transactions[[#This Row],[Date]],12,2)=12,-0.5,0)) -> 45201 | Q215: =DATE(YEAR(Transactions[[#This Row],[Datetime]]),MONTH(Transactions[[#This Row],[Datetime]]),1) -> 45200 | R215: =AND(Transactions[[#This Row],[Datetime]]>=EDATE(MAX(Transactions[Datetime]),-6),Transactions[[#This Row],[Datetime]]<=TODAY()) -> FALSE | S215: =AVERAGEIFS(Transactions[Month''s Total],Transactions[Recent],TRUE,Transactions[Custom Category],Transactions[[#This Row],[Custom Category]]) -> 14532.99 | T215: =SUMIFS(Transactions[Amount],Transactions[Month],Transactions[[#This Row],[Month]],Transactions[Custom Category],Transactions[[#This Row],[Custom Category]]) -> 3947.82 | U215: =IF(COUNTIF(Budgets[Custom Category],Transactions[[#This Row],[Custom Category]])=0,Transactions[[#This Row],[6M AVG]],_xlfn.XLOOKUP(Transactions[[#This Row],[Custom Category]],Budgets[Custom Category],Budgets[Monthly],0,0)) -> 14532.99 | V215: =IF(Transactions[[#This Row],[Month]]=Sel_Month,Transactions[[#This Row],[Amount]],0) -> 0
... A219: eOMxkwaqNZH7Vznj6o6XTA4KJOvewbhnEVmgd | B219: added | C219: -417.84 | D219: Bank Fees, Foreign Transaction | E219: 2023-10-02, 8:00:00 p.m. | F219: CAD | H219: Online Banking foreign exchange Ref 3WW342761132220 | I219: other | J219: FALSE | K219: qbx15Ap8zQTerAqKYXY1SVoL9aNBdRIDdmRqw | L219: =_xlfn.XLOOKUP(Transactions[[#This Row],[Account ID]],Accounts[Plaid Account ID],Accounts[Name],"Not Found",0) -> RBC Staff Banking | M219: =_xlfn.XLOOKUP(Transactions[[#This Row],[Account ID]],Accounts[Plaid Account ID],Accounts[Institution Name],"Not Found",0) -> RBC Royal Bank | N219: =IF(Transactions[[#This Row],[Amount]]<0,"credit","debit") -> credit | O219: {=IF( ISNUMBER(MATCH(Transactions[[#This Row],[Categories]], _xlfn._xlws.FILTER(Custom_Cat[Name], LEN(Custom_Cat[Name]) >= 3), 0)), INDEX(Custom_Cat[Custom Category], MATCH(Transactions[[#This Row],[Categories]], _xlfn._xlws.FILTER(Custom_Cat[Name], LEN(Custom_Cat[Name]) >= 3), 0)), IFERROR( INDEX( Custom_Cat[Custom Category], MATCH( 1, (ISNUMBER(SEARCH(LOWER(Custom_Cat[Name]), LOWER(Transactions[[#This Row],[Name]])))) * (LEN(Custom_Cat[Name]) >= 3) * ( (IF(LEFT(Custom_Cat[Amount],1)="<",Transactions[[#This Row],[Amount]]<VALUE(MID(Custom_Cat[Amount], 2, LEN(Custom_Cat[Amount])-1)),TRUE)) * (IF(LEFT(Custom_Cat[Amount],1)=">",Transactions[[#This Row],[Amount]]>VALUE(MID(Custom_Cat[Amount], 2, LEN(Custom_Cat[Amount])-1)),TRUE)) ), 0 ) ), Transactions[[#This Row],[Categories]] ) )} -> Income,Salary | P219: =DATE(LEFT(Transactions[[#This Row],[Date]],4),MID(Transactions[[#This Row],[Date]],6,2),MID(Transactions[[#This Row],[Date]],9,2))+IF(RIGHT(Transactions[[#This Row],[Date]],2)="pm",IF(MID(Transactions[[#This Row],[Date]],12,2)<12,0.5,0),IF(MID(Transactions[[#This Row],[Date]],12,2)=12,-0.5,0)) -> 45201 | Q219: =DATE(YEAR(Transactions[[#This Row],[Datetime]]),MONTH(Transactions[[#This Row],[Datetime]]),1) -> 45200 | R219: =AND(Transactions[[#This Row],[Datetime]]>=EDATE(MAX(Transactions[Datetime]),-6),Transactions[[#This Row],[Datetime]]<=TODAY()) -> FALSE | S219: =AVERAGEIFS(Transactions[Month''s Total],Transactions[Recent],TRUE,Transactions[Custom Category],Transactions[[#This Row],[Custom Category]]) -> -18125.097 | T219: =SUMIFS(Transactions[Amount],Transactions[Month],Transactions[[#This Row],[Month]],Transactions[Custom Category],Transactions[[#This Row],[Custom Category]]) -> -1434.43 | U219: =IF(COUNTIF(Budgets[Custom Category],Transactions[[#This Row],[Custom Category]])=0,Transactions[[#This Row],[6M AVG]],_xlfn.XLOOKUP(Transactions[[#This Row],[Custom Category]],Budgets[Custom Category],Budgets[Monthly],0,0)) -> -18125.097 | V219: =IF(Transactions[[#This Row],[Month]]=Sel_Month,Transactions[[#This Row],[Amount]],0) -> 0
A220: eOMxkwaqNZH7Vznj6o6XTA4KJOvewbhnEVmgd | B220: added | C220: 192.58 | D220: Service, Financial, Loans and Mortgages | E220: 2023-10-05, 8:00:00 p.m. | F220: CAD | G220: Personal Loan Spl | H220: Personal Loan SPL | I220: online | J220: FALSE | K220: mN4wx3p0zOuZMxmrzRzyCq8rkQPRe6uBbgaRP | L220: =_xlfn.XLOOKUP(Transactions[[#This Row],[Account ID]],Accounts[Plaid Account ID],Accounts[Name],"Not Found",0) -> RBC Staff Banking | M220: =_xlfn.XLOOKUP(Transactions[[#This Row],[Account ID]],Accounts[Plaid Account ID],Accounts[Institution Name],"Not Found",0) -> RBC Royal Bank | N220: =IF(Transactions[[#This Row],[Amount]]<0,"credit","debit") -> debit | O220: {=IF( ISNUMBER(MATCH(Transactions[[#This Row],[Categories]], _xlfn._xlws.FILTER(Custom_Cat[Name], LEN(Custom_Cat[Name]) >= 3), 0)), INDEX(Custom_Cat[Custom Category], MATCH(Transactions[[#This Row],[Categories]], _xlfn._xlws.FILTER(Custom_Cat[Name], LEN(Custom_Cat[Name]) >= 3), 0)), IFERROR( INDEX( Custom_Cat[Custom Category], MATCH( 1, (ISNUMBER(SEARCH(LOWER(Custom_Cat[Name]), LOWER(Transactions[[#This Row],[Name]])))) * (LEN(Custom_Cat[Name]) >= 3) * ( (IF(LEFT(Custom_Cat[Amount],1)="<",Transactions[[#This Row],[Amount]]<VALUE(MID(Custom_Cat[Amount], 2, LEN(Custom_Cat[Amount])-1)),TRUE)) * (IF(LEFT(Custom_Cat[Amount],1)=">",Transactions[[#This Row],[Amount]]>VALUE(MID(Custom_Cat[Amount], 2, LEN(Custom_Cat[Amount])-1)),TRUE)) ), 0 ) ), Transactions[[#This Row],[Categories]] ) )} -> Loans,Car | P220: =DATE(LEFT(Transactions[[#This Row],[Date]],4),MID(Transactions[[#This Row],[Date]],6,2),MID(Transactions[[#This Row],[Date]],9,2))+IF(RIGHT(Transactions[[#This Row],[Date]],2)="pm",IF(MID(Transactions[[#This Row],[Date]],12,2)<12,0.5,0),IF(MID(Transactions[[#This Row],[Date]],12,2)=12,-0.5,0)) -> 45204 | Q220: =DATE(YEAR(Transactions[[#This Row],[Datetime]]),MONTH(Transactions[[#This Row],[Datetime]]),1) -> 45200 | R220: =AND(Transactions[[#This Row],[Datetime]]>=EDATE(MAX(Transactions[Datetime]),-6),Transactions[[#This Row],[Datetime]]<=TODAY()) -> FALSE | S220: =AVERAGEIFS(Transactions[Month''s Total],Transactions[Recent],TRUE,Transactions[Custom Category],Transactions[[#This Row],[Custom Category]]) -> 624.12818 | T220: =SUMIFS(Transactions[Amount],Transactions[Month],Transactions[[#This Row],[Month]],Transactions[Custom Category],Transactions[[#This Row],[Custom Category]]) -> 385.16 | U220: =IF(COUNTIF(Budgets[Custom Category],Transactions[[#This Row],[Custom Category]])=0,Transactions[[#This Row],[6M AVG]],_xlfn.XLOOKUP(Transactions[[#This Row],[Custom Category]],Budgets[Custom Category],Budgets[Monthly],0,0)) -> 624.12818 | V220: =IF(Transactions[[#This Row],[Month]]=Sel_Month,Transactions[[#This Row],[Amount]],0) -> 0
A221: eOMxkwaqNZH7Vznj6o6XTA4KJOvewbhnEVmgd | B221: added | C221: 24.8 | D221: Transfer, Debit | E221: 2023-10-05, 8:00:00 p.m. | F221: CAD | H221: Online Banking transfer - 8082 | I221: other | J221: FALSE | K221: dO9xKdaPN8H9zOvYwpwosEkP31wpmBhKYXAkO | L221: =_xlfn.XLOOKUP(Transactions[[#This Row],[Account ID]],Accounts[Plaid Account ID],Accounts[Name],"Not Found",0) -> RBC Staff Banking | M221: =_xlfn.XLOOKUP(Transactions[[#This Row],[Account ID]],Accounts[Plaid Account ID],Accounts[Institution Name],"Not Found",0) -> RBC Royal Bank | N221: =IF(Transactions[[#This Row],[Amount]]<0,"credit","debit") -> debit | O221: {=IF( ISNUMBER(MATCH(Transactions[[#This Row],[Categories]], _xlfn._xlws.FILTER(Custom_Cat[Name], LEN(Custom_Cat[Name]) >= 3), 0)), INDEX(Custom_Cat[Custom Category], MATCH(Transactions[[#This Row],[Categories]], _xlfn._xlws.FILTER(Custom_Cat[Name], LEN(Custom_Cat[Name]) >= 3), 0)), IFERROR( INDEX( Custom_Cat[Custom Category], MATCH( 1, (ISNUMBER(SEARCH(LOWER(Custom_Cat[Name]), LOWER(Transactions[[#This Row],[Name]])))) * (LEN(Custom_Cat[Name]) >= 3) * ( (IF(LEFT(Custom_Cat[Amount],1)="<",Transactions[[#This Row],[Amount]]<VALUE(MID(Custom_Cat[Amount], 2, LEN(Custom_Cat[Amount])-1)),TRUE)) * (IF(LEFT(Custom_Cat[Amount],1)=">",Transactions[[#This Row],[Amount]]>VALUE(MID(Custom_Cat[Amount], 2, LEN(Custom_Cat[Amount])-1)),TRUE)) ), 0 ) ), Transactions[[#This Row],[Categories]] ) )} -> Transfer, Debit | P221: =DATE(LEFT(Transactions[[#This Row],[Date]],4),MID(Transactions[[#This Row],[Date]],6,2),MID(Transactions[[#This Row],[Date]],9,2))+IF(RIGHT(Transactions[[#This Row],[Date]],2)="pm",IF(MID(Transactions[[#This Row],[Date]],12,2)<12,0.5,0),IF(MID(Transactions[[#This Row],[Date]],12,2)=12,-0.5,0)) -> 45204 | Q221: =DATE(YEAR(Transactions[[#This Row],[Datetime]]),MONTH(Transactions[[#This Row],[Datetime]]),1) -> 45200 | R221: =AND(Transactions[[#This Row],[Datetime]]>=EDATE(MAX(Transactions[Datetime]),-6),Transactions[[#This Row],[Datetime]]<=TODAY()) -> FALSE | S221: =AVERAGEIFS(Transactions[Month''s Total],Transactions[Recent],TRUE,Transactions[Custom Category],Transactions[[#This Row],[Custom Category]]) -> 12758.461 | T221: =SUMIFS(Transactions[Amount],Transactions[Month],Transactions[[#This Row],[Month]],Transactions[Custom Category],Transactions[[#This Row],[Custom Category]]) -> 1148.73 | U221: =IF(COUNTIF(Budgets[Custom Category],Transactions[[#This Row],[Custom Category]])=0,Transactions[[#This Row],[6M AVG]],_xlfn.XLOOKUP(Transactions[[#This Row],[Custom Category]],Budgets[Custom Category],Budgets[Monthly],0,0)) -> 12758.461 | V221: =IF(Transactions[[#This Row],[Month]]=Sel_Month,Transactions[[#This Row],[Amount]],0) -> 0
A222: eOMxkwaqNZH7Vznj6o6XTA4KJOvewbhnEVmgd | B222: added | C222: -0.34 | D222: Transfer, Payroll | E222: 2023-10-09, 8:00:00 p.m. | F222: CAD | H222: Misc Payment Google LLC | I222: other | J222: FALSE | K222: Yepjdz7nNKt6JRzgrpr5C8LVBoYkynfJvkLNy | L222: =_xlfn.XLOOKUP(Transactions[[#This Row],[Account ID]],Accounts[Plaid Account ID],Accounts[Name],"Not Found",0) -> RBC Staff Banking | M222: =_xlfn.XLOOKUP(Transactions[[#This Row],[Account ID]],Accounts[Plaid Account ID],Accounts[Institution Name],"Not Found",0) -> RBC Royal Bank | N222: =IF(Transactions[[#This Row],[Amount]]<0,"credit","debit") -> credit | O222: {=IF( ISNUMBER(MATCH(Transactions[[#This Row],[Categories]], _xlfn._xlws.FILTER(Custom_Cat[Name], LEN(Custom_Cat[Name]) >= 3), 0)), INDEX(Custom_Cat[Custom Category], MATCH(Transactions[[#This Row],[Categories]], _xlfn._xlws.FILTER(Custom_Cat[Name], LEN(Custom_Cat[Name]) >= 3), 0)), IFERROR( INDEX( Custom_Cat[Custom Category], MATCH( 1, (ISNUMBER(SEARCH(LOWER(Custom_Cat[Name]), LOWER(Transactions[[#This Row],[Name]])))) * (LEN(Custom_Cat[Name]) >= 3) * ( (IF(LEFT(Custom_Cat[Amount],1)="<",Transactions[[#This Row],[Amount]]<VALUE(MID(Custom_Cat[Amount], 2, LEN(Custom_Cat[Amount])-1)),TRUE)) * (IF(LEFT(Custom_Cat[Amount],1)=">",Transactions[[#This Row],[Amount]]>VALUE(MID(Custom_Cat[Amount], 2, LEN(Custom_Cat[Amount])-1)),TRUE)) ), 0 ) ), Transactions[[#This Row],[Categories]] ) )} -> Transfer,Internal | P222: =DATE(LEFT(Transactions[[#This Row],[Date]],4),MID(Transactions[[#This Row],[Date]],6,2),MID(Transactions[[#This Row],[Date]],9,2))+IF(RIGHT(Transactions[[#This Row],[Date]],2)="pm",IF(MID(Transactions[[#This Row],[Date]],12,2)<12,0.5,0),IF(MID(Transactions[[#This Row],[Date]],12,2)=12,-0.5,0)) -> 45208 | Q222: =DATE(YEAR(Transactions[[#This Row],[Datetime]]),MONTH(Transactions[[#This Row],[Datetime]]),1) -> 45200 | R222: =AND(Transactions[[#This Row],[Datetime]]>=EDATE(MAX(Transactions[Datetime]),-6),Transactions[[#This Row],[Datetime]]<=TODAY()) -> FALSE | S222: =AVERAGEIFS(Transactions[Month''s Total],Transactions[Recent],TRUE,Transactions[Custom Category],Transactions[[#This Row],[Custom Category]]) -> 14532.99 | T222: =SUMIFS(Transactions[Amount],Transactions[Month],Transactions[[#This Row],[Month]],Transactions[Custom Category],Transactions[[#This Row],[Custom Category]]) -> 3947.82 | U222: =IF(COUNTIF(Budgets[Custom Category],Transactions[[#This Row],[Custom Category]])=0,Transactions[[#This Row],[6M AVG]],_xlfn.XLOOKUP(Transactions[[#This Row],[Custom Category]],Budgets[Custom Category],Budgets[Monthly],0,0)) -> 14532.99 | V222: =IF(Transactions[[#This Row],[Month]]=Sel_Month,Transactions[[#This Row],[Amount]],0) -> 0
A223: eOMxkwaqNZH7Vznj6o6XTA4KJOvewbhnEVmgd | B223: added | C223: -1500 | D223: Transfer, Credit | E223: 2023-10-09, 8:00:00 p.m. | F223: CAD | H223: e-Transfer - Autodeposit PAULA ANDREA AMARILES RESTREPO C1AC5Xj8dmVa | I223: other | J223: FALSE | K223: zbLXY8dVz1Tm4RXq9P9buZMDN463qzCve07ae | L223: =_xlfn.XLOOKUP(Transactions[[#This Row],[Account ID]],Accounts[Plaid Account ID],Accounts[Name],"Not Found",0) -> RBC Staff Banking | M223: =_xlfn.XLOOKUP(Transactions[[#This Row],[Account ID]],Accounts[Plaid Account ID],Accounts[Institution Name],"Not Found",0) -> RBC Royal Bank | N223: =IF(Transactions[[#This Row],[Amount]]<0,"credit","debit") -> credit | O223: {=IF( ISNUMBER(MATCH(Transactions[[#This Row],[Categories]], _xlfn._xlws.FILTER(Custom_Cat[Name], LEN(Custom_Cat[Name]) >= 3), 0)), INDEX(Custom_Cat[Custom Category], MATCH(Transactions[[#This Row],[Categories]], _xlfn._xlws.FILTER(Custom_Cat[Name], LEN(Custom_Cat[Name]) >= 3), 0)), IFERROR( INDEX( Custom_Cat[Custom Category], MATCH( 1, (ISNUMBER(SEARCH(LOWER(Custom_Cat[Name]), LOWER(Transactions[[#This Row],[Name]])))) * (LEN(Custom_Cat[Name]) >= 3) * ( (IF(LEFT(Custom_Cat[Amount],1)="<",Transactions[[#This Row],[Amount]]<VALUE(MID(Custom_Cat[Amount], 2, LEN(Custom_Cat[Amount])-1)),TRUE)) * (IF(LEFT(Custom_Cat[Amount],1)=">",Transactions[[#This Row],[Amount]]>VALUE(MID(Custom_Cat[Amount], 2, LEN(Custom_Cat[Amount])-1)),TRUE)) ), 0 ) ), Transactions[[#This Row],[Categories]] ) )} -> Transfer,Internal | P223: =DATE(LEFT(Transactions[[#This Row],[Date]],4),MID(Transactions[[#This Row],[Date]],6,2),MID(Transactions[[#This Row],[Date]],9,2))+IF(RIGHT(Transactions[[#This Row],[Date]],2)="pm",IF(MID(Transactions[[#This Row],[Date]],12,2)<12,0.5,0),IF(MID(Transactions[[#This Row],[Date]],12,2)=12,-0.5,0)) -> 45208 | Q223: =DATE(YEAR(Transactions[[#This Row],[Datetime]]),MONTH(Transactions[[#This Row],[Datetime]]),1) -> 45200 | R223: =AND(Transactions[[#This Row],[Datetime]]>=EDATE(MAX(Transactions[Datetime]),-6),Transactions[[#This Row],[Datetime]]<=TODAY()) -> FALSE | S223: =AVERAGEIFS(Transactions[Month''s Total],Transactions[Recent],TRUE,Transactions[Custom Category],Transactions[[#This Row],[Custom Category]]) -> 14532.99 | T223: =SUMIFS(Transactions[Amount],Transactions[Month],Transactions[[#This Row],[Month]],Transactions[Custom Category],Transactions[[#This Row],[Custom Category]]) -> 3947.82 | U223: =IF(COUNTIF(Budgets[Custom Category],Transactions[[#This Row],[Custom Category]])=0,Transactions[[#This Row],[6M AVG]],_xlfn.XLOOKUP(Transactions[[#This Row],[Custom Category]],Budgets[Custom Category],Budgets[Monthly],0,0)) -> 14532.99 | V223: =IF(Transactions[[#This Row],[Month]]=Sel_Month,Transactions[[#This Row],[Amount]],0) -> 0
A224: eOMxkwaqNZH7Vznj6o6XTA4KJOvewbhnEVmgd | B224: added | C224: 50 | D224: Transfer, Debit | E224: 2023-10-10, 8:00:00 p.m. | F224: CAD | H224: e-Transfer sent Costumes YCUP3R | I224: other | J224: FALSE | K224: eOMxkwaqNZH7Vznj6o6XTA4vJObVpKTnBm0Mw | L224: =_xlfn.XLOOKUP(Transactions[[#This Row],[Account ID]],Accounts[Plaid Account ID],Accounts[Name],"Not Found",0) -> RBC Staff Banking | M224: =_xlfn.XLOOKUP(Transactions[[#This Row],[Account ID]],Accounts[Plaid Account ID],Accounts[Institution Name],"Not Found",0) -> RBC Royal Bank | N224: =IF(Transactions[[#This Row],[Amount]]<0,"credit","debit") -> debit | O224: {=IF( ISNUMBER(MATCH(Transactions[[#This Row],[Categories]], _xlfn._xlws.FILTER(Custom_Cat[Name], LEN(Custom_Cat[Name]) >= 3), 0)), INDEX(Custom_Cat[Custom Category], MATCH(Transactions[[#This Row],[Categories]], _xlfn._xlws.FILTER(Custom_Cat[Name], LEN(Custom_Cat[Name]) >= 3), 0)), IFERROR( INDEX( Custom_Cat[Custom Category], MATCH( 1, (ISNUMBER(SEARCH(LOWER(Custom_Cat[Name]), LOWER(Transactions[[#This Row],[Name]])))) * (LEN(Custom_Cat[Name]) >= 3) * ( (IF(LEFT(Custom_Cat[Amount],1)="<",Transactions[[#This Row],[Amount]]<VALUE(MID(Custom_Cat[Amount], 2, LEN(Custom_Cat[Amount])-1)),TRUE)) * (IF(LEFT(Custom_Cat[Amount],1)=">",Transactions[[#This Row],[Amount]]>VALUE(MID(Custom_Cat[Amount], 2, LEN(Custom_Cat[Amount])-1)),TRUE)) ), 0 ) ), Transactions[[#This Row],[Categories]] ) )} -> Transfer, Debit | P224: =DATE(LEFT(Transactions[[#This Row],[Date]],4),MID(Transactions[[#This Row],[Date]],6,2),MID(Transactions[[#This Row],[Date]],9,2))+IF(RIGHT(Transactions[[#This Row],[Date]],2)="pm",IF(MID(Transactions[[#This Row],[Date]],12,2)<12,0.5,0),IF(MID(Transactions[[#This Row],[Date]],12,2)=12,-0.5,0)) -> 45209 | Q224: =DATE(YEAR(Transactions[[#This Row],[Datetime]]),MONTH(Transactions[[#This Row],[Datetime]]),1) -> 45200 | R224: =AND(Transactions[[#This Row],[Datetime]]>=EDATE(MAX(Transactions[Datetime]),-6),Transactions[[#This Row],[Datetime]]<=TODAY()) -> FALSE | S224: =AVERAGEIFS(Transactions[Month''s Total],Transactions[Recent],TRUE,Transactions[Custom Category],Transactions[[#This Row],[Custom Category]]) -> 12758.461 | T224: =SUMIFS(Transactions[Amount],Transactions[Month],Transactions[[#This Row],[Month]],Transactions[Custom Category],Transactions[[#This Row],[Custom Category]]) -> 1148.73 | U224: =IF(COUNTIF(Budgets[Custom Category],Transactions[[#This Row],[Custom Category]])=0,Transactions[[#This Row],[6M AVG]],_xlfn.XLOOKUP(Transactions[[#This Row],[Custom Category]],Budgets[Custom Category],Budgets[Monthly],0,0)) -> 12758.461 | V224: =IF(Transactions[[#This Row],[Month]]=Sel_Month,Transactions[[#This Row],[Amount]],0) -> 0
A225: eOMxkwaqNZH7Vznj6o6XTA4KJOvewbhnEVmgd | B225: added | C225: 150.52 | D225: Service, Utilities, Electric | E225: 2023-10-11, 8:00:00 p.m. | F225: CAD | G225: Hydro | H225: Hydro Bill Pmt TORONTO HYDRO | I225: online | J225: FALSE | K225: pb4DZkp8zRTK7y0VqjqAT7D6dOa9NYh3YEpNd | L225: =_xlfn.XLOOKUP(Transactions[[#This Row],[Account ID]],Accounts[Plaid Account ID],Accounts[Name],"Not Found",0) -> RBC Staff Banking | M225: =_xlfn.XLOOKUP(Transactions[[#This Row],[Account ID]],Accounts[Plaid Account ID],Accounts[Institution Name],"Not Found",0) -> RBC Royal Bank | N225: =IF(Transactions[[#This Row],[Amount]]<0,"credit","debit") -> debit | O225: {=IF( ISNUMBER(MATCH(Transactions[[#This Row],[Categories]], _xlfn._xlws.FILTER(Custom_Cat[Name], LEN(Custom_Cat[Name]) >= 3), 0)), INDEX(Custom_Cat[Custom Category], MATCH(Transactions[[#This Row],[Categories]], _xlfn._xlws.FILTER(Custom_Cat[Name], LEN(Custom_Cat[Name]) >= 3), 0)), IFERROR( INDEX( Custom_Cat[Custom Category], MATCH( 1, (ISNUMBER(SEARCH(LOWER(Custom_Cat[Name]), LOWER(Transactions[[#This Row],[Name]])))) * (LEN(Custom_Cat[Name]) >= 3) * ( (IF(LEFT(Custom_Cat[Amount],1)="<",Transactions[[#This Row],[Amount]]<VALUE(MID(Custom_Cat[Amount], 2, LEN(Custom_Cat[Amount])-1)),TRUE)) * (IF(LEFT(Custom_Cat[Amount],1)=">",Transactions[[#This Row],[Amount]]>VALUE(MID(Custom_Cat[Amount], 2, LEN(Custom_Cat[Amount])-1)),TRUE)) ), 0 ) ), Transactions[[#This Row],[Categories]] ) )} -> Utilities,Electric | P225: =DATE(LEFT(Transactions[[#This Row],[Date]],4),MID(Transactions[[#This Row],[Date]],6,2),MID(Transactions[[#This Row],[Date]],9,2))+IF(RIGHT(Transactions[[#This Row],[Date]],2)="pm",IF(MID(Transactions[[#This Row],[Date]],12,2)<12,0.5,0),IF(MID(Transactions[[#This Row],[Date]],12,2)=12,-0.5,0)) -> 45210 | Q225: =DATE(YEAR(Transactions[[#This Row],[Datetime]]),MONTH(Transactions[[#This Row],[Datetime]]),1) -> 45200 | R225: =AND(Transactions[[#This Row],[Datetime]]>=EDATE(MAX(Transactions[Datetime]),-6),Transactions[[#This Row],[Datetime]]<=TODAY()) -> FALSE | S225: =AVERAGEIFS(Transactions[Month''s Total],Transactions[Recent],TRUE,Transactions[Custom Category],Transactions[[#This Row],[Custom Category]]) -> 139.88333 | T225: =SUMIFS(Transactions[Amount],Transactions[Month],Transactions[[#This Row],[Month]],Transactions[Custom Category],Transactions[[#This Row],[Custom Category]]) -> 150.52 | U225: =IF(COUNTIF(Budgets[Custom Category],Transactions[[#This Row],[Custom Category]])=0,Transactions[[#This Row],[6M AVG]],_xlfn.XLOOKUP(Transactions[[#This Row],[Custom Category]],Budgets[Custom Category],Budgets[Monthly],0,0)) -> 139.88333 | V225: =IF(Transactions[[#This Row],[Month]]=Sel_Month,Transactions[[#This Row],[Amount]],0) -> 0
A226: eOMxkwaqNZH7Vznj6o6XTA4KJOvewbhnEVmgd | B226: added | C226: 81.93 | D226: Service, Utilities, Gas | E226: 2023-10-11, 8:00:00 p.m. | F226: CAD | G226: Enbridge Gas | H226: Utility Bill Pmt Enbridge Gas | I226: online | J226: FALSE | K226: Xp8jezanNyTBNo6ARXRZC15emqw3KxHdEAYMp | L226: =_xlfn.XLOOKUP(Transactions[[#This Row],[Account ID]],Accounts[Plaid Account ID],Accounts[Name],"Not Found",0) -> RBC Staff Banking | M226: =_xlfn.XLOOKUP(Transactions[[#This Row],[Account ID]],Accounts[Plaid Account ID],Accounts[Institution Name],"Not Found",0) -> RBC Royal Bank | N226: =IF(Transactions[[#This Row],[Amount]]<0,"credit","debit") -> debit | O226: {=IF( ISNUMBER(MATCH(Transactions[[#This Row],[Categories]], _xlfn._xlws.FILTER(Custom_Cat[Name], LEN(Custom_Cat[Name]) >= 3), 0)), INDEX(Custom_Cat[Custom Category], MATCH(Transactions[[#This Row],[Categories]], _xlfn._xlws.FILTER(Custom_Cat[Name], LEN(Custom_Cat[Name]) >= 3), 0)), IFERROR( INDEX( Custom_Cat[Custom Category], MATCH( 1, (ISNUMBER(SEARCH(LOWER(Custom_Cat[Name]), LOWER(Transactions[[#This Row],[Name]])))) * (LEN(Custom_Cat[Name]) >= 3) * ( (IF(LEFT(Custom_Cat[Amount],1)="<",Transactions[[#This Row],[Amount]]<VALUE(MID(Custom_Cat[Amount], 2, LEN(Custom_Cat[Amount])-1)),TRUE)) * (IF(LEFT(Custom_Cat[Amount],1)=">",Transactions[[#This Row],[Amount]]>VALUE(MID(Custom_Cat[Amount], 2, LEN(Custom_Cat[Amount])-1)),TRUE)) ), 0 ) ), Transactions[[#This Row],[Categories]] ) )} -> Utilities,Gas | P226: =DATE(LEFT(Transactions[[#This Row],[Date]],4),MID(Transactions[[#This Row],[Date]],6,2),MID(Transactions[[#This Row],[Date]],9,2))+IF(RIGHT(Transactions[[#This Row],[Date]],2)="pm",IF(MID(Transactions[[#This Row],[Date]],12,2)<12,0.5,0),IF(MID(Transactions[[#This Row],[Date]],12,2)=12,-0.5,0)) -> 45210 | Q226: =DATE(YEAR(Transactions[[#This Row],[Datetime]]),MONTH(Transactions[[#This Row],[Datetime]]),1) -> 45200 | R226: =AND(Transactions[[#This Row],[Datetime]]>=EDATE(MAX(Transactions[Datetime]),-6),Transactions[[#This Row],[Datetime]]<=TODAY()) -> FALSE | S226: =AVERAGEIFS(Transactions[Month''s Total],Transactions[Recent],TRUE,Transactions[Custom Category],Transactions[[#This Row],[Custom Category]]) -> 153.08333 | T226: =SUMIFS(Transactions[Amount],Transactions[Month],Transactions[[#This Row],[Month]],Transactions[Custom Category],Transactions[[#This Row],[Custom Category]]) -> 81.93 | U226: =IF(COUNTIF(Budgets[Custom Category],Transactions[[#This Row],[Custom Category]])=0,Transactions[[#This Row],[6M AVG]],_xlfn.XLOOKUP(Transactions[[#This Row],[Custom Category]],Budgets[Custom Category],Budgets[Monthly],0,0)) -> 153.08333 | V226: =IF(Transactions[[#This Row],[Month]]=Sel_Month,Transactions[[#This Row],[Amount]],0) -> 0
A227: eOMxkwaqNZH7Vznj6o6XTA4KJOvewbhnEVmgd | B227: added | C227: 16 | D227: Transfer, Debit | E227: 2023-10-11, 8:00:00 p.m. | F227: CAD | H227: e-Transfer sent Paula Amariles UAG3ZY | I227: other | J227: FALSE | K227: NpJvYzRnNdTaNZ0XOMOATOvyme7ABYiojem5a | L227: =_xlfn.XLOOKUP(Transactions[[#This Row],[Account ID]],Accounts[Plaid Account ID],Accounts[Name],"Not Found",0) -> RBC Staff Banking | M227: =_xlfn.XLOOKUP(Transactions[[#This Row],[Account ID]],Accounts[Plaid Account ID],Accounts[Institution Name],"Not Found",0) -> RBC Royal Bank | N227: =IF(Transactions[[#This Row],[Amount]]<0,"credit","debit") -> debit | O227: {=IF( ISNUMBER(MATCH(Transactions[[#This Row],[Categories]], _xlfn._xlws.FILTER(Custom_Cat[Name], LEN(Custom_Cat[Name]) >= 3), 0)), INDEX(Custom_Cat[Custom Category], MATCH(Transactions[[#This Row],[Categories]], _xlfn._xlws.FILTER(Custom_Cat[Name], LEN(Custom_Cat[Name]) >= 3), 0)), IFERROR( INDEX( Custom_Cat[Custom Category], MATCH( 1, (ISNUMBER(SEARCH(LOWER(Custom_Cat[Name]), LOWER(Transactions[[#This Row],[Name]])))) * (LEN(Custom_Cat[Name]) >= 3) * ( (IF(LEFT(Custom_Cat[Amount],1)="<",Transactions[[#This Row],[Amount]]<VALUE(MID(Custom_Cat[Amount], 2, LEN(Custom_Cat[Amount])-1)),TRUE)) * (IF(LEFT(Custom_Cat[Amount],1)=">",Transactions[[#This Row],[Amount]]>VALUE(MID(Custom_Cat[Amount], 2, LEN(Custom_Cat[Amount])-1)),TRUE)) ), 0 ) ), Transactions[[#This Row],[Categories]] ) )} -> Transfer,Internal | P227: =DATE(LEFT(Transactions[[#This Row],[Date]],4),MID(Transactions[[#This Row],[Date]],6,2),MID(Transactions[[#This Row],[Date]],9,2))+IF(RIGHT(Transactions[[#This Row],[Date]],2)="pm",IF(MID(Transactions[[#This Row],[Date]],12,2)<12,0.5,0),IF(MID(Transactions[[#This Row],[Date]],12,2)=12,-0.5,0)) -> 45210 | Q227: =DATE(YEAR(Transactions[[#This Row],[Datetime]]),MONTH(Transactions[[#This Row],[Datetime]]),1) -> 45200 | R227: =AND(Transactions[[#This Row],[Datetime]]>=EDATE(MAX(Transactions[Datetime]),-6),Transactions[[#This Row],[Datetime]]<=TODAY()) -> FALSE | S227: =AVERAGEIFS(Transactions[Month''s Total],Transactions[Recent],TRUE,Transactions[Custom Category],Transactions[[#This Row],[Custom Category]]) -> 14532.99 | T227: =SUMIFS(Transactions[Amount],Transactions[Month],Transactions[[#This Row],[Month]],Transactions[Custom Category],Transactions[[#This Row],[Custom Category]]) -> 3947.82 | U227: =IF(COUNTIF(Budgets[Custom Category],Transactions[[#This Row],[Custom Category]])=0,Transactions[[#This Row],[6M AVG]],_xlfn.XLOOKUP(Transactions[[#This Row],[Custom Category]],Budgets[Custom Category],Budgets[Monthly],0,0)) -> 14532.99 | V227: =IF(Transactions[[#This Row],[Month]]=Sel_Month,Transactions[[#This Row],[Amount]],0) -> 0
A228: eOMxkwaqNZH7Vznj6o6XTA4KJOvewbhnEVmgd | B228: added | C228: -244 | D228: Transfer, Payroll, Benefits | E228: 2023-10-12, 8:00:00 p.m. | F228: CAD | H228: Climate Action Incentive CANADA | I228: other | J228: FALSE | K228: nN46JypjzMu8QYa5zKzrIVjqMJ6z3LIBzR15E | L228: =_xlfn.XLOOKUP(Transactions[[#This Row],[Account ID]],Accounts[Plaid Account ID],Accounts[Name],"Not Found",0) -> RBC Staff Banking | M228: =_xlfn.XLOOKUP(Transactions[[#This Row],[Account ID]],Accounts[Plaid Account ID],Accounts[Institution Name],"Not Found",0) -> RBC Royal Bank | N228: =IF(Transactions[[#This Row],[Amount]]<0,"credit","debit") -> credit | O228: {=IF( ISNUMBER(MATCH(Transactions[[#This Row],[Categories]], _xlfn._xlws.FILTER(Custom_Cat[Name], LEN(Custom_Cat[Name]) >= 3), 0)), INDEX(Custom_Cat[Custom Category], MATCH(Transactions[[#This Row],[Categories]], _xlfn._xlws.FILTER(Custom_Cat[Name], LEN(Custom_Cat[Name]) >= 3), 0)), IFERROR( INDEX( Custom_Cat[Custom Category], MATCH( 1, (ISNUMBER(SEARCH(LOWER(Custom_Cat[Name]), LOWER(Transactions[[#This Row],[Name]])))) * (LEN(Custom_Cat[Name]) >= 3) * ( (IF(LEFT(Custom_Cat[Amount],1)="<",Transactions[[#This Row],[Amount]]<VALUE(MID(Custom_Cat[Amount], 2, LEN(Custom_Cat[Amount])-1)),TRUE)) * (IF(LEFT(Custom_Cat[Amount],1)=">",Transactions[[#This Row],[Amount]]>VALUE(MID(Custom_Cat[Amount], 2, LEN(Custom_Cat[Amount])-1)),TRUE)) ), 0 ) ), Transactions[[#This Row],[Categories]] ) )} -> Transfer, Payroll, Benefits | P228: =DATE(LEFT(Transactions[[#This Row],[Date]],4),MID(Transactions[[#This Row],[Date]],6,2),MID(Transactions[[#This Row],[Date]],9,2))+IF(RIGHT(Transactions[[#This Row],[Date]],2)="pm",IF(MID(Transactions[[#This Row],[Date]],12,2)<12,0.5,0),IF(MID(Transactions[[#This Row],[Date]],12,2)=12,-0.5,0)) -> 45211 | Q228: =DATE(YEAR(Transactions[[#This Row],[Datetime]]),MONTH(Transactions[[#This Row],[Datetime]]),1) -> 45200 | R228: =AND(Transactions[[#This Row],[Datetime]]>=EDATE(MAX(Transactions[Datetime]),-6),Transactions[[#This Row],[Datetime]]<=TODAY()) -> FALSE | S228: =AVERAGEIFS(Transactions[Month''s Total],Transactions[Recent],TRUE,Transactions[Custom Category],Transactions[[#This Row],[Custom Category]]) -> -244 | T228: =SUMIFS(Transactions[Amount],Transactions[Month],Transactions[[#This Row],[Month]],Transactions[Custom Category],Transactions[[#This Row],[Custom Category]]) -> -244 | U228: =IF(COUNTIF(Budgets[Custom Category],Transactions[[#This Row],[Custom Category]])=0,Transactions[[#This Row],[6M AVG]],_xlfn.XLOOKUP(Transactions[[#This Row],[Custom Category]],Budgets[Custom Category],Budgets[Monthly],0,0)) -> -244 | V228: =IF(Transactions[[#This Row],[Month]]=Sel_Month,Transactions[[#This Row],[Amount]],0) -> 0
A229: eOMxkwaqNZH7Vznj6o6XTA4KJOvewbhnEVmgd | B229: added | C229: 1652.35 | D229: Transfer, Billpay | E229: 2023-10-15, 8:00:00 p.m. | F229: CAD | H229: Misc Payment AMEX BILL PYMT | I229: other | J229: FALSE | K229: VpQOez8nNBT0NRm8n6nJCAg8mvOeq3T4V1P6J | L229: =_xlfn.XLOOKUP(Transactions[[#This Row],[Account ID]],Accounts[Plaid Account ID],Accounts[Name],"Not Found",0) -> RBC Staff Banking | M229: =_xlfn.XLOOKUP(Transactions[[#This Row],[Account ID]],Accounts[Plaid Account ID],Accounts[Institution Name],"Not Found",0) -> RBC Royal Bank | N229: =IF(Transactions[[#This Row],[Amount]]<0,"credit","debit") -> debit | O229: {=IF( ISNUMBER(MATCH(Transactions[[#This Row],[Categories]], _xlfn._xlws.FILTER(Custom_Cat[Name], LEN(Custom_Cat[Name]) >= 3), 0)), INDEX(Custom_Cat[Custom Category], MATCH(Transactions[[#This Row],[Categories]], _xlfn._xlws.FILTER(Custom_Cat[Name], LEN(Custom_Cat[Name]) >= 3), 0)), IFERROR( INDEX( Custom_Cat[Custom Category], MATCH( 1, (ISNUMBER(SEARCH(LOWER(Custom_Cat[Name]), LOWER(Transactions[[#This Row],[Name]])))) * (LEN(Custom_Cat[Name]) >= 3) * ( (IF(LEFT(Custom_Cat[Amount],1)="<",Transactions[[#This Row],[Amount]]<VALUE(MID(Custom_Cat[Amount], 2, LEN(Custom_Cat[Amount])-1)),TRUE)) * (IF(LEFT(Custom_Cat[Amount],1)=">",Transactions[[#This Row],[Amount]]>VALUE(MID(Custom_Cat[Amount], 2, LEN(Custom_Cat[Amount])-1)),TRUE)) ), 0 ) ), Transactions[[#This Row],[Categories]] ) )} -> Transfer,Internal | P229: =DATE(LEFT(Transactions[[#This Row],[Date]],4),MID(Transactions[[#This Row],[Date]],6,2),MID(Transactions[[#This Row],[Date]],9,2))+IF(RIGHT(Transactions[[#This Row],[Date]],2)="pm",IF(MID(Transactions[[#This Row],[Date]],12,2)<12,0.5,0),IF(MID(Transactions[[#This Row],[Date]],12,2)=12,-0.5,0)) -> 45214 | Q229: =DATE(YEAR(Transactions[[#This Row],[Datetime]]),MONTH(Transactions[[#This Row],[Datetime]]),1) -> 45200 | R229: =AND(Transactions[[#This Row],[Datetime]]>=EDATE(MAX(Transactions[Datetime]),-6),Transactions[[#This Row],[Datetime]]<=TODAY()) -> FALSE | S229: =AVERAGEIFS(Transactions[Month''s Total],Transactions[Recent],TRUE,Transactions[Custom Category],Transactions[[#This Row],[Custom Category]]) -> 14532.99 | T229: =SUMIFS(Transactions[Amount],Transactions[Month],Transactions[[#This Row],[Month]],Transactions[Custom Category],Transactions[[#This Row],[Custom Category]]) -> 3947.82 | U229: =IF(COUNTIF(Budgets[Custom Category],Transactions[[#This Row],[Custom Category]])=0,Transactions[[#This Row],[6M AVG]],_xlfn.XLOOKUP(Transactions[[#This Row],[Custom Category]],Budgets[Custom Category],Budgets[Monthly],0,0)) -> 14532.99 | V229: =IF(Transactions[[#This Row],[Month]]=Sel_Month,Transactions[[#This Row],[Amount]],0) -> 0
A230: eOMxkwaqNZH7Vznj6o6XTA4KJOvewbhnEVmgd | B230: added | C230: 420.55 | D230: Service, Insurance | E230: 2023-10-15, 8:00:00 p.m. | F230: CAD | G230: Insurance Belair Ins Ass. | H230: Insurance BELAIR INS/ASS. | I230: online | J230: FALSE | K230: OpOQezXnNwT19bjmMBMvsZyjQ75eoYCxydQXJ | L230: =_xlfn.XLOOKUP(Transactions[[#This Row],[Account ID]],Accounts[Plaid Account ID],Accounts[Name],"Not Found",0) -> RBC Staff Banking | M230: =_xlfn.XLOOKUP(Transactions[[#This Row],[Account ID]],Accounts[Plaid Account ID],Accounts[Institution Name],"Not Found",0) -> RBC Royal Bank | N230: =IF(Transactions[[#This Row],[Amount]]<0,"credit","debit") -> debit | O230: {=IF( ISNUMBER(MATCH(Transactions[[#This Row],[Categories]], _xlfn._xlws.FILTER(Custom_Cat[Name], LEN(Custom_Cat[Name]) >= 3), 0)), INDEX(Custom_Cat[Custom Category], MATCH(Transactions[[#This Row],[Categories]], _xlfn._xlws.FILTER(Custom_Cat[Name], LEN(Custom_Cat[Name]) >= 3), 0)), IFERROR( INDEX( Custom_Cat[Custom Category], MATCH( 1, (ISNUMBER(SEARCH(LOWER(Custom_Cat[Name]), LOWER(Transactions[[#This Row],[Name]])))) * (LEN(Custom_Cat[Name]) >= 3) * ( (IF(LEFT(Custom_Cat[Amount],1)="<",Transactions[[#This Row],[Amount]]<VALUE(MID(Custom_Cat[Amount], 2, LEN(Custom_Cat[Amount])-1)),TRUE)) * (IF(LEFT(Custom_Cat[Amount],1)=">",Transactions[[#This Row],[Amount]]>VALUE(MID(Custom_Cat[Amount], 2, LEN(Custom_Cat[Amount])-1)),TRUE)) ), 0 ) ), Transactions[[#This Row],[Categories]] ) )} -> Insurance,Car | P230: =DATE(LEFT(Transactions[[#This Row],[Date]],4),MID(Transactions[[#This Row],[Date]],6,2),MID(Transactions[[#This Row],[Date]],9,2))+IF(RIGHT(Transactions[[#This Row],[Date]],2)="pm",IF(MID(Transactions[[#This Row],[Date]],12,2)<12,0.5,0),IF(MID(Transactions[[#This Row],[Date]],12,2)=12,-0.5,0)) -> 45214 | Q230: =DATE(YEAR(Transactions[[#This Row],[Datetime]]),MONTH(Transactions[[#This Row],[Datetime]]),1) -> 45200 | R230: =AND(Transactions[[#This Row],[Datetime]]>=EDATE(MAX(Transactions[Datetime]),-6),Transactions[[#This Row],[Datetime]]<=TODAY()) -> FALSE | S230: =AVERAGEIFS(Transactions[Month''s Total],Transactions[Recent],TRUE,Transactions[Custom Category],Transactions[[#This Row],[Custom Category]]) -> 432.996 | T230: =SUMIFS(Transactions[Amount],Transactions[Month],Transactions[[#This Row],[Month]],Transactions[Custom Category],Transactions[[#This Row],[Custom Category]]) -> 420.55 | U230: =IF(COUNTIF(Budgets[Custom Category],Transactions[[#This Row],[Custom Category]])=0,Transactions[[#This Row],[6M AVG]],_xlfn.XLOOKUP(Transactions[[#This Row],[Custom Category]],Budgets[Custom Category],Budgets[Monthly],0,0)) -> 432.996 | V230: =IF(Transactions[[#This Row],[Month]]=Sel_Month,Transactions[[#This Row],[Amount]],0) -> 0
A231: eOMxkwaqNZH7Vznj6o6XTA4KJOvewbhnEVmgd | B231: added | C231: 65.7 | D231: Service, Insurance | E231: 2023-10-15, 8:00:00 p.m. | F231: CAD | G231: Life Insurance Foresters | H231: Life Insurance Foresters Life | I231: online | J231: FALSE | K231: MpJZezRn7XToeMmQ6r6kTn1Y9wDExAIXoZvDj | L231: =_xlfn.XLOOKUP(Transactions[[#This Row],[Account ID]],Accounts[Plaid Account ID],Accounts[Name],"Not Found",0) -> RBC Staff Banking | M231: =_xlfn.XLOOKUP(Transactions[[#This Row],[Account ID]],Accounts[Plaid Account ID],Accounts[Institution Name],"Not Found",0) -> RBC Royal Bank | N231: =IF(Transactions[[#This Row],[Amount]]<0,"credit","debit") -> debit | O231: {=IF( ISNUMBER(MATCH(Transactions[[#This Row],[Categories]], _xlfn._xlws.FILTER(Custom_Cat[Name], LEN(Custom_Cat[Name]) >= 3), 0)), INDEX(Custom_Cat[Custom Category], MATCH(Transactions[[#This Row],[Categories]], _xlfn._xlws.FILTER(Custom_Cat[Name], LEN(Custom_Cat[Name]) >= 3), 0)), IFERROR( INDEX( Custom_Cat[Custom Category], MATCH( 1, (ISNUMBER(SEARCH(LOWER(Custom_Cat[Name]), LOWER(Transactions[[#This Row],[Name]])))) * (LEN(Custom_Cat[Name]) >= 3) * ( (IF(LEFT(Custom_Cat[Amount],1)="<",Transactions[[#This Row],[Amount]]<VALUE(MID(Custom_Cat[Amount], 2, LEN(Custom_Cat[Amount])-1)),TRUE)) * (IF(LEFT(Custom_Cat[Amount],1)=">",Transactions[[#This Row],[Amount]]>VALUE(MID(Custom_Cat[Amount], 2, LEN(Custom_Cat[Amount])-1)),TRUE)) ), 0 ) ), Transactions[[#This Row],[Categories]] ) )} -> Insurance,Life | P231: =DATE(LEFT(Transactions[[#This Row],[Date]],4),MID(Transactions[[#This Row],[Date]],6,2),MID(Transactions[[#This Row],[Date]],9,2))+IF(RIGHT(Transactions[[#This Row],[Date]],2)="pm",IF(MID(Transactions[[#This Row],[Date]],12,2)<12,0.5,0),IF(MID(Transactions[[#This Row],[Date]],12,2)=12,-0.5,0)) -> 45214 | Q231: =DATE(YEAR(Transactions[[#This Row],[Datetime]]),MONTH(Transactions[[#This Row],[Datetime]]),1) -> 45200 | R231: =AND(Transactions[[#This Row],[Datetime]]>=EDATE(MAX(Transactions[Datetime]),-6),Transactions[[#This Row],[Datetime]]<=TODAY()) -> FALSE | S231: =AVERAGEIFS(Transactions[Month''s Total],Transactions[Recent],TRUE,Transactions[Custom Category],Transactions[[#This Row],[Custom Category]]) -> 65.7 | T231: =SUMIFS(Transactions[Amount],Transactions[Month],Transactions[[#This Row],[Month]],Transactions[Custom Category],Transactions[[#This Row],[Custom Category]]) -> 65.7 | U231: =IF(COUNTIF(Budgets[Custom Category],Transactions[[#This Row],[Custom Category]])=0,Transactions[[#This Row],[6M AVG]],_xlfn.XLOOKUP(Transactions[[#This Row],[Custom Category]],Budgets[Custom Category],Budgets[Monthly],0,0)) -> 65.7 | V231: =IF(Transactions[[#This Row],[Month]]=Sel_Month,Transactions[[#This Row],[Amount]],0) -> 0
A232: eOMxkwaqNZH7Vznj6o6XTA4KJOvewbhnEVmgd | B232: added | C232: 50.86 | D232: Service, Insurance | E232: 2023-10-15, 8:00:00 p.m. | F232: CAD | G232: Insurance Belair Ins Ass. | H232: Insurance BELAIR INS/ASS. | I232: online | J232: FALSE | K232: EpbNezRmxVTmn9PBE8EDupkqO6mLyrIQxmOrm | L232: =_xlfn.XLOOKUP(Transactions[[#This Row],[Account ID]],Accounts[Plaid Account ID],Accounts[Name],"Not Found",0) -> RBC Staff Banking | M232: =_xlfn.XLOOKUP(Transactions[[#This Row],[Account ID]],Accounts[Plaid Account ID],Accounts[Institution Name],"Not Found",0) -> RBC Royal Bank | N232: =IF(Transactions[[#This Row],[Amount]]<0,"credit","debit") -> debit | O232: {=IF( ISNUMBER(MATCH(Transactions[[#This Row],[Categories]], _xlfn._xlws.FILTER(Custom_Cat[Name], LEN(Custom_Cat[Name]) >= 3), 0)), INDEX(Custom_Cat[Custom Category], MATCH(Transactions[[#This Row],[Categories]], _xlfn._xlws.FILTER(Custom_Cat[Name], LEN(Custom_Cat[Name]) >= 3), 0)), IFERROR( INDEX( Custom_Cat[Custom Category], MATCH( 1, (ISNUMBER(SEARCH(LOWER(Custom_Cat[Name]), LOWER(Transactions[[#This Row],[Name]])))) * (LEN(Custom_Cat[Name]) >= 3) * ( (IF(LEFT(Custom_Cat[Amount],1)="<",Transactions[[#This Row],[Amount]]<VALUE(MID(Custom_Cat[Amount], 2, LEN(Custom_Cat[Amount])-1)),TRUE)) * (IF(LEFT(Custom_Cat[Amount],1)=">",Transactions[[#This Row],[Amount]]>VALUE(MID(Custom_Cat[Amount], 2, LEN(Custom_Cat[Amount])-1)),TRUE)) ), 0 ) ), Transactions[[#This Row],[Categories]] ) )} -> Insurance,Home | P232: =DATE(LEFT(Transactions[[#This Row],[Date]],4),MID(Transactions[[#This Row],[Date]],6,2),MID(Transactions[[#This Row],[Date]],9,2))+IF(RIGHT(Transactions[[#This Row],[Date]],2)="pm",IF(MID(Transactions[[#This Row],[Date]],12,2)<12,0.5,0),IF(MID(Transactions[[#This Row],[Date]],12,2)=12,-0.5,0)) -> 45214 | Q232: =DATE(YEAR(Transactions[[#This Row],[Datetime]]),MONTH(Transactions[[#This Row],[Datetime]]),1) -> 45200 | R232: =AND(Transactions[[#This Row],[Datetime]]>=EDATE(MAX(Transactions[Datetime]),-6),Transactions[[#This Row],[Datetime]]<=TODAY()) -> FALSE | S232: =AVERAGEIFS(Transactions[Month''s Total],Transactions[Recent],TRUE,Transactions[Custom Category],Transactions[[#This Row],[Custom Category]]) -> 57.905 | T232: =SUMIFS(Transactions[Amount],Transactions[Month],Transactions[[#This Row],[Month]],Transactions[Custom Category],Transactions[[#This Row],[Custom Category]]) -> 50.86 | U232: =IF(COUNTIF(Budgets[Custom Category],Transactions[[#This Row],[Custom Category]])=0,Transactions[[#This Row],[6M AVG]],_xlfn.XLOOKUP(Transactions[[#This Row],[Custom Category]],Budgets[Custom Category],Budgets[Monthly],0,0)) -> 57.905 | V232: =IF(Transactions[[#This Row],[Month]]=Sel_Month,Transactions[[#This Row],[Amount]],0) -> 0
A233: eOMxkwaqNZH7Vznj6o6XTA4KJOvewbhnEVmgd | B233: added | C233: -240 | D233: Transfer, Credit | E233: 2023-10-15, 8:00:00 p.m. | F233: CAD | H233: e-Transfer - Autodeposit Ana Maria Avila Amaya C1ANs4zF4x4x | I233: other | J233: FALSE | K233: RXJjezRnNDSkNOaAe7ersEnVX69vo5hewxXba | L233: =_xlfn.XLOOKUP(Transactions[[#This Row],[Account ID]],Accounts[Plaid Account ID],Accounts[Name],"Not Found",0) -> RBC Staff Banking | M233: =_xlfn.XLOOKUP(Transactions[[#This Row],[Account ID]],Accounts[Plaid Account ID],Accounts[Institution Name],"Not Found",0) -> RBC Royal Bank | N233: =IF(Transactions[[#This Row],[Amount]]<0,"credit","debit") -> credit | O233: {=IF( ISNUMBER(MATCH(Transactions[[#This Row],[Categories]], _xlfn._xlws.FILTER(Custom_Cat[Name], LEN(Custom_Cat[Name]) >= 3), 0)), INDEX(Custom_Cat[Custom Category], MATCH(Transactions[[#This Row],[Categories]], _xlfn._xlws.FILTER(Custom_Cat[Name], LEN(Custom_Cat[Name]) >= 3), 0)), IFERROR( INDEX( Custom_Cat[Custom Category], MATCH( 1, (ISNUMBER(SEARCH(LOWER(Custom_Cat[Name]), LOWER(Transactions[[#This Row],[Name]])))) * (LEN(Custom_Cat[Name]) >= 3) * ( (IF(LEFT(Custom_Cat[Amount],1)="<",Transactions[[#This Row],[Amount]]<VALUE(MID(Custom_Cat[Amount], 2, LEN(Custom_Cat[Amount])-1)),TRUE)) * (IF(LEFT(Custom_Cat[Amount],1)=">",Transactions[[#This Row],[Amount]]>VALUE(MID(Custom_Cat[Amount], 2, LEN(Custom_Cat[Amount])-1)),TRUE)) ), 0 ) ), Transactions[[#This Row],[Categories]] ) )} -> Income,Repayment | P233: =DATE(LEFT(Transactions[[#This Row],[Date]],4),MID(Transactions[[#This Row],[Date]],6,2),MID(Transactions[[#This Row],[Date]],9,2))+IF(RIGHT(Transactions[[#This Row],[Date]],2)="pm",IF(MID(Transactions[[#This Row],[Date]],12,2)<12,0.5,0),IF(MID(Transactions[[#This Row],[Date]],12,2)=12,-0.5,0)) -> 45214 | Q233: =DATE(YEAR(Transactions[[#This Row],[Datetime]]),MONTH(Transactions[[#This Row],[Datetime]]),1) -> 45200 | R233: =AND(Transactions[[#This Row],[Datetime]]>=EDATE(MAX(Transactions[Datetime]),-6),Transactions[[#This Row],[Datetime]]<=TODAY()) -> FALSE | S233: =AVERAGEIFS(Transactions[Month''s Total],Transactions[Recent],TRUE,Transactions[Custom Category],Transactions[[#This Row],[Custom Category]]) -> -3209.0714 | T233: =SUMIFS(Transactions[Amount],Transactions[Month],Transactions[[#This Row],[Month]],Transactions[Custom Category],Transactions[[#This Row],[Custom Category]]) -> -4718 | U233: =IF(COUNTIF(Budgets[Custom Category],Transactions[[#This Row],[Custom Category]])=0,Transactions[[#This Row],[6M AVG]],_xlfn.XLOOKUP(Transactions[[#This Row],[Custom Category]],Budgets[Custom Category],Budgets[Monthly],0,0)) -> -3209.0714 | V233: =IF(Transactions[[#This Row],[Month]]=Sel_Month,Transactions[[#This Row],[Amount]],0) -> 0
A234: eOMxkwaqNZH7Vznj6o6XTA4KJOvewbhnEVmgd | B234: added | C234: -1022.62 | D234: Bank Fees, Foreign Transaction | E234: 2023-10-15, 8:00:00 p.m. | F234: CAD | H234: Online Banking foreign exchange Ref 3WW882862139100 | I234: other | J234: FALSE | K234: QpJ5ezRXNLTNEw45P1PjHB0VAQrj7MtO8YAgQ | L234: =_xlfn.XLOOKUP(Transactions[[#This Row],[Account ID]],Accounts[Plaid Account ID],Accounts[Name],"Not Found",0) -> RBC Staff Banking | M234: =_xlfn.XLOOKUP(Transactions[[#This Row],[Account ID]],Accounts[Plaid Account ID],Accounts[Institution Name],"Not Found",0) -> RBC Royal Bank | N234: =IF(Transactions[[#This Row],[Amount]]<0,"credit","debit") -> credit | O234: {=IF( ISNUMBER(MATCH(Transactions[[#This Row],[Categories]], _xlfn._xlws.FILTER(Custom_Cat[Name], LEN(Custom_Cat[Name]) >= 3), 0)), INDEX(Custom_Cat[Custom Category], MATCH(Transactions[[#This Row],[Categories]], _xlfn._xlws.FILTER(Custom_Cat[Name], LEN(Custom_Cat[Name]) >= 3), 0)), IFERROR( INDEX( Custom_Cat[Custom Category], MATCH( 1, (ISNUMBER(SEARCH(LOWER(Custom_Cat[Name]), LOWER(Transactions[[#This Row],[Name]])))) * (LEN(Custom_Cat[Name]) >= 3) * ( (IF(LEFT(Custom_Cat[Amount],1)="<",Transactions[[#This Row],[Amount]]<VALUE(MID(Custom_Cat[Amount], 2, LEN(Custom_Cat[Amount])-1)),TRUE)) * (IF(LEFT(Custom_Cat[Amount],1)=">",Transactions[[#This Row],[Amount]]>VALUE(MID(Custom_Cat[Amount], 2, LEN(Custom_Cat[Amount])-1)),TRUE)) ), 0 ) ), Transactions[[#This Row],[Categories]] ) )} -> Income,Salary | P234: =DATE(LEFT(Transactions[[#This Row],[Date]],4),MID(Transactions[[#This Row],[Date]],6,2),MID(Transactions[[#This Row],[Date]],9,2))+IF(RIGHT(Transactions[[#This Row],[Date]],2)="pm",IF(MID(Transactions[[#This Row],[Date]],12,2)<12,0.5,0),IF(MID(Transactions[[#This Row],[Date]],12,2)=12,-0.5,0)) -> 45214 | Q234: =DATE(YEAR(Transactions[[#This Row],[Datetime]]),MONTH(Transactions[[#This Row],[Datetime]]),1) -> 45200 | R234: =AND(Transactions[[#This Row],[Datetime]]>=EDATE(MAX(Transactions[Datetime]),-6),Transactions[[#This Row],[Datetime]]<=TODAY()) -> FALSE | S234: =AVERAGEIFS(Transactions[Month''s Total],Transactions[Recent],TRUE,Transactions[Custom Category],Transactions[[#This Row],[Custom Category]]) -> -18125.097 | T234: =SUMIFS(Transactions[Amount],Transactions[Month],Transactions[[#This Row],[Month]],Transactions[Custom Category],Transactions[[#This Row],[Custom Category]]) -> -1434.43 | U234: =IF(COUNTIF(Budgets[Custom Category],Transactions[[#This Row],[Custom Category]])=0,Transactions[[#This Row],[6M AVG]],_xlfn.XLOOKUP(Transactions[[#This Row],[Custom Category]],Budgets[Custom Category],Budgets[Monthly],0,0)) -> -18125.097 | V234: =IF(Transactions[[#This Row],[Month]]=Sel_Month,Transactions[[#This Row],[Amount]],0) -> 0
A235: eOMxkwaqNZH7Vznj6o6XTA4KJOvewbhnEVmgd | B235: added | C235: 0.46 | D235: Bank Fees, Overdraft | E235: 2023-10-16, 8:00:00 p.m. | F235: CAD | H235: Overdraft interest | I235: other | J235: FALSE | K235: gO8zvLa3NoHaQ0YpjAjgTz6wOrNX97U8JerDB | L235: =_xlfn.XLOOKUP(Transactions[[#This Row],[Account ID]],Accounts[Plaid Account ID],Accounts[Name],"Not Found",0) -> RBC Staff Banking | M235: =_xlfn.XLOOKUP(Transactions[[#This Row],[Account ID]],Accounts[Plaid Account ID],Accounts[Institution Name],"Not Found",0) -> RBC Royal Bank | N235: =IF(Transactions[[#This Row],[Amount]]<0,"credit","debit") -> debit | O235: {=IF( ISNUMBER(MATCH(Transactions[[#This Row],[Categories]], _xlfn._xlws.FILTER(Custom_Cat[Name], LEN(Custom_Cat[Name]) >= 3), 0)), INDEX(Custom_Cat[Custom Category], MATCH(Transactions[[#This Row],[Categories]], _xlfn._xlws.FILTER(Custom_Cat[Name], LEN(Custom_Cat[Name]) >= 3), 0)), IFERROR( INDEX( Custom_Cat[Custom Category], MATCH( 1, (ISNUMBER(SEARCH(LOWER(Custom_Cat[Name]), LOWER(Transactions[[#This Row],[Name]])))) * (LEN(Custom_Cat[Name]) >= 3) * ( (IF(LEFT(Custom_Cat[Amount],1)="<",Transactions[[#This Row],[Amount]]<VALUE(MID(Custom_Cat[Amount], 2, LEN(Custom_Cat[Amount])-1)),TRUE)) * (IF(LEFT(Custom_Cat[Amount],1)=">",Transactions[[#This Row],[Amount]]>VALUE(MID(Custom_Cat[Amount], 2, LEN(Custom_Cat[Amount])-1)),TRUE)) ), 0 ) ), Transactions[[#This Row],[Categories]] ) )} -> Bank Fees | P235: =DATE(LEFT(Transactions[[#This Row],[Date]],4),MID(Transactions[[#This Row],[Date]],6,2),MID(Transactions[[#This Row],[Date]],9,2))+IF(RIGHT(Transactions[[#This Row],[Date]],2)="pm",IF(MID(Transactions[[#This Row],[Date]],12,2)<12,0.5,0),IF(MID(Transactions[[#This Row],[Date]],12,2)=12,-0.5,0)) -> 45215 | Q235: =DATE(YEAR(Transactions[[#This Row],[Datetime]]),MONTH(Transactions[[#This Row],[Datetime]]),1) -> 45200 | R235: =AND(Transactions[[#This Row],[Datetime]]>=EDATE(MAX(Transactions[Datetime]),-6),Transactions[[#This Row],[Datetime]]<=TODAY()) -> FALSE | S235: =AVERAGEIFS(Transactions[Month''s Total],Transactions[Recent],TRUE,Transactions[Custom Category],Transactions[[#This Row],[Custom Category]]) -> 2.5077778 | T235: =SUMIFS(Transactions[Amount],Transactions[Month],Transactions[[#This Row],[Month]],Transactions[Custom Category],Transactions[[#This Row],[Custom Category]]) -> 0.46 | U235: =IF(COUNTIF(Budgets[Custom Category],Transactions[[#This Row],[Custom Category]])=0,Transactions[[#This Row],[6M AVG]],_xlfn.XLOOKUP(Transactions[[#This Row],[Custom Category]],Budgets[Custom Category],Budgets[Monthly],0,0)) -> 2.5077778 | V235: =IF(Transactions[[#This Row],[Month]]=Sel_Month,Transactions[[#This Row],[Amount]],0) -> 0
A236: eOMxkwaqNZH7Vznj6o6XTA4KJOvewbhnEVmgd | B236: added | C236: -40.67 | D236: Transfer, Third Party, PayPal | E236: 2023-10-16, 8:00:00 p.m. | F236: CAD | H236: Misc Payment PAYPAL | I236: other | J236: FALSE | K236: 7XKm7e1kPjSN8406PMPpHBoDkwnM6Zt0eVbqp | L236: =_xlfn.XLOOKUP(Transactions[[#This Row],[Account ID]],Accounts[Plaid Account ID],Accounts[Name],"Not Found",0) -> RBC Staff Banking | M236: =_xlfn.XLOOKUP(Transactions[[#This Row],[Account ID]],Accounts[Plaid Account ID],Accounts[Institution Name],"Not Found",0) -> RBC Royal Bank | N236: =IF(Transactions[[#This Row],[Amount]]<0,"credit","debit") -> credit | O236: {=IF( ISNUMBER(MATCH(Transactions[[#This Row],[Categories]], _xlfn._xlws.FILTER(Custom_Cat[Name], LEN(Custom_Cat[Name]) >= 3), 0)), INDEX(Custom_Cat[Custom Category], MATCH(Transactions[[#This Row],[Categories]], _xlfn._xlws.FILTER(Custom_Cat[Name], LEN(Custom_Cat[Name]) >= 3), 0)), IFERROR( INDEX( Custom_Cat[Custom Category], MATCH( 1, (ISNUMBER(SEARCH(LOWER(Custom_Cat[Name]), LOWER(Transactions[[#This Row],[Name]])))) * (LEN(Custom_Cat[Name]) >= 3) * ( (IF(LEFT(Custom_Cat[Amount],1)="<",Transactions[[#This Row],[Amount]]<VALUE(MID(Custom_Cat[Amount], 2, LEN(Custom_Cat[Amount])-1)),TRUE)) * (IF(LEFT(Custom_Cat[Amount],1)=">",Transactions[[#This Row],[Amount]]>VALUE(MID(Custom_Cat[Amount], 2, LEN(Custom_Cat[Amount])-1)),TRUE)) ), 0 ) ), Transactions[[#This Row],[Categories]] ) )} -> Transfer,Internal | P236: =DATE(LEFT(Transactions[[#This Row],[Date]],4),MID(Transactions[[#This Row],[Date]],6,2),MID(Transactions[[#This Row],[Date]],9,2))+IF(RIGHT(Transactions[[#This Row],[Date]],2)="pm",IF(MID(Transactions[[#This Row],[Date]],12,2)<12,0.5,0),IF(MID(Transactions[[#This Row],[Date]],12,2)=12,-0.5,0)) -> 45215 | Q236: =DATE(YEAR(Transactions[[#This Row],[Datetime]]),MONTH(Transactions[[#This Row],[Datetime]]),1) -> 45200 | R236: =AND(Transactions[[#This Row],[Datetime]]>=EDATE(MAX(Transactions[Datetime]),-6),Transactions[[#This Row],[Datetime]]<=TODAY()) -> FALSE | S236: =AVERAGEIFS(Transactions[Month''s Total],Transactions[Recent],TRUE,Transactions[Custom Category],Transactions[[#This Row],[Custom Category]]) -> 14532.99 | T236: =SUMIFS(Transactions[Amount],Transactions[Month],Transactions[[#This Row],[Month]],Transactions[Custom Category],Transactions[[#This Row],[Custom Category]]) -> 3947.82 | U236: =IF(COUNTIF(Budgets[Custom Category],Transactions[[#This Row],[Custom Category]])=0,Transactions[[#This Row],[6M AVG]],_xlfn.XLOOKUP(Transactions[[#This Row],[Custom Category]],Budgets[Custom Category],Budgets[Monthly],0,0)) -> 14532.99 | V236: =IF(Transactions[[#This Row],[Month]]=Sel_Month,Transactions[[#This Row],[Amount]],0) -> 0
A237: eOMxkwaqNZH7Vznj6o6XTA4KJOvewbhnEVmgd | B237: added | C237: 50 | D237: Transfer, Debit | E237: 2023-10-16, 8:00:00 p.m. | F237: CAD | H237: e-Transfer sent Mina Morshed | I237: other | J237: FALSE | K237: 9XAwVpqvB4SJ7qVOnyngi8Mg3XoQPjfg1evVD | L237: =_xlfn.XLOOKUP(Transactions[[#This Row],[Account ID]],Accounts[Plaid Account ID],Accounts[Name],"Not Found",0) -> RBC Staff Banking | M237: =_xlfn.XLOOKUP(Transactions[[#This Row],[Account ID]],Accounts[Plaid Account ID],Accounts[Institution Name],"Not Found",0) -> RBC Royal Bank | N237: =IF(Transactions[[#This Row],[Amount]]<0,"credit","debit") -> debit | O237: {=IF( ISNUMBER(MATCH(Transactions[[#This Row],[Categories]], _xlfn._xlws.FILTER(Custom_Cat[Name], LEN(Custom_Cat[Name]) >= 3), 0)), INDEX(Custom_Cat[Custom Category], MATCH(Transactions[[#This Row],[Categories]], _xlfn._xlws.FILTER(Custom_Cat[Name], LEN(Custom_Cat[Name]) >= 3), 0)), IFERROR( INDEX( Custom_Cat[Custom Category], MATCH( 1, (ISNUMBER(SEARCH(LOWER(Custom_Cat[Name]), LOWER(Transactions[[#This Row],[Name]])))) * (LEN(Custom_Cat[Name]) >= 3) * ( (IF(LEFT(Custom_Cat[Amount],1)="<",Transactions[[#This Row],[Amount]]<VALUE(MID(Custom_Cat[Amount], 2, LEN(Custom_Cat[Amount])-1)),TRUE)) * (IF(LEFT(Custom_Cat[Amount],1)=">",Transactions[[#This Row],[Amount]]>VALUE(MID(Custom_Cat[Amount], 2, LEN(Custom_Cat[Amount])-1)),TRUE)) ), 0 ) ), Transactions[[#This Row],[Categories]] ) )} -> Transfer, Debit | P237: =DATE(LEFT(Transactions[[#This Row],[Date]],4),MID(Transactions[[#This Row],[Date]],6,2),MID(Transactions[[#This Row],[Date]],9,2))+IF(RIGHT(Transactions[[#This Row],[Date]],2)="pm",IF(MID(Transactions[[#This Row],[Date]],12,2)<12,0.5,0),IF(MID(Transactions[[#This Row],[Date]],12,2)=12,-0.5,0)) -> 45215 | Q237: =DATE(YEAR(Transactions[[#This Row],[Datetime]]),MONTH(Transactions[[#This Row],[Datetime]]),1) -> 45200 | R237: =AND(Transactions[[#This Row],[Datetime]]>=EDATE(MAX(Transactions[Datetime]),-6),Transactions[[#This Row],[Datetime]]<=TODAY()) -> FALSE | S237: =AVERAGEIFS(Transactions[Month''s Total],Transactions[Recent],TRUE,Transactions[Custom Category],Transactions[[#This Row],[Custom Category]]) -> 12758.461 | T237: =SUMIFS(Transactions[Amount],Transactions[Month],Transactions[[#This Row],[Month]],Transactions[Custom Category],Transactions[[#This Row],[Custom Category]]) -> 1148.73 | U237: =IF(COUNTIF(Budgets[Custom Category],Transactions[[#This Row],[Custom Category]])=0,Transactions[[#This Row],[6M AVG]],_xlfn.XLOOKUP(Transactions[[#This Row],[Custom Category]],Budgets[Custom Category],Budgets[Monthly],0,0)) -> 12758.461 | V237: =IF(Transactions[[#This Row],[Month]]=Sel_Month,Transactions[[#This Row],[Amount]],0) -> 0
A238: eOMxkwaqNZH7Vznj6o6XTA4KJOvewbhnEVmgd | B238: added | C238: 973.93 | D238: Transfer, Debit | E238: 2023-10-18, 8:00:00 p.m. | F238: CAD | H238: Online Banking transfer - 6133 | I238: other | J238: FALSE | K238: oN4L8KpOzEuYrb1g4k4vTxr91PjR3pU4wmRP5 | L238: =_xlfn.XLOOKUP(Transactions[[#This Row],[Account ID]],Accounts[Plaid Account ID],Accounts[Name],"Not Found",0) -> RBC Staff Banking | M238: =_xlfn.XLOOKUP(Transactions[[#This Row],[Account ID]],Accounts[Plaid Account ID],Accounts[Institution Name],"Not Found",0) -> RBC Royal Bank | N238: =IF(Transactions[[#This Row],[Amount]]<0,"credit","debit") -> debit | O238: {=IF( ISNUMBER(MATCH(Transactions[[#This Row],[Categories]], _xlfn._xlws.FILTER(Custom_Cat[Name], LEN(Custom_Cat[Name]) >= 3), 0)), INDEX(Custom_Cat[Custom Category], MATCH(Transactions[[#This Row],[Categories]], _xlfn._xlws.FILTER(Custom_Cat[Name], LEN(Custom_Cat[Name]) >= 3), 0)), IFERROR( INDEX( Custom_Cat[Custom Category], MATCH( 1, (ISNUMBER(SEARCH(LOWER(Custom_Cat[Name]), LOWER(Transactions[[#This Row],[Name]])))) * (LEN(Custom_Cat[Name]) >= 3) * ( (IF(LEFT(Custom_Cat[Amount],1)="<",Transactions[[#This Row],[Amount]]<VALUE(MID(Custom_Cat[Amount], 2, LEN(Custom_Cat[Amount])-1)),TRUE)) * (IF(LEFT(Custom_Cat[Amount],1)=">",Transactions[[#This Row],[Amount]]>VALUE(MID(Custom_Cat[Amount], 2, LEN(Custom_Cat[Amount])-1)),TRUE)) ), 0 ) ), Transactions[[#This Row],[Categories]] ) )} -> Transfer, Debit | P238: =DATE(LEFT(Transactions[[#This Row],[Date]],4),MID(Transactions[[#This Row],[Date]],6,2),MID(Transactions[[#This Row],[Date]],9,2))+IF(RIGHT(Transactions[[#This Row],[Date]],2)="pm",IF(MID(Transactions[[#This Row],[Date]],12,2)<12,0.5,0),IF(MID(Transactions[[#This Row],[Date]],12,2)=12,-0.5,0)) -> 45217 | Q238: =DATE(YEAR(Transactions[[#This Row],[Datetime]]),MONTH(Transactions[[#This Row],[Datetime]]),1) -> 45200 | R238: =AND(Transactions[[#This Row],[Datetime]]>=EDATE(MAX(Transactions[Datetime]),-6),Transactions[[#This Row],[Datetime]]<=TODAY()) -> FALSE | S238: =AVERAGEIFS(Transactions[Month''s Total],Transactions[Recent],TRUE,Transactions[Custom Category],Transactions[[#This Row],[Custom Category]]) -> 12758.461 | T238: =SUMIFS(Transactions[Amount],Transactions[Month],Transactions[[#This Row],[Month]],Transactions[Custom Category],Transactions[[#This Row],[Custom Category]]) -> 1148.73 | U238: =IF(COUNTIF(Budgets[Custom Category],Transactions[[#This Row],[Custom Category]])=0,Transactions[[#This Row],[6M AVG]],_xlfn.XLOOKUP(Transactions[[#This Row],[Custom Category]],Budgets[Custom Category],Budgets[Monthly],0,0)) -> 12758.461 | V238: =IF(Transactions[[#This Row],[Month]]=Sel_Month,Transactions[[#This Row],[Amount]],0) -> 0
A239: eOMxkwaqNZH7Vznj6o6XTA4KJOvewbhnEVmgd | B239: added | C239: -660 | D239: Transfer, Credit | E239: 2023-10-18, 8:00:00 p.m. | F239: CAD | H239: e-Transfer - Autodeposit PAULA ANDREA AMARILES RESTREPO C1AA8phgk9NF | I239: other | J239: FALSE | K239: bp893zMDNxT90nm7Q5QEskAbRZX0jzCJnEkmm | L239: =_xlfn.XLOOKUP(Transactions[[#This Row],[Account ID]],Accounts[Plaid Account ID],Accounts[Name],"Not Found",0) -> RBC Staff Banking | M239: =_xlfn.XLOOKUP(Transactions[[#This Row],[Account ID]],Accounts[Plaid Account ID],Accounts[Institution Name],"Not Found",0) -> RBC Royal Bank | N239: =IF(Transactions[[#This Row],[Amount]]<0,"credit","debit") -> credit | O239: {=IF( ISNUMBER(MATCH(Transactions[[#This Row],[Categories]], _xlfn._xlws.FILTER(Custom_Cat[Name], LEN(Custom_Cat[Name]) >= 3), 0)), INDEX(Custom_Cat[Custom Category], MATCH(Transactions[[#This Row],[Categories]], _xlfn._xlws.FILTER(Custom_Cat[Name], LEN(Custom_Cat[Name]) >= 3), 0)), IFERROR( INDEX( Custom_Cat[Custom Category], MATCH( 1, (ISNUMBER(SEARCH(LOWER(Custom_Cat[Name]), LOWER(Transactions[[#This Row],[Name]])))) * (LEN(Custom_Cat[Name]) >= 3) * ( (IF(LEFT(Custom_Cat[Amount],1)="<",Transactions[[#This Row],[Amount]]<VALUE(MID(Custom_Cat[Amount], 2, LEN(Custom_Cat[Amount])-1)),TRUE)) * (IF(LEFT(Custom_Cat[Amount],1)=">",Transactions[[#This Row],[Amount]]>VALUE(MID(Custom_Cat[Amount], 2, LEN(Custom_Cat[Amount])-1)),TRUE)) ), 0 ) ), Transactions[[#This Row],[Categories]] ) )} -> Transfer,Internal | P239: =DATE(LEFT(Transactions[[#This Row],[Date]],4),MID(Transactions[[#This Row],[Date]],6,2),MID(Transactions[[#This Row],[Date]],9,2))+IF(RIGHT(Transactions[[#This Row],[Date]],2)="pm",IF(MID(Transactions[[#This Row],[Date]],12,2)<12,0.5,0),IF(MID(Transactions[[#This Row],[Date]],12,2)=12,-0.5,0)) -> 45217 | Q239: =DATE(YEAR(Transactions[[#This Row],[Datetime]]),MONTH(Transactions[[#This Row],[Datetime]]),1) -> 45200 | R239: =AND(Transactions[[#This Row],[Datetime]]>=EDATE(MAX(Transactions[Datetime]),-6),Transactions[[#This Row],[Datetime]]<=TODAY()) -> FALSE | S239: =AVERAGEIFS(Transactions[Month''s Total],Transactions[Recent],TRUE,Transactions[Custom Category],Transactions[[#This Row],[Custom Category]]) -> 14532.99 | T239: =SUMIFS(Transactions[Amount],Transactions[Month],Transactions[[#This Row],[Month]],Transactions[Custom Category],Transactions[[#This Row],[Custom Category]]) -> 3947.82 | U239: =IF(COUNTIF(Budgets[Custom Category],Transactions[[#This Row],[Custom Category]])=0,Transactions[[#This Row],[6M AVG]],_xlfn.XLOOKUP(Transactions[[#This Row],[Custom Category]],Budgets[Custom Category],Budgets[Monthly],0,0)) -> 14532.99 | V239: =IF(Transactions[[#This Row],[Month]]=Sel_Month,Transactions[[#This Row],[Amount]],0) -> 0
A240: eOMxkwaqNZH7Vznj6o6XTA4KJOvewbhnEVmgd | B240: added | C240: 192.58 | D240: Service, Financial, Loans and Mortgages | E240: 2023-10-19, 8:00:00 p.m. | F240: CAD | G240: Personal Loan Spl | H240: Personal Loan SPL | I240: online | J240: FALSE | K240: 5X3rbpLyDvSjXnV1EPEZi9zQ3D1jgwcwvjrKR | L240: =_xlfn.XLOOKUP(Transactions[[#This Row],[Account ID]],Accounts[Plaid Account ID],Accounts[Name],"Not Found",0) -> RBC Staff Banking | M240: =_xlfn.XLOOKUP(Transactions[[#This Row],[Account ID]],Accounts[Plaid Account ID],Accounts[Institution Name],"Not Found",0) -> RBC Royal Bank | N240: =IF(Transactions[[#This Row],[Amount]]<0,"credit","debit") -> debit | O240: {=IF( ISNUMBER(MATCH(Transactions[[#This Row],[Categories]], _xlfn._xlws.FILTER(Custom_Cat[Name], LEN(Custom_Cat[Name]) >= 3), 0)), INDEX(Custom_Cat[Custom Category], MATCH(Transactions[[#This Row],[Categories]], _xlfn._xlws.FILTER(Custom_Cat[Name], LEN(Custom_Cat[Name]) >= 3), 0)), IFERROR( INDEX( Custom_Cat[Custom Category], MATCH( 1, (ISNUMBER(SEARCH(LOWER(Custom_Cat[Name]), LOWER(Transactions[[#This Row],[Name]])))) * (LEN(Custom_Cat[Name]) >= 3) * ( (IF(LEFT(Custom_Cat[Amount],1)="<",Transactions[[#This Row],[Amount]]<VALUE(MID(Custom_Cat[Amount], 2, LEN(Custom_Cat[Amount])-1)),TRUE)) * (IF(LEFT(Custom_Cat[Amount],1)=">",Transactions[[#This Row],[Amount]]>VALUE(MID(Custom_Cat[Amount], 2, LEN(Custom_Cat[Amount])-1)),TRUE)) ), 0 ) ), Transactions[[#This Row],[Categories]] ) )} -> Loans,Car | P240: =DATE(LEFT(Transactions[[#This Row],[Date]],4),MID(Transactions[[#This Row],[Date]],6,2),MID(Transactions[[#This Row],[Date]],9,2))+IF(RIGHT(Transactions[[#This Row],[Date]],2)="pm",IF(MID(Transactions[[#This Row],[Date]],12,2)<12,0.5,0),IF(MID(Transactions[[#This Row],[Date]],12,2)=12,-0.5,0)) -> 45218 | Q240: =DATE(YEAR(Transactions[[#This Row],[Datetime]]),MONTH(Transactions[[#This Row],[Datetime]]),1) -> 45200 | R240: =AND(Transactions[[#This Row],[Datetime]]>=EDATE(MAX(Transactions[Datetime]),-6),Transactions[[#This Row],[Datetime]]<=TODAY()) -> FALSE | S240: =AVERAGEIFS(Transactions[Month''s Total],Transactions[Recent],TRUE,Transactions[Custom Category],Transactions[[#This Row],[Custom Category]]) -> 624.12818 | T240: =SUMIFS(Transactions[Amount],Transactions[Month],Transactions[[#This Row],[Month]],Transactions[Custom Category],Transactions[[#This Row],[Custom Category]]) -> 385.16 | U240: =IF(COUNTIF(Budgets[Custom Category],Transactions[[#This Row],[Custom Category]])=0,Transactions[[#This Row],[6M AVG]],_xlfn.XLOOKUP(Transactions[[#This Row],[Custom Category]],Budgets[Custom Category],Budgets[Monthly],0,0)) -> 624.12818 | V240: =IF(Transactions[[#This Row],[Month]]=Sel_Month,Transactions[[#This Row],[Amount]],0) -> 0
A241: eOMxkwaqNZH7Vznj6o6XTA4KJOvewbhnEVmgd | B241: added | C241: 50 | D241: Transfer, Debit | E241: 2023-10-22, 8:00:00 p.m. | F241: CAD | H241: e-Transfer sent Childcraft TKEJWD | I241: other | J241: FALSE | K241: 8ekd9pPAqrtQrAjep3pmc6b3P1gLRmIxDbo9V | L241: =_xlfn.XLOOKUP(Transactions[[#This Row],[Account ID]],Accounts[Plaid Account ID],Accounts[Name],"Not Found",0) -> RBC Staff Banking | M241: =_xlfn.XLOOKUP(Transactions[[#This Row],[Account ID]],Accounts[Plaid Account ID],Accounts[Institution Name],"Not Found",0) -> RBC Royal Bank | N241: =IF(Transactions[[#This Row],[Amount]]<0,"credit","debit") -> debit | O241: {=IF( ISNUMBER(MATCH(Transactions[[#This Row],[Categories]], _xlfn._xlws.FILTER(Custom_Cat[Name], LEN(Custom_Cat[Name]) >= 3), 0)), INDEX(Custom_Cat[Custom Category], MATCH(Transactions[[#This Row],[Categories]], _xlfn._xlws.FILTER(Custom_Cat[Name], LEN(Custom_Cat[Name]) >= 3), 0)), IFERROR( INDEX( Custom_Cat[Custom Category], MATCH( 1, (ISNUMBER(SEARCH(LOWER(Custom_Cat[Name]), LOWER(Transactions[[#This Row],[Name]])))) * (LEN(Custom_Cat[Name]) >= 3) * ( (IF(LEFT(Custom_Cat[Amount],1)="<",Transactions[[#This Row],[Amount]]<VALUE(MID(Custom_Cat[Amount], 2, LEN(Custom_Cat[Amount])-1)),TRUE)) * (IF(LEFT(Custom_Cat[Amount],1)=">",Transactions[[#This Row],[Amount]]>VALUE(MID(Custom_Cat[Amount], 2, LEN(Custom_Cat[Amount])-1)),TRUE)) ), 0 ) ), Transactions[[#This Row],[Categories]] ) )} -> Transfer, Debit | P241: =DATE(LEFT(Transactions[[#This Row],[Date]],4),MID(Transactions[[#This Row],[Date]],6,2),MID(Transactions[[#This Row],[Date]],9,2))+IF(RIGHT(Transactions[[#This Row],[Date]],2)="pm",IF(MID(Transactions[[#This Row],[Date]],12,2)<12,0.5,0),IF(MID(Transactions[[#This Row],[Date]],12,2)=12,-0.5,0)) -> 45221 | Q241: =DATE(YEAR(Transactions[[#This Row],[Datetime]]),MONTH(Transactions[[#This Row],[Datetime]]),1) -> 45200 | R241: =AND(Transactions[[#This Row],[Datetime]]>=EDATE(MAX(Transactions[Datetime]),-6),Transactions[[#This Row],[Datetime]]<=TODAY()) -> FALSE | S241: =AVERAGEIFS(Transactions[Month''s Total],Transactions[Recent],TRUE,Transactions[Custom Category],Transactions[[#This Row],[Custom Category]]) -> 12758.461 | T241: =SUMIFS(Transactions[Amount],Transactions[Month],Transactions[[#This Row],[Month]],Transactions[Custom Category],Transactions[[#This Row],[Custom Category]]) -> 1148.73 | U241: =IF(COUNTIF(Budgets[Custom Category],Transactions[[#This Row],[Custom Category]])=0,Transactions[[#This Row],[6M AVG]],_xlfn.XLOOKUP(Transactions[[#This Row],[Custom Category]],Budgets[Custom Category],Budgets[Monthly],0,0)) -> 12758.461 | V241: =IF(Transactions[[#This Row],[Month]]=Sel_Month,Transactions[[#This Row],[Amount]],0) -> 0
A242: eOMxkwaqNZH7Vznj6o6XTA4KJOvewbhnEVmgd | B242: added | C242: -479 | D242: Transfer, Credit | E242: 2023-10-22, 8:00:00 p.m. | F242: CAD | H242: e-Transfer - Autodeposit PAULA ANDREA AMARILES RESTREPO C1Ac22cpjPaj | I242: other | J242: FALSE | K242: ZORJwzanNkHyVPDOemeocB6pX7EqzMtbmYexr | L242: =_xlfn.XLOOKUP(Transactions[[#This Row],[Account ID]],Accounts[Plaid Account ID],Accounts[Name],"Not Found",0) -> RBC Staff Banking | M242: =_xlfn.XLOOKUP(Transactions[[#This Row],[Account ID]],Accounts[Plaid Account ID],Accounts[Institution Name],"Not Found",0) -> RBC Royal Bank | N242: =IF(Transactions[[#This Row],[Amount]]<0,"credit","debit") -> credit | O242: {=IF( ISNUMBER(MATCH(Transactions[[#This Row],[Categories]], _xlfn._xlws.FILTER(Custom_Cat[Name], LEN(Custom_Cat[Name]) >= 3), 0)), INDEX(Custom_Cat[Custom Category], MATCH(Transactions[[#This Row],[Categories]], _xlfn._xlws.FILTER(Custom_Cat[Name], LEN(Custom_Cat[Name]) >= 3), 0)), IFERROR( INDEX( Custom_Cat[Custom Category], MATCH( 1, (ISNUMBER(SEARCH(LOWER(Custom_Cat[Name]), LOWER(Transactions[[#This Row],[Name]])))) * (LEN(Custom_Cat[Name]) >= 3) * ( (IF(LEFT(Custom_Cat[Amount],1)="<",Transactions[[#This Row],[Amount]]<VALUE(MID(Custom_Cat[Amount], 2, LEN(Custom_Cat[Amount])-1)),TRUE)) * (IF(LEFT(Custom_Cat[Amount],1)=">",Transactions[[#This Row],[Amount]]>VALUE(MID(Custom_Cat[Amount], 2, LEN(Custom_Cat[Amount])-1)),TRUE)) ), 0 ) ), Transactions[[#This Row],[Categories]] ) )} -> Transfer,Internal | P242: =DATE(LEFT(Transactions[[#This Row],[Date]],4),MID(Transactions[[#This Row],[Date]],6,2),MID(Transactions[[#This Row],[Date]],9,2))+IF(RIGHT(Transactions[[#This Row],[Date]],2)="pm",IF(MID(Transactions[[#This Row],[Date]],12,2)<12,0.5,0),IF(MID(Transactions[[#This Row],[Date]],12,2)=12,-0.5,0)) -> 45221 | Q242: =DATE(YEAR(Transactions[[#This Row],[Datetime]]),MONTH(Transactions[[#This Row],[Datetime]]),1) -> 45200 | R242: =AND(Transactions[[#This Row],[Datetime]]>=EDATE(MAX(Transactions[Datetime]),-6),Transactions[[#This Row],[Datetime]]<=TODAY()) -> FALSE | S242: =AVERAGEIFS(Transactions[Month''s Total],Transactions[Recent],TRUE,Transactions[Custom Category],Transactions[[#This Row],[Custom Category]]) -> 14532.99 | T242: =SUMIFS(Transactions[Amount],Transactions[Month],Transactions[[#This Row],[Month]],Transactions[Custom Category],Transactions[[#This Row],[Custom Category]]) -> 3947.82 | U242: =IF(COUNTIF(Budgets[Custom Category],Transactions[[#This Row],[Custom Category]])=0,Transactions[[#This Row],[6M AVG]],_xlfn.XLOOKUP(Transactions[[#This Row],[Custom Category]],Budgets[Custom Category],Budgets[Monthly],0,0)) -> 14532.99 | V242: =IF(Transactions[[#This Row],[Month]]=Sel_Month,Transactions[[#This Row],[Amount]],0) -> 0
A243: eOMxkwaqNZH7Vznj6o6XTA4KJOvewbhnEVmgd | B243: added | C243: 6.03 | D243: Transfer, Debit | E243: 2023-10-24, 8:00:00 p.m. | F243: CAD | H243: Online transfer sent - 3876 Automatos Consulting | I243: other | J243: FALSE | K243: JpJrezRvoQTpmz9wbZb3IX5DmZejR0HmyJKpq | L243: =_xlfn.XLOOKUP(Transactions[[#This Row],[Account ID]],Accounts[Plaid Account ID],Accounts[Name],"Not Found",0) -> RBC Staff Banking | M243: =_xlfn.XLOOKUP(Transactions[[#This Row],[Account ID]],Accounts[Plaid Account ID],Accounts[Institution Name],"Not Found",0) -> RBC Royal Bank | N243: =IF(Transactions[[#This Row],[Amount]]<0,"credit","debit") -> debit | O243: {=IF( ISNUMBER(MATCH(Transactions[[#This Row],[Categories]], _xlfn._xlws.FILTER(Custom_Cat[Name], LEN(Custom_Cat[Name]) >= 3), 0)), INDEX(Custom_Cat[Custom Category], MATCH(Transactions[[#This Row],[Categories]], _xlfn._xlws.FILTER(Custom_Cat[Name], LEN(Custom_Cat[Name]) >= 3), 0)), IFERROR( INDEX( Custom_Cat[Custom Category], MATCH( 1, (ISNUMBER(SEARCH(LOWER(Custom_Cat[Name]), LOWER(Transactions[[#This Row],[Name]])))) * (LEN(Custom_Cat[Name]) >= 3) * ( (IF(LEFT(Custom_Cat[Amount],1)="<",Transactions[[#This Row],[Amount]]<VALUE(MID(Custom_Cat[Amount], 2, LEN(Custom_Cat[Amount])-1)),TRUE)) * (IF(LEFT(Custom_Cat[Amount],1)=">",Transactions[[#This Row],[Amount]]>VALUE(MID(Custom_Cat[Amount], 2, LEN(Custom_Cat[Amount])-1)),TRUE)) ), 0 ) ), Transactions[[#This Row],[Categories]] ) )} -> Income,Salary | P243: =DATE(LEFT(Transactions[[#This Row],[Date]],4),MID(Transactions[[#This Row],[Date]],6,2),MID(Transactions[[#This Row],[Date]],9,2))+IF(RIGHT(Transactions[[#This Row],[Date]],2)="pm",IF(MID(Transactions[[#This Row],[Date]],12,2)<12,0.5,0),IF(MID(Transactions[[#This Row],[Date]],12,2)=12,-0.5,0)) -> 45223 | Q243: =DATE(YEAR(Transactions[[#This Row],[Datetime]]),MONTH(Transactions[[#This Row],[Datetime]]),1) -> 45200 | R243: =AND(Transactions[[#This Row],[Datetime]]>=EDATE(MAX(Transactions[Datetime]),-6),Transactions[[#This Row],[Datetime]]<=TODAY()) -> FALSE | S243: =AVERAGEIFS(Transactions[Month''s Total],Transactions[Recent],TRUE,Transactions[Custom Category],Transactions[[#This Row],[Custom Category]]) -> -18125.097 | T243: =SUMIFS(Transactions[Amount],Transactions[Month],Transactions[[#This Row],[Month]],Transactions[Custom Category],Transactions[[#This Row],[Custom Category]]) -> -1434.43 | U243: =IF(COUNTIF(Budgets[Custom Category],Transactions[[#This Row],[Custom Category]])=0,Transactions[[#This Row],[6M AVG]],_xlfn.XLOOKUP(Transactions[[#This Row],[Custom Category]],Budgets[Custom Category],Budgets[Monthly],0,0)) -> -18125.097 | V243: =IF(Transactions[[#This Row],[Month]]=Sel_Month,Transactions[[#This Row],[Amount]],0) -> 0
A244: eOMxkwaqNZH7Vznj6o6XTA4KJOvewbhnEVmgd | B244: added | C244: 0.06 | D244: Shops | E244: 2023-10-29, 8:00:00 p.m. | F244: CAD | G244: eBay | H244: Misc Payment EBAY CANADA LTD | I244: online | J244: FALSE | K244: jOoXrPpkN7HKQmxMzAzLTXvM6gnwZYHexgEXj | L244: =_xlfn.XLOOKUP(Transactions[[#This Row],[Account ID]],Accounts[Plaid Account ID],Accounts[Name],"Not Found",0) -> RBC Staff Banking | M244: =_xlfn.XLOOKUP(Transactions[[#This Row],[Account ID]],Accounts[Plaid Account ID],Accounts[Institution Name],"Not Found",0) -> RBC Royal Bank | N244: =IF(Transactions[[#This Row],[Amount]]<0,"credit","debit") -> debit | O244: {=IF( ISNUMBER(MATCH(Transactions[[#This Row],[Categories]], _xlfn._xlws.FILTER(Custom_Cat[Name], LEN(Custom_Cat[Name]) >= 3), 0)), INDEX(Custom_Cat[Custom Category], MATCH(Transactions[[#This Row],[Categories]], _xlfn._xlws.FILTER(Custom_Cat[Name], LEN(Custom_Cat[Name]) >= 3), 0)), IFERROR( INDEX( Custom_Cat[Custom Category], MATCH( 1, (ISNUMBER(SEARCH(LOWER(Custom_Cat[Name]), LOWER(Transactions[[#This Row],[Name]])))) * (LEN(Custom_Cat[Name]) >= 3) * ( (IF(LEFT(Custom_Cat[Amount],1)="<",Transactions[[#This Row],[Amount]]<VALUE(MID(Custom_Cat[Amount], 2, LEN(Custom_Cat[Amount])-1)),TRUE)) * (IF(LEFT(Custom_Cat[Amount],1)=">",Transactions[[#This Row],[Amount]]>VALUE(MID(Custom_Cat[Amount], 2, LEN(Custom_Cat[Amount])-1)),TRUE)) ), 0 ) ), Transactions[[#This Row],[Categories]] ) )} -> Transfer,Internal | P244: =DATE(LEFT(Transactions[[#This Row],[Date]],4),MID(Transactions[[#This Row],[Date]],6,2),MID(Transactions[[#This Row],[Date]],9,2))+IF(RIGHT(Transactions[[#This Row],[Date]],2)="pm",IF(MID(Transactions[[#This Row],[Date]],12,2)<12,0.5,0),IF(MID(Transactions[[#This Row],[Date]],12,2)=12,-0.5,0)) -> 45228 | Q244: =DATE(YEAR(Transactions[[#This Row],[Datetime]]),MONTH(Transactions[[#This Row],[Datetime]]),1) -> 45200 | R244: =AND(Transactions[[#This Row],[Datetime]]>=EDATE(MAX(Transactions[Datetime]),-6),Transactions[[#This Row],[Datetime]]<=TODAY()) -> FALSE | S244: =AVERAGEIFS(Transactions[Month''s Total],Transactions[Recent],TRUE,Transactions[Custom Category],Transactions[[#This Row],[Custom Category]]) -> 14532.99 | T244: =SUMIFS(Transactions[Amount],Transactions[Month],Transactions[[#This Row],[Month]],Transactions[Custom Category],Transactions[[#This Row],[Custom Category]]) -> 3947.82 | U244: =IF(COUNTIF(Budgets[Custom Category],Transactions[[#This Row],[Custom Category]])=0,Transactions[[#This Row],[6M AVG]],_xlfn.XLOOKUP(Transactions[[#This Row],[Custom Category]],Budgets[Custom Category],Budgets[Monthly],0,0)) -> 14532.99 | V244: =IF(Transactions[[#This Row],[Month]]=Sel_Month,Transactions[[#This Row],[Amount]],0) -> 0
A245: eOMxkwaqNZH7Vznj6o6XTA4KJOvewbhnEVmgd | B245: added | C245: -0.05 | D245: Transfer, Payroll | E245: 2023-10-29, 8:00:00 p.m. | F245: CAD | H245: Misc Payment EBAY CANADA LTD | I245: other | J245: FALSE | K245: rb4Povp8znTzYwXg9A9rIP8EwJAjozHVXqo8a | L245: =_xlfn.XLOOKUP(Transactions[[#This Row],[Account ID]],Accounts[Plaid Account ID],Accounts[Name],"Not Found",0) -> RBC Staff Banking | M245: =_xlfn.XLOOKUP(Transactions[[#This Row],[Account ID]],Accounts[Plaid Account ID],Accounts[Institution Name],"Not Found",0) -> RBC Royal Bank | N245: =IF(Transactions[[#This Row],[Amount]]<0,"credit","debit") -> credit | O245: {=IF( ISNUMBER(MATCH(Transactions[[#This Row],[Categories]], _xlfn._xlws.FILTER(Custom_Cat[Name], LEN(Custom_Cat[Name]) >= 3), 0)), INDEX(Custom_Cat[Custom Category], MATCH(Transactions[[#This Row],[Categories]], _xlfn._xlws.FILTER(Custom_Cat[Name], LEN(Custom_Cat[Name]) >= 3), 0)), IFERROR( INDEX( Custom_Cat[Custom Category], MATCH( 1, (ISNUMBER(SEARCH(LOWER(Custom_Cat[Name]), LOWER(Transactions[[#This Row],[Name]])))) * (LEN(Custom_Cat[Name]) >= 3) * ( (IF(LEFT(Custom_Cat[Amount],1)="<",Transactions[[#This Row],[Amount]]<VALUE(MID(Custom_Cat[Amount], 2, LEN(Custom_Cat[Amount])-1)),TRUE)) * (IF(LEFT(Custom_Cat[Amount],1)=">",Transactions[[#This Row],[Amount]]>VALUE(MID(Custom_Cat[Amount], 2, LEN(Custom_Cat[Amount])-1)),TRUE)) ), 0 ) ), Transactions[[#This Row],[Categories]] ) )} -> Transfer,Internal | P245: =DATE(LEFT(Transactions[[#This Row],[Date]],4),MID(Transactions[[#This Row],[Date]],6,2),MID(Transactions[[#This Row],[Date]],9,2))+IF(RIGHT(Transactions[[#This Row],[Date]],2)="pm",IF(MID(Transactions[[#This Row],[Date]],12,2)<12,0.5,0),IF(MID(Transactions[[#This Row],[Date]],12,2)=12,-0.5,0)) -> 45228 | Q245: =DATE(YEAR(Transactions[[#This Row],[Datetime]]),MONTH(Transactions[[#This Row],[Datetime]]),1) -> 45200 | R245: =AND(Transactions[[#This Row],[Datetime]]>=EDATE(MAX(Transactions[Datetime]),-6),Transactions[[#This Row],[Datetime]]<=TODAY()) -> FALSE | S245: =AVERAGEIFS(Transactions[Month''s Total],Transactions[Recent],TRUE,Transactions[Custom Category],Transactions[[#This Row],[Custom Category]]) -> 14532.99 | T245: =SUMIFS(Transactions[Amount],Transactions[Month],Transactions[[#This Row],[Month]],Transactions[Custom Category],Transactions[[#This Row],[Custom Category]]) -> 3947.82 | U245: =IF(COUNTIF(Budgets[Custom Category],Transactions[[#This Row],[Custom Category]])=0,Transactions[[#This Row],[6M AVG]],_xlfn.XLOOKUP(Transactions[[#This Row],[Custom Category]],Budgets[Custom Category],Budgets[Monthly],0,0)) -> 14532.99 | V245: =IF(Transactions[[#This Row],[Month]]=Sel_Month,Transactions[[#This Row],[Amount]],0) -> 0
A246: eOMxkwaqNZH7Vznj6o6XTA4KJOvewbhnEVmgd | B246: added | C246: -0.01 | D246: Transfer, Payroll | E246: 2023-10-29, 8:00:00 p.m. | F246: CAD | H246: Misc Payment EBAY CANADA LTD | I246: other | J246: FALSE | K246: 4XBJop63LASgpJk40108SNX9nADgJBHR3PaQ1 | L246: =_xlfn.XLOOKUP(Transactions[[#This Row],[Account ID]],Accounts[Plaid Account ID],Accounts[Name],"Not Found",0) -> RBC Staff Banking | M246: =_xlfn.XLOOKUP(Transactions[[#This Row],[Account ID]],Accounts[Plaid Account ID],Accounts[Institution Name],"Not Found",0) -> RBC Royal Bank | N246: =IF(Transactions[[#This Row],[Amount]]<0,"credit","debit") -> credit | O246: {=IF( ISNUMBER(MATCH(Transactions[[#This Row],[Categories]], _xlfn._xlws.FILTER(Custom_Cat[Name], LEN(Custom_Cat[Name]) >= 3), 0)), INDEX(Custom_Cat[Custom Category], MATCH(Transactions[[#This Row],[Categories]], _xlfn._xlws.FILTER(Custom_Cat[Name], LEN(Custom_Cat[Name]) >= 3), 0)), IFERROR( INDEX( Custom_Cat[Custom Category], MATCH( 1, (ISNUMBER(SEARCH(LOWER(Custom_Cat[Name]), LOWER(Transactions[[#This Row],[Name]])))) * (LEN(Custom_Cat[Name]) >= 3) * ( (IF(LEFT(Custom_Cat[Amount],1)="<",Transactions[[#This Row],[Amount]]<VALUE(MID(Custom_Cat[Amount], 2, LEN(Custom_Cat[Amount])-1)),TRUE)) * (IF(LEFT(Custom_Cat[Amount],1)=">",Transactions[[#This Row],[Amount]]>VALUE(MID(Custom_Cat[Amount], 2, LEN(Custom_Cat[Amount])-1)),TRUE)) ), 0 ) ), Transactions[[#This Row],[Categories]] ) )} -> Transfer,Internal | P246: =DATE(LEFT(Transactions[[#This Row],[Date]],4),MID(Transactions[[#This Row],[Date]],6,2),MID(Transactions[[#This Row],[Date]],9,2))+IF(RIGHT(Transactions[[#This Row],[Date]],2)="pm",IF(MID(Transactions[[#This Row],[Date]],12,2)<12,0.5,0),IF(MID(Transactions[[#This Row],[Date]],12,2)=12,-0.5,0)) -> 45228 | Q246: =DATE(YEAR(Transactions[[#This Row],[Datetime]]),MONTH(Transactions[[#This Row],[Datetime]]),1) -> 45200 | R246: =AND(Transactions[[#This Row],[Datetime]]>=EDATE(MAX(Transactions[Datetime]),-6),Transactions[[#This Row],[Datetime]]<=TODAY()) -> FALSE | S246: =AVERAGEIFS(Transactions[Month''s Total],Transactions[Recent],TRUE,Transactions[Custom Category],Transactions[[#This Row],[Custom Category]]) -> 14532.99 | T246: =SUMIFS(Transactions[Amount],Transactions[Month],Transactions[[#This Row],[Month]],Transactions[Custom Category],Transactions[[#This Row],[Custom Category]]) -> 3947.82 | U246: =IF(COUNTIF(Budgets[Custom Category],Transactions[[#This Row],[Custom Category]])=0,Transactions[[#This Row],[6M AVG]],_xlfn.XLOOKUP(Transactions[[#This Row],[Custom Category]],Budgets[Custom Category],Budgets[Monthly],0,0)) -> 14532.99 | V246: =IF(Transactions[[#This Row],[Month]]=Sel_Month,Transactions[[#This Row],[Amount]],0) -> 0
A247: eOMxkwaqNZH7Vznj6o6XTA4KJOvewbhnEVmgd | B247: added | C247: -233.55 | D247: Shops | E247: 2023-10-29, 8:00:00 p.m. | F247: CAD | H247: Misc Payment EBAY COMMERCE C | I247: other | J247: FALSE | K247: aOmnBzRLeaHw07Ken5nMiKY1XRyknxI76J0ea | L247: =_xlfn.XLOOKUP(Transactions[[#This Row],[Account ID]],Accounts[Plaid Account ID],Accounts[Name],"Not Found",0) -> RBC Staff Banking | M247: =_xlfn.XLOOKUP(Transactions[[#This Row],[Account ID]],Accounts[Plaid Account ID],Accounts[Institution Name],"Not Found",0) -> RBC Royal Bank | N247: =IF(Transactions[[#This Row],[Amount]]<0,"credit","debit") -> credit | O247: {=IF( ISNUMBER(MATCH(Transactions[[#This Row],[Categories]], _xlfn._xlws.FILTER(Custom_Cat[Name], LEN(Custom_Cat[Name]) >= 3), 0)), INDEX(Custom_Cat[Custom Category], MATCH(Transactions[[#This Row],[Categories]], _xlfn._xlws.FILTER(Custom_Cat[Name], LEN(Custom_Cat[Name]) >= 3), 0)), IFERROR( INDEX( Custom_Cat[Custom Category], MATCH( 1, (ISNUMBER(SEARCH(LOWER(Custom_Cat[Name]), LOWER(Transactions[[#This Row],[Name]])))) * (LEN(Custom_Cat[Name]) >= 3) * ( (IF(LEFT(Custom_Cat[Amount],1)="<",Transactions[[#This Row],[Amount]]<VALUE(MID(Custom_Cat[Amount], 2, LEN(Custom_Cat[Amount])-1)),TRUE)) * (IF(LEFT(Custom_Cat[Amount],1)=">",Transactions[[#This Row],[Amount]]>VALUE(MID(Custom_Cat[Amount], 2, LEN(Custom_Cat[Amount])-1)),TRUE)) ), 0 ) ), Transactions[[#This Row],[Categories]] ) )} -> Transfer,Internal | P247: =DATE(LEFT(Transactions[[#This Row],[Date]],4),MID(Transactions[[#This Row],[Date]],6,2),MID(Transactions[[#This Row],[Date]],9,2))+IF(RIGHT(Transactions[[#This Row],[Date]],2)="pm",IF(MID(Transactions[[#This Row],[Date]],12,2)<12,0.5,0),IF(MID(Transactions[[#This Row],[Date]],12,2)=12,-0.5,0)) -> 45228 | Q247: =DATE(YEAR(Transactions[[#This Row],[Datetime]]),MONTH(Transactions[[#This Row],[Datetime]]),1) -> 45200 | R247: =AND(Transactions[[#This Row],[Datetime]]>=EDATE(MAX(Transactions[Datetime]),-6),Transactions[[#This Row],[Datetime]]<=TODAY()) -> FALSE | S247: =AVERAGEIFS(Transactions[Month''s Total],Transactions[Recent],TRUE,Transactions[Custom Category],Transactions[[#This Row],[Custom Category]]) -> 14532.99 | T247: =SUMIFS(Transactions[Amount],Transactions[Month],Transactions[[#This Row],[Month]],Transactions[Custom Category],Transactions[[#This Row],[Custom Category]]) -> 3947.82 | U247: =IF(COUNTIF(Budgets[Custom Category],Transactions[[#This Row],[Custom Category]])=0,Transactions[[#This Row],[6M AVG]],_xlfn.XLOOKUP(Transactions[[#This Row],[Custom Category]],Budgets[Custom Category],Budgets[Monthly],0,0)) -> 14532.99 | V247: =IF(Transactions[[#This Row],[Month]]=Sel_Month,Transactions[[#This Row],[Amount]],0) -> 0
A248: eOMxkwaqNZH7Vznj6o6XTA4KJOvewbhnEVmgd | B248: added | C248: 400 | D248: Transfer, Debit | E248: 2023-10-29, 8:00:00 p.m. | F248: CAD | H248: e-Transfer sent PAULA ANDREA AMARILES RESTREPO 278R32 | I248: other | J248: FALSE | K248: xbwkYxX7zLT9rJvXa0a1swmEBLdAn0hOdw7vo | L248: =_xlfn.XLOOKUP(Transactions[[#This Row],[Account ID]],Accounts[Plaid Account ID],Accounts[Name],"Not Found",0) -> RBC Staff Banking | M248: =_xlfn.XLOOKUP(Transactions[[#This Row],[Account ID]],Accounts[Plaid Account ID],Accounts[Institution Name],"Not Found",0) -> RBC Royal Bank | N248: =IF(Transactions[[#This Row],[Amount]]<0,"credit","debit") -> debit | O248: {=IF( ISNUMBER(MATCH(Transactions[[#This Row],[Categories]], _xlfn._xlws.FILTER(Custom_Cat[Name], LEN(Custom_Cat[Name]) >= 3), 0)), INDEX(Custom_Cat[Custom Category], MATCH(Transactions[[#This Row],[Categories]], _xlfn._xlws.FILTER(Custom_Cat[Name], LEN(Custom_Cat[Name]) >= 3), 0)), IFERROR( INDEX( Custom_Cat[Custom Category], MATCH( 1, (ISNUMBER(SEARCH(LOWER(Custom_Cat[Name]), LOWER(Transactions[[#This Row],[Name]])))) * (LEN(Custom_Cat[Name]) >= 3) * ( (IF(LEFT(Custom_Cat[Amount],1)="<",Transactions[[#This Row],[Amount]]<VALUE(MID(Custom_Cat[Amount], 2, LEN(Custom_Cat[Amount])-1)),TRUE)) * (IF(LEFT(Custom_Cat[Amount],1)=">",Transactions[[#This Row],[Amount]]>VALUE(MID(Custom_Cat[Amount], 2, LEN(Custom_Cat[Amount])-1)),TRUE)) ), 0 ) ), Transactions[[#This Row],[Categories]] ) )} -> Transfer,Internal | P248: =DATE(LEFT(Transactions[[#This Row],[Date]],4),MID(Transactions[[#This Row],[Date]],6,2),MID(Transactions[[#This Row],[Date]],9,2))+IF(RIGHT(Transactions[[#This Row],[Date]],2)="pm",IF(MID(Transactions[[#This Row],[Date]],12,2)<12,0.5,0),IF(MID(Transactions[[#This Row],[Date]],12,2)=12,-0.5,0)) -> 45228 | Q248: =DATE(YEAR(Transactions[[#This Row],[Datetime]]),MONTH(Transactions[[#This Row],[Datetime]]),1) -> 45200 | R248: =AND(Transactions[[#This Row],[Datetime]]>=EDATE(MAX(Transactions[Datetime]),-6),Transactions[[#This Row],[Datetime]]<=TODAY()) -> FALSE | S248: =AVERAGEIFS(Transactions[Month''s Total],Transactions[Recent],TRUE,Transactions[Custom Category],Transactions[[#This Row],[Custom Category]]) -> 14532.99 | T248: =SUMIFS(Transactions[Amount],Transactions[Month],Transactions[[#This Row],[Month]],Transactions[Custom Category],Transactions[[#This Row],[Custom Category]]) -> 3947.82 | U248: =IF(COUNTIF(Budgets[Custom Category],Transactions[[#This Row],[Custom Category]])=0,Transactions[[#This Row],[6M AVG]],_xlfn.XLOOKUP(Transactions[[#This Row],[Custom Category]],Budgets[Custom Category],Budgets[Monthly],0,0)) -> 14532.99 | V248: =IF(Transactions[[#This Row],[Month]]=Sel_Month,Transactions[[#This Row],[Amount]],0) -> 0
A249: eOMxkwaqNZH7Vznj6o6XTA4KJOvewbhnEVmgd | B249: added | C249: 2000 | D249: Transfer, Debit | E249: 2023-10-31, 8:00:00 p.m. | F249: CAD | H249: e-Transfer sent Bridgeway 5RVK4S | I249: other | J249: FALSE | K249: kObx4qpAm9HOVm5g9D90iNbgweVADmHo5zkB9 | L249: =_xlfn.XLOOKUP(Transactions[[#This Row],[Account ID]],Accounts[Plaid Account ID],Accounts[Name],"Not Found",0) -> RBC Staff Banking | M249: =_xlfn.XLOOKUP(Transactions[[#This Row],[Account ID]],Accounts[Plaid Account ID],Accounts[Institution Name],"Not Found",0) -> RBC Royal Bank | N249: =IF(Transactions[[#This Row],[Amount]]<0,"credit","debit") -> debit | O249: {=IF( ISNUMBER(MATCH(Transactions[[#This Row],[Categories]], _xlfn._xlws.FILTER(Custom_Cat[Name], LEN(Custom_Cat[Name]) >= 3), 0)), INDEX(Custom_Cat[Custom Category], MATCH(Transactions[[#This Row],[Categories]], _xlfn._xlws.FILTER(Custom_Cat[Name], LEN(Custom_Cat[Name]) >= 3), 0)), IFERROR( INDEX( Custom_Cat[Custom Category], MATCH( 1, (ISNUMBER(SEARCH(LOWER(Custom_Cat[Name]), LOWER(Transactions[[#This Row],[Name]])))) * (LEN(Custom_Cat[Name]) >= 3) * ( (IF(LEFT(Custom_Cat[Amount],1)="<",Transactions[[#This Row],[Amount]]<VALUE(MID(Custom_Cat[Amount], 2, LEN(Custom_Cat[Amount])-1)),TRUE)) * (IF(LEFT(Custom_Cat[Amount],1)=">",Transactions[[#This Row],[Amount]]>VALUE(MID(Custom_Cat[Amount], 2, LEN(Custom_Cat[Amount])-1)),TRUE)) ), 0 ) ), Transactions[[#This Row],[Categories]] ) )} -> Rent | P249: =DATE(LEFT(Transactions[[#This Row],[Date]],4),MID(Transactions[[#This Row],[Date]],6,2),MID(Transactions[[#This Row],[Date]],9,2))+IF(RIGHT(Transactions[[#This Row],[Date]],2)="pm",IF(MID(Transactions[[#This Row],[Date]],12,2)<12,0.5,0),IF(MID(Transactions[[#This Row],[Date]],12,2)=12,-0.5,0)) -> 45230 | Q249: =DATE(YEAR(Transactions[[#This Row],[Datetime]]),MONTH(Transactions[[#This Row],[Datetime]]),1) -> 45200 | R249: =AND(Transactions[[#This Row],[Datetime]]>=EDATE(MAX(Transactions[Datetime]),-6),Transactions[[#This Row],[Datetime]]<=TODAY()) -> FALSE | S249: =AVERAGEIFS(Transactions[Month''s Total],Transactions[Recent],TRUE,Transactions[Custom Category],Transactions[[#This Row],[Custom Category]]) -> 5076 | T249: =SUMIFS(Transactions[Amount],Transactions[Month],Transactions[[#This Row],[Month]],Transactions[Custom Category],Transactions[[#This Row],[Custom Category]]) -> 2000 | U249: =IF(COUNTIF(Budgets[Custom Category],Transactions[[#This Row],[Custom Category]])=0,Transactions[[#This Row],[6M AVG]],_xlfn.XLOOKUP(Transactions[[#This Row],[Custom Category]],Budgets[Custom Category],Budgets[Monthly],0,0)) -> 5076 | V249: =IF(Transactions[[#This Row],[Month]]=Sel_Month,Transactions[[#This Row],[Amount]],0) -> 0
A250: eOMxkwaqNZH7Vznj6o6XTA4KJOvewbhnEVmgd | B250: added | C250: 0.96 | D250: Transfer, Debit | E250: 2023-10-31, 8:00:00 p.m. | F250: CAD | H250: e-Transfer sent Manuel Avila TD QKE8DT | I250: other | J250: FALSE | K250: AXN3ez01jbS3APoek4kdu09LwN1vAaCMVrm06 | L250: =_xlfn.XLOOKUP(Transactions[[#This Row],[Account ID]],Accounts[Plaid Account ID],Accounts[Name],"Not Found",0) -> RBC Staff Banking | M250: =_xlfn.XLOOKUP(Transactions[[#This Row],[Account ID]],Accounts[Plaid Account ID],Accounts[Institution Name],"Not Found",0) -> RBC Royal Bank | N250: =IF(Transactions[[#This Row],[Amount]]<0,"credit","debit") -> debit | O250: {=IF( ISNUMBER(MATCH(Transactions[[#This Row],[Categories]], _xlfn._xlws.FILTER(Custom_Cat[Name], LEN(Custom_Cat[Name]) >= 3), 0)), INDEX(Custom_Cat[Custom Category], MATCH(Transactions[[#This Row],[Categories]], _xlfn._xlws.FILTER(Custom_Cat[Name], LEN(Custom_Cat[Name]) >= 3), 0)), IFERROR( INDEX( Custom_Cat[Custom Category], MATCH( 1, (ISNUMBER(SEARCH(LOWER(Custom_Cat[Name]), LOWER(Transactions[[#This Row],[Name]])))) * (LEN(Custom_Cat[Name]) >= 3) * ( (IF(LEFT(Custom_Cat[Amount],1)="<",Transactions[[#This Row],[Amount]]<VALUE(MID(Custom_Cat[Amount], 2, LEN(Custom_Cat[Amount])-1)),TRUE)) * (IF(LEFT(Custom_Cat[Amount],1)=">",Transactions[[#This Row],[Amount]]>VALUE(MID(Custom_Cat[Amount], 2, LEN(Custom_Cat[Amount])-1)),TRUE)) ), 0 ) ), Transactions[[#This Row],[Categories]] ) )} -> Transfer,Internal | P250: =DATE(LEFT(Transactions[[#This Row],[Date]],4),MID(Transactions[[#This Row],[Date]],6,2),MID(Transactions[[#This Row],[Date]],9,2))+IF(RIGHT(Transactions[[#This Row],[Date]],2)="pm",IF(MID(Transactions[[#This Row],[Date]],12,2)<12,0.5,0),IF(MID(Transactions[[#This Row],[Date]],12,2)=12,-0.5,0)) -> 45230 | Q250: =DATE(YEAR(Transactions[[#This Row],[Datetime]]),MONTH(Transactions[[#This Row],[Datetime]]),1) -> 45200 | R250: =AND(Transactions[[#This Row],[Datetime]]>=EDATE(MAX(Transactions[Datetime]),-6),Transactions[[#This Row],[Datetime]]<=TODAY()) -> FALSE | S250: =AVERAGEIFS(Transactions[Month''s Total],Transactions[Recent],TRUE,Transactions[Custom Category],Transactions[[#This Row],[Custom Category]]) -> 14532.99 | T250: =SUMIFS(Transactions[Amount],Transactions[Month],Transactions[[#This Row],[Month]],Transactions[Custom Category],Transactions[[#This Row],[Custom Category]]) -> 3947.82 | U250: =IF(COUNTIF(Budgets[Custom Category],Transactions[[#This Row],[Custom Category]])=0,Transactions[[#This Row],[6M AVG]],_xlfn.XLOOKUP(Transactions[[#This Row],[Custom Category]],Budgets[Custom Category],Budgets[Monthly],0,0)) -> 14532.99 | V250: =IF(Transactions[[#This Row],[Month]]=Sel_Month,Transactions[[#This Row],[Amount]],0) -> 0
A251: eOMxkwaqNZH7Vznj6o6XTA4KJOvewbhnEVmgd | B251: added | C251: -1200 | D251: Transfer, Credit | E251: 2023-10-31, 8:00:00 p.m. | F251: CAD | H251: e-Transfer - Autodeposit David Alexander Garcia Hernandez C1AGNfrBdtnD | I251: other | J251: FALSE | K251: vbVy94p8zwTZVRYD787pCbvAOBy1zeFVZxwjV | L251: =_xlfn.XLOOKUP(Transactions[[#This Row],[Account ID]],Accounts[Plaid Account ID],Accounts[Name],"Not Found",0) -> RBC Staff Banking | M251: =_xlfn.XLOOKUP(Transactions[[#This Row],[Account ID]],Accounts[Plaid Account ID],Accounts[Institution Name],"Not Found",0) -> RBC Royal Bank | N251: =IF(Transactions[[#This Row],[Amount]]<0,"credit","debit") -> credit | O251: {=IF( ISNUMBER(MATCH(Transactions[[#This Row],[Categories]], _xlfn._xlws.FILTER(Custom_Cat[Name], LEN(Custom_Cat[Name]) >= 3), 0)), INDEX(Custom_Cat[Custom Category], MATCH(Transactions[[#This Row],[Categories]], _xlfn._xlws.FILTER(Custom_Cat[Name], LEN(Custom_Cat[Name]) >= 3), 0)), IFERROR( INDEX( Custom_Cat[Custom Category], MATCH( 1, (ISNUMBER(SEARCH(LOWER(Custom_Cat[Name]), LOWER(Transactions[[#This Row],[Name]])))) * (LEN(Custom_Cat[Name]) >= 3) * ( (IF(LEFT(Custom_Cat[Amount],1)="<",Transactions[[#This Row],[Amount]]<VALUE(MID(Custom_Cat[Amount], 2, LEN(Custom_Cat[Amount])-1)),TRUE)) * (IF(LEFT(Custom_Cat[Amount],1)=">",Transactions[[#This Row],[Amount]]>VALUE(MID(Custom_Cat[Amount], 2, LEN(Custom_Cat[Amount])-1)),TRUE)) ), 0 ) ), Transactions[[#This Row],[Categories]] ) )} -> Income,Repayment | P251: =DATE(LEFT(Transactions[[#This Row],[Date]],4),MID(Transactions[[#This Row],[Date]],6,2),MID(Transactions[[#This Row],[Date]],9,2))+IF(RIGHT(Transactions[[#This Row],[Date]],2)="pm",IF(MID(Transactions[[#This Row],[Date]],12,2)<12,0.5,0),IF(MID(Transactions[[#This Row],[Date]],12,2)=12,-0.5,0)) -> 45230 | Q251: =DATE(YEAR(Transactions[[#This Row],[Datetime]]),MONTH(Transactions[[#This Row],[Datetime]]),1) -> 45200 | R251: =AND(Transactions[[#This Row],[Datetime]]>=EDATE(MAX(Transactions[Datetime]),-6),Transactions[[#This Row],[Datetime]]<=TODAY()) -> FALSE | S251: =AVERAGEIFS(Transactions[Month''s Total],Transactions[Recent],TRUE,Transactions[Custom Category],Transactions[[#This Row],[Custom Category]]) -> -3209.0714 | T251: =SUMIFS(Transactions[Amount],Transactions[Month],Transactions[[#This Row],[Month]],Transactions[Custom Category],Transactions[[#This Row],[Custom Category]]) -> -4718 | U251: =IF(COUNTIF(Budgets[Custom Category],Transactions[[#This Row],[Custom Category]])=0,Transactions[[#This Row],[6M AVG]],_xlfn.XLOOKUP(Transactions[[#This Row],[Custom Category]],Budgets[Custom Category],Budgets[Monthly],0,0)) -> -3209.0714 | V251: =IF(Transactions[[#This Row],[Month]]=Sel_Month,Transactions[[#This Row],[Amount]],0) -> 0
A252: eOMxkwaqNZH7Vznj6o6XTA4KJOvewbhnEVmgd | B252: added | C252: -904 | D252: Transfer, Credit | E252: 2023-10-31, 8:00:00 p.m. | F252: CAD | H252: e-Transfer - Autodeposit DIANA-LORENA CORTES-RODRIGUEZ C1AgwHkSqHbk | I252: other | J252: FALSE | K252: 0XDrJpO173S7XKVnMwM4TZO9yeN74wCApZ6a9 | L252: =_xlfn.XLOOKUP(Transactions[[#This Row],[Account ID]],Accounts[Plaid Account ID],Accounts[Name],"Not Found",0) -> RBC Staff Banking | M252: =_xlfn.XLOOKUP(Transactions[[#This Row],[Account ID]],Accounts[Plaid Account ID],Accounts[Institution Name],"Not Found",0) -> RBC Royal Bank | N252: =IF(Transactions[[#This Row],[Amount]]<0,"credit","debit") -> credit | O252: {=IF( ISNUMBER(MATCH(Transactions[[#This Row],[Categories]], _xlfn._xlws.FILTER(Custom_Cat[Name], LEN(Custom_Cat[Name]) >= 3), 0)), INDEX(Custom_Cat[Custom Category], MATCH(Transactions[[#This Row],[Categories]], _xlfn._xlws.FILTER(Custom_Cat[Name], LEN(Custom_Cat[Name]) >= 3), 0)), IFERROR( INDEX( Custom_Cat[Custom Category], MATCH( 1, (ISNUMBER(SEARCH(LOWER(Custom_Cat[Name]), LOWER(Transactions[[#This Row],[Name]])))) * (LEN(Custom_Cat[Name]) >= 3) * ( (IF(LEFT(Custom_Cat[Amount],1)="<",Transactions[[#This Row],[Amount]]<VALUE(MID(Custom_Cat[Amount], 2, LEN(Custom_Cat[Amount])-1)),TRUE)) * (IF(LEFT(Custom_Cat[Amount],1)=">",Transactions[[#This Row],[Amount]]>VALUE(MID(Custom_Cat[Amount], 2, LEN(Custom_Cat[Amount])-1)),TRUE)) ), 0 ) ), Transactions[[#This Row],[Categories]] ) )} -> Income,Repayment | P252: =DATE(LEFT(Transactions[[#This Row],[Date]],4),MID(Transactions[[#This Row],[Date]],6,2),MID(Transactions[[#This Row],[Date]],9,2))+IF(RIGHT(Transactions[[#This Row],[Date]],2)="pm",IF(MID(Transactions[[#This Row],[Date]],12,2)<12,0.5,0),IF(MID(Transactions[[#This Row],[Date]],12,2)=12,-0.5,0)) -> 45230 | Q252: =DATE(YEAR(Transactions[[#This Row],[Datetime]]),MONTH(Transactions[[#This Row],[Datetime]]),1) -> 45200 | R252: =AND(Transactions[[#This Row],[Datetime]]>=EDATE(MAX(Transactions[Datetime]),-6),Transactions[[#This Row],[Datetime]]<=TODAY()) -> FALSE | S252: =AVERAGEIFS(Transactions[Month''s Total],Transactions[Recent],TRUE,Transactions[Custom Category],Transactions[[#This Row],[Custom Category]]) -> -3209.0714 | T252: =SUMIFS(Transactions[Amount],Transactions[Month],Transactions[[#This Row],[Month]],Transactions[Custom Category],Transactions[[#This Row],[Custom Category]]) -> -4718 | U252: =IF(COUNTIF(Budgets[Custom Category],Transactions[[#This Row],[Custom Category]])=0,Transactions[[#This Row],[6M AVG]],_xlfn.XLOOKUP(Transactions[[#This Row],[Custom Category]],Budgets[Custom Category],Budgets[Monthly],0,0)) -> -3209.0714 | V252: =IF(Transactions[[#This Row],[Month]]=Sel_Month,Transactions[[#This Row],[Amount]],0) -> 0
A253: eOMxkwaqNZH7Vznj6o6XTA4KJOvewbhnEVmgd | B253: added | C253: 192.58 | D253: Service, Financial, Loans and Mortgages | E253: 2023-11-02, 8:00:00 p.m. | F253: CAD | G253: Personal Loan Spl | H253: Personal Loan SPL | I253: online | J253: FALSE | K253: BXVyezjPrgSxXRna9M9wIa65QjPRpru3BPmkm | L253: =_xlfn.XLOOKUP(Transactions[[#This Row],[Account ID]],Accounts[Plaid Account ID],Accounts[Name],"Not Found",0) -> RBC Staff Banking | M253: =_xlfn.XLOOKUP(Transactions[[#This Row],[Account ID]],Accounts[Plaid Account ID],Accounts[Institution Name],"Not Found",0) -> RBC Royal Bank | N253: =IF(Transactions[[#This Row],[Amount]]<0,"credit","debit") -> debit | O253: {=IF( ISNUMBER(MATCH(Transactions[[#This Row],[Categories]], _xlfn._xlws.FILTER(Custom_Cat[Name], LEN(Custom_Cat[Name]) >= 3), 0)), INDEX(Custom_Cat[Custom Category], MATCH(Transactions[[#This Row],[Categories]], _xlfn._xlws.FILTER(Custom_Cat[Name], LEN(Custom_Cat[Name]) >= 3), 0)), IFERROR( INDEX( Custom_Cat[Custom Category], MATCH( 1, (ISNUMBER(SEARCH(LOWER(Custom_Cat[Name]), LOWER(Transactions[[#This Row],[Name]])))) * (LEN(Custom_Cat[Name]) >= 3) * ( (IF(LEFT(Custom_Cat[Amount],1)="<",Transactions[[#This Row],[Amount]]<VALUE(MID(Custom_Cat[Amount], 2, LEN(Custom_Cat[Amount])-1)),TRUE)) * (IF(LEFT(Custom_Cat[Amount],1)=">",Transactions[[#This Row],[Amount]]>VALUE(MID(Custom_Cat[Amount], 2, LEN(Custom_Cat[Amount])-1)),TRUE)) ), 0 ) ), Transactions[[#This Row],[Categories]] ) )} -> Loans,Car | P253: =DATE(LEFT(Transactions[[#This Row],[Date]],4),MID(Transactions[[#This Row],[Date]],6,2),MID(Transactions[[#This Row],[Date]],9,2))+IF(RIGHT(Transactions[[#This Row],[Date]],2)="pm",IF(MID(Transactions[[#This Row],[Date]],12,2)<12,0.5,0),IF(MID(Transactions[[#This Row],[Date]],12,2)=12,-0.5,0)) -> 45232 | Q253: =DATE(YEAR(Transactions[[#This Row],[Datetime]]),MONTH(Transactions[[#This Row],[Datetime]]),1) -> 45231 | R253: =AND(Transactions[[#This Row],[Datetime]]>=EDATE(MAX(Transactions[Datetime]),-6),Transactions[[#This Row],[Datetime]]<=TODAY()) -> FALSE | S253: =AVERAGEIFS(Transactions[Month''s Total],Transactions[Recent],TRUE,Transactions[Custom Category],Transactions[[#This Row],[Custom Category]]) -> 624.12818 | T253: =SUMIFS(Transactions[Amount],Transactions[Month],Transactions[[#This Row],[Month]],Transactions[Custom Category],Transactions[[#This Row],[Custom Category]]) -> 577.74 | U253: =IF(COUNTIF(Budgets[Custom Category],Transactions[[#This Row],[Custom Category]])=0,Transactions[[#This Row],[6M AVG]],_xlfn.XLOOKUP(Transactions[[#This Row],[Custom Category]],Budgets[Custom Category],Budgets[Monthly],0,0)) -> 624.12818 | V253: =IF(Transactions[[#This Row],[Month]]=Sel_Month,Transactions[[#This Row],[Amount]],0) -> 0
A254: eOMxkwaqNZH7Vznj6o6XTA4KJOvewbhnEVmgd | B254: added | C254: -245.35 | D254: Shops | E254: 2023-11-02, 8:00:00 p.m. | F254: CAD | H254: Misc Payment EBAY COMMERCE C | I254: other | J254: FALSE | K254: 3XqR5pwB6kSDXQKBzEzJcMaqRzJov7Io13XBR | L254: =_xlfn.XLOOKUP(Transactions[[#This Row],[Account ID]],Accounts[Plaid Account ID],Accounts[Name],"Not Found",0) -> RBC Staff Banking | M254: =_xlfn.XLOOKUP(Transactions[[#This Row],[Account ID]],Accounts[Plaid Account ID],Accounts[Institution Name],"Not Found",0) -> RBC Royal Bank | N254: =IF(Transactions[[#This Row],[Amount]]<0,"credit","debit") -> credit | O254: {=IF( ISNUMBER(MATCH(Transactions[[#This Row],[Categories]], _xlfn._xlws.FILTER(Custom_Cat[Name], LEN(Custom_Cat[Name]) >= 3), 0)), INDEX(Custom_Cat[Custom Category], MATCH(Transactions[[#This Row],[Categories]], _xlfn._xlws.FILTER(Custom_Cat[Name], LEN(Custom_Cat[Name]) >= 3), 0)), IFERROR( INDEX( Custom_Cat[Custom Category], MATCH( 1, (ISNUMBER(SEARCH(LOWER(Custom_Cat[Name]), LOWER(Transactions[[#This Row],[Name]])))) * (LEN(Custom_Cat[Name]) >= 3) * ( (IF(LEFT(Custom_Cat[Amount],1)="<",Transactions[[#This Row],[Amount]]<VALUE(MID(Custom_Cat[Amount], 2, LEN(Custom_Cat[Amount])-1)),TRUE)) * (IF(LEFT(Custom_Cat[Amount],1)=">",Transactions[[#This Row],[Amount]]>VALUE(MID(Custom_Cat[Amount], 2, LEN(Custom_Cat[Amount])-1)),TRUE)) ), 0 ) ), Transactions[[#This Row],[Categories]] ) )} -> Transfer,Internal | P254: =DATE(LEFT(Transactions[[#This Row],[Date]],4),MID(Transactions[[#This Row],[Date]],6,2),MID(Transactions[[#This Row],[Date]],9,2))+IF(RIGHT(Transactions[[#This Row],[Date]],2)="pm",IF(MID(Transactions[[#This Row],[Date]],12,2)<12,0.5,0),IF(MID(Transactions[[#This Row],[Date]],12,2)=12,-0.5,0)) -> 45232 | Q254: =DATE(YEAR(Transactions[[#This Row],[Datetime]]),MONTH(Transactions[[#This Row],[Datetime]]),1) -> 45231 | R254: =AND(Transactions[[#This Row],[Datetime]]>=EDATE(MAX(Transactions[Datetime]),-6),Transactions[[#This Row],[Datetime]]<=TODAY()) -> FALSE | S254: =AVERAGEIFS(Transactions[Month''s Total],Transactions[Recent],TRUE,Transactions[Custom Category],Transactions[[#This Row],[Custom Category]]) -> 14532.99 | T254: =SUMIFS(Transactions[Amount],Transactions[Month],Transactions[[#This Row],[Month]],Transactions[Custom Category],Transactions[[#This Row],[Custom Category]]) -> 1819.79 | U254: =IF(COUNTIF(Budgets[Custom Category],Transactions[[#This Row],[Custom Category]])=0,Transactions[[#This Row],[6M AVG]],_xlfn.XLOOKUP(Transactions[[#This Row],[Custom Category]],Budgets[Custom Category],Budgets[Monthly],0,0)) -> 14532.99 | V254: =IF(Transactions[[#This Row],[Month]]=Sel_Month,Transactions[[#This Row],[Amount]],0) -> 0
A255: eOMxkwaqNZH7Vznj6o6XTA4KJOvewbhnEVmgd | B255: added | C255: 74.12 | D255: Transfer, Debit | E255: 2023-11-02, 8:00:00 p.m. | F255: CAD | H255: Online Banking transfer - 0802 | I255: other | J255: FALSE | K255: yb6XYJp8zDT3z0Oj6P61uAR95LwZj7TpQewxK | L255: =_xlfn.XLOOKUP(Transactions[[#This Row],[Account ID]],Accounts[Plaid Account ID],Accounts[Name],"Not Found",0) -> RBC Staff Banking | M255: =_xlfn.XLOOKUP(Transactions[[#This Row],[Account ID]],Accounts[Plaid Account ID],Accounts[Institution Name],"Not Found",0) -> RBC Royal Bank | N255: =IF(Transactions[[#This Row],[Amount]]<0,"credit","debit") -> debit | O255: {=IF( ISNUMBER(MATCH(Transactions[[#This Row],[Categories]], _xlfn._xlws.FILTER(Custom_Cat[Name], LEN(Custom_Cat[Name]) >= 3), 0)), INDEX(Custom_Cat[Custom Category], MATCH(Transactions[[#This Row],[Categories]], _xlfn._xlws.FILTER(Custom_Cat[Name], LEN(Custom_Cat[Name]) >= 3), 0)), IFERROR( INDEX( Custom_Cat[Custom Category], MATCH( 1, (ISNUMBER(SEARCH(LOWER(Custom_Cat[Name]), LOWER(Transactions[[#This Row],[Name]])))) * (LEN(Custom_Cat[Name]) >= 3) * ( (IF(LEFT(Custom_Cat[Amount],1)="<",Transactions[[#This Row],[Amount]]<VALUE(MID(Custom_Cat[Amount], 2, LEN(Custom_Cat[Amount])-1)),TRUE)) * (IF(LEFT(Custom_Cat[Amount],1)=">",Transactions[[#This Row],[Amount]]>VALUE(MID(Custom_Cat[Amount], 2, LEN(Custom_Cat[Amount])-1)),TRUE)) ), 0 ) ), Transactions[[#This Row],[Categories]] ) )} -> Transfer, Debit | P255: =DATE(LEFT(Transactions[[#This Row],[Date]],4),MID(Transactions[[#This Row],[Date]],6,2),MID(Transactions[[#This Row],[Date]],9,2))+IF(RIGHT(Transactions[[#This Row],[Date]],2)="pm",IF(MID(Transactions[[#This Row],[Date]],12,2)<12,0.5,0),IF(MID(Transactions[[#This Row],[Date]],12,2)=12,-0.5,0)) -> 45232 | Q255: =DATE(YEAR(Transactions[[#This Row],[Datetime]]),MONTH(Transactions[[#This Row],[Datetime]]),1) -> 45231 | R255: =AND(Transactions[[#This Row],[Datetime]]>=EDATE(MAX(Transactions[Datetime]),-6),Transactions[[#This Row],[Datetime]]<=TODAY()) -> FALSE | S255: =AVERAGEIFS(Transactions[Month''s Total],Transactions[Recent],TRUE,Transactions[Custom Category],Transactions[[#This Row],[Custom Category]]) -> 12758.461 | T255: =SUMIFS(Transactions[Amount],Transactions[Month],Transactions[[#This Row],[Month]],Transactions[Custom Category],Transactions[[#This Row],[Custom Category]]) -> 114.12 | U255: =IF(COUNTIF(Budgets[Custom Category],Transactions[[#This Row],[Custom Category]])=0,Transactions[[#This Row],[6M AVG]],_xlfn.XLOOKUP(Transactions[[#This Row],[Custom Category]],Budgets[Custom Category],Budgets[Monthly],0,0)) -> 12758.461 | V255: =IF(Transactions[[#This Row],[Month]]=Sel_Month,Transactions[[#This Row],[Amount]],0) -> 0
A256: eOMxkwaqNZH7Vznj6o6XTA4KJOvewbhnEVmgd | B256: added | C256: 340.96 | D256: Transfer, Debit | E256: 2023-11-02, 8:00:00 p.m. | F256: CAD | H256: e-Transfer sent Manuel CIBC ZX426H | I256: other | J256: FALSE | K256: KYmvezN0bnso8Rk5dDdyTx4XOVejyKUE9aO7Z | L256: =_xlfn.XLOOKUP(Transactions[[#This Row],[Account ID]],Accounts[Plaid Account ID],Accounts[Name],"Not Found",0) -> RBC Staff Banking | M256: =_xlfn.XLOOKUP(Transactions[[#This Row],[Account ID]],Accounts[Plaid Account ID],Accounts[Institution Name],"Not Found",0) -> RBC Royal Bank | N256: =IF(Transactions[[#This Row],[Amount]]<0,"credit","debit") -> debit | O256: {=IF( ISNUMBER(MATCH(Transactions[[#This Row],[Categories]], _xlfn._xlws.FILTER(Custom_Cat[Name], LEN(Custom_Cat[Name]) >= 3), 0)), INDEX(Custom_Cat[Custom Category], MATCH(Transactions[[#This Row],[Categories]], _xlfn._xlws.FILTER(Custom_Cat[Name], LEN(Custom_Cat[Name]) >= 3), 0)), IFERROR( INDEX( Custom_Cat[Custom Category], MATCH( 1, (ISNUMBER(SEARCH(LOWER(Custom_Cat[Name]), LOWER(Transactions[[#This Row],[Name]])))) * (LEN(Custom_Cat[Name]) >= 3) * ( (IF(LEFT(Custom_Cat[Amount],1)="<",Transactions[[#This Row],[Amount]]<VALUE(MID(Custom_Cat[Amount], 2, LEN(Custom_Cat[Amount])-1)),TRUE)) * (IF(LEFT(Custom_Cat[Amount],1)=">",Transactions[[#This Row],[Amount]]>VALUE(MID(Custom_Cat[Amount], 2, LEN(Custom_Cat[Amount])-1)),TRUE)) ), 0 ) ), Transactions[[#This Row],[Categories]] ) )} -> Transfer,Internal | P256: =DATE(LEFT(Transactions[[#This Row],[Date]],4),MID(Transactions[[#This Row],[Date]],6,2),MID(Transactions[[#This Row],[Date]],9,2))+IF(RIGHT(Transactions[[#This Row],[Date]],2)="pm",IF(MID(Transactions[[#This Row],[Date]],12,2)<12,0.5,0),IF(MID(Transactions[[#This Row],[Date]],12,2)=12,-0.5,0)) -> 45232 | Q256: =DATE(YEAR(Transactions[[#This Row],[Datetime]]),MONTH(Transactions[[#This Row],[Datetime]]),1) -> 45231 | R256: =AND(Transactions[[#This Row],[Datetime]]>=EDATE(MAX(Transactions[Datetime]),-6),Transactions[[#This Row],[Datetime]]<=TODAY()) -> FALSE | S256: =AVERAGEIFS(Transactions[Month''s Total],Transactions[Recent],TRUE,Transactions[Custom Category],Transactions[[#This Row],[Custom Category]]) -> 14532.99 | T256: =SUMIFS(Transactions[Amount],Transactions[Month],Transactions[[#This Row],[Month]],Transactions[Custom Category],Transactions[[#This Row],[Custom Category]]) -> 1819.79 | U256: =IF(COUNTIF(Budgets[Custom Category],Transactions[[#This Row],[Custom Category]])=0,Transactions[[#This Row],[6M AVG]],_xlfn.XLOOKUP(Transactions[[#This Row],[Custom Category]],Budgets[Custom Category],Budgets[Monthly],0,0)) -> 14532.99 | V256: =IF(Transactions[[#This Row],[Month]]=Sel_Month,Transactions[[#This Row],[Amount]],0) -> 0
A257: eOMxkwaqNZH7Vznj6o6XTA4KJOvewbhnEVmgd | B257: added | C257: 111.64 | D257: Service, Utilities, Electric | E257: 2023-11-08, 7:00:00 p.m. | F257: CAD | G257: Hydro | H257: Hydro Bill Pmt TORONTO HYDRO | I257: online | J257: FALSE | K257: PpbjezRnN6TVNZrBQMQ0UYbVLx7r4zIo90L3Y | L257: =_xlfn.XLOOKUP(Transactions[[#This Row],[Account ID]],Accounts[Plaid Account ID],Accounts[Name],"Not Found",0) -> RBC Staff Banking | M257: =_xlfn.XLOOKUP(Transactions[[#This Row],[Account ID]],Accounts[Plaid Account ID],Accounts[Institution Name],"Not Found",0) -> RBC Royal Bank | N257: =IF(Transactions[[#This Row],[Amount]]<0,"credit","debit") -> debit | O257: {=IF( ISNUMBER(MATCH(Transactions[[#This Row],[Categories]], _xlfn._xlws.FILTER(Custom_Cat[Name], LEN(Custom_Cat[Name]) >= 3), 0)), INDEX(Custom_Cat[Custom Category], MATCH(Transactions[[#This Row],[Categories]], _xlfn._xlws.FILTER(Custom_Cat[Name], LEN(Custom_Cat[Name]) >= 3), 0)), IFERROR( INDEX( Custom_Cat[Custom Category], MATCH( 1, (ISNUMBER(SEARCH(LOWER(Custom_Cat[Name]), LOWER(Transactions[[#This Row],[Name]])))) * (LEN(Custom_Cat[Name]) >= 3) * ( (IF(LEFT(Custom_Cat[Amount],1)="<",Transactions[[#This Row],[Amount]]<VALUE(MID(Custom_Cat[Amount], 2, LEN(Custom_Cat[Amount])-1)),TRUE)) * (IF(LEFT(Custom_Cat[Amount],1)=">",Transactions[[#This Row],[Amount]]>VALUE(MID(Custom_Cat[Amount], 2, LEN(Custom_Cat[Amount])-1)),TRUE)) ), 0 ) ), Transactions[[#This Row],[Categories]] ) )} -> Utilities,Electric | P257: =DATE(LEFT(Transactions[[#This Row],[Date]],4),MID(Transactions[[#This Row],[Date]],6,2),MID(Transactions[[#This Row],[Date]],9,2))+IF(RIGHT(Transactions[[#This Row],[Date]],2)="pm",IF(MID(Transactions[[#This Row],[Date]],12,2)<12,0.5,0),IF(MID(Transactions[[#This Row],[Date]],12,2)=12,-0.5,0)) -> 45238 | Q257: =DATE(YEAR(Transactions[[#This Row],[Datetime]]),MONTH(Transactions[[#This Row],[Datetime]]),1) -> 45231 | R257: =AND(Transactions[[#This Row],[Datetime]]>=EDATE(MAX(Transactions[Datetime]),-6),Transactions[[#This Row],[Datetime]]<=TODAY()) -> FALSE | S257: =AVERAGEIFS(Transactions[Month''s Total],Transactions[Recent],TRUE,Transactions[Custom Category],Transactions[[#This Row],[Custom Category]]) -> 139.88333 | T257: =SUMIFS(Transactions[Amount],Transactions[Month],Transactions[[#This Row],[Month]],Transactions[Custom Category],Transactions[[#This Row],[Custom Category]]) -> 111.64 | U257: =IF(COUNTIF(Budgets[Custom Category],Transactions[[#This Row],[Custom Category]])=0,Transactions[[#This Row],[6M AVG]],_xlfn.XLOOKUP(Transactions[[#This Row],[Custom Category]],Budgets[Custom Category],Budgets[Monthly],0,0)) -> 139.88333 | V257: =IF(Transactions[[#This Row],[Month]]=Sel_Month,Transactions[[#This Row],[Amount]],0) -> 0
A258: eOMxkwaqNZH7Vznj6o6XTA4KJOvewbhnEVmgd | B258: added | C258: -753.14 | D258: Transfer, Credit | E258: 2023-11-08, 7:00:00 p.m. | F258: CAD | H258: Telephone Banking transfer Ref 091863135650660 | I258: other | J258: FALSE | K258: qbx15Ap8zQTerAqKYXY1SVoL9aNBdRIDdmRvw | L258: =_xlfn.XLOOKUP(Transactions[[#This Row],[Account ID]],Accounts[Plaid Account ID],Accounts[Name],"Not Found",0) -> RBC Staff Banking | M258: =_xlfn.XLOOKUP(Transactions[[#This Row],[Account ID]],Accounts[Plaid Account ID],Accounts[Institution Name],"Not Found",0) -> RBC Royal Bank | N258: =IF(Transactions[[#This Row],[Amount]]<0,"credit","debit") -> credit | O258: {=IF( ISNUMBER(MATCH(Transactions[[#This Row],[Categories]], _xlfn._xlws.FILTER(Custom_Cat[Name], LEN(Custom_Cat[Name]) >= 3), 0)), INDEX(Custom_Cat[Custom Category], MATCH(Transactions[[#This Row],[Categories]], _xlfn._xlws.FILTER(Custom_Cat[Name], LEN(Custom_Cat[Name]) >= 3), 0)), IFERROR( INDEX( Custom_Cat[Custom Category], MATCH( 1, (ISNUMBER(SEARCH(LOWER(Custom_Cat[Name]), LOWER(Transactions[[#This Row],[Name]])))) * (LEN(Custom_Cat[Name]) >= 3) * ( (IF(LEFT(Custom_Cat[Amount],1)="<",Transactions[[#This Row],[Amount]]<VALUE(MID(Custom_Cat[Amount], 2, LEN(Custom_Cat[Amount])-1)),TRUE)) * (IF(LEFT(Custom_Cat[Amount],1)=">",Transactions[[#This Row],[Amount]]>VALUE(MID(Custom_Cat[Amount], 2, LEN(Custom_Cat[Amount])-1)),TRUE)) ), 0 ) ), Transactions[[#This Row],[Categories]] ) )} -> Transfer, Credit | P258: =DATE(LEFT(Transactions[[#This Row],[Date]],4),MID(Transactions[[#This Row],[Date]],6,2),MID(Transactions[[#This Row],[Date]],9,2))+IF(RIGHT(Transactions[[#This Row],[Date]],2)="pm",IF(MID(Transactions[[#This Row],[Date]],12,2)<12,0.5,0),IF(MID(Transactions[[#This Row],[Date]],12,2)=12,-0.5,0)) -> 45238 | Q258: =DATE(YEAR(Transactions[[#This Row],[Datetime]]),MONTH(Transactions[[#This Row],[Datetime]]),1) -> 45231 | R258: =AND(Transactions[[#This Row],[Datetime]]>=EDATE(MAX(Transactions[Datetime]),-6),Transactions[[#This Row],[Datetime]]<=TODAY()) -> FALSE | S258: =AVERAGEIFS(Transactions[Month''s Total],Transactions[Recent],TRUE,Transactions[Custom Category],Transactions[[#This Row],[Custom Category]]) -> -333.34667 | T258: =SUMIFS(Transactions[Amount],Transactions[Month],Transactions[[#This Row],[Month]],Transactions[Custom Category],Transactions[[#This Row],[Custom Category]]) -> -5808.97 | U258: =IF(COUNTIF(Budgets[Custom Category],Transactions[[#This Row],[Custom Category]])=0,Transactions[[#This Row],[6M AVG]],_xlfn.XLOOKUP(Transactions[[#This Row],[Custom Category]],Budgets[Custom Category],Budgets[Monthly],0,0)) -> -333.34667 | V258: =IF(Transactions[[#This Row],[Month]]=Sel_Month,Transactions[[#This Row],[Amount]],0) -> 0
